Workbook

Sheet dashboard
A1: Sales Ops KPI Dashboard
A2: Use this tab to explain the operational story in an interview.
A3: KPI | B3: Value | C3: Interpretation
A4: CRM Gross Sales | B4: =reconciliation_summary!B4 -> 472328.52 | C4: CRM order demand
A5: ERP Invoice Amount | B5: =reconciliation_summary!B5 -> 429804.52 | C5: Invoiced revenue
A6: Variance | B6: =reconciliation_summary!B6 -> -42524 | C6: Difference needing review
A7: Open Exceptions | B7: =reconciliation_summary!B9 -> 934 | C7: Backlog count
A8: Critical Exceptions | B8: =reconciliation_summary!B10 -> 116 | C8: Highest-risk items
A9: Inventory Short Orders | B9: =reconciliation_summary!B11 -> 24 | C9: Fulfillment risk
A10: Orphan ERP Invoices | B10: =reconciliation_summary!B14 -> 5 | C10: ERP/data integrity risk
A13: Enterprise Realism Add-ons
A14: OTIF % | B14: =sla_metrics!B5 -> 0.21755725 | C14: Shipment performance
A15: Open Compliance Holds | B15: =sla_metrics!B8 -> 238 | C15: Regulatory / fulfillment blockers
A16: Credit Hold Recommendations | B16: =sla_metrics!B9 -> 93 | C16: AR risk
A17: Support SLA Breaches | B17: =sla_metrics!B7 -> 268 | C17: Customer support backlog
A18: Orphan ERP Invoices | B18: =reconciliation_summary!B14 -> 5 | C18: ERP/data integrity risk

Sheet executive_summary
A1: Executive Summary
A2: Plain-English narrative layer for an interview or portfolio walkthrough.
A3: Section | B3: Narrative
A4: Revenue readiness | B4: CRM demand, ERP invoices, credit memos, and AR aging should be reviewed together before publishing revenue-facing reporting. The workbook intentionally includes partial invoices, orphan invoices, credits, and timing gaps.
A5: Fulfillment risk | B5: Warehouse shipments now allow OTIF, short-ship, and hours-to-ship analysis. Use these to explain whether missed sales are demand issues or execution constraints.
A6: Compliance risk | B6: State-specific compliance review flags expired licenses, missing manifests, and restricted SKUs. This is especially relevant in regulated CPG/cannabis-style operations.
A7: Customer impact | B7: Support cases connect operational failures to customer-facing issues like invoice mismatches, late shipments, and damaged/refused deliveries.
A8: Cash impact | B8: Accounts receivable aging highlights invoices that are not just operationally complete but financially unresolved. Credit-hold recommendations help connect Sales Ops to Finance.
A9: Recommended next action | B9: Prioritize Critical compliance holds, orphan invoices, SLA-breached support cases, and AR balances in 61-90 or 90+ aging buckets before treating the period as clean.

Sheet crm_orders
A1: order_id | B1: order_date | C1: customer_id | D1: customer_name | E1: state | F1: sales_rep | G1: channel | H1: sku | I1: product_name | J1: qty_ordered | K1: unit_price | L1: gross_sales | M1: crm_status | N1: requested_ship_date | O1: available_inventory | P1: inventory_flag | Q1: duplicate_order_flag | R1: missing_key_flag | S1: order_value_band
A2: ORD000372 | B2: 46038 | D2: =IFERROR(VLOOKUP(C2,customer_lookup!$A:$E,2,FALSE),"") | E2: =IFERROR(VLOOKUP(C2,customer_lookup!$A:$E,3,FALSE),"") | F2: =IFERROR(VLOOKUP(C2,customer_lookup!$A:$E,5,FALSE),"") | G2: Wholesale | H2: SKU0019 | I2: =IFERROR(VLOOKUP(H2,product_lookup!$A:$D,2,FALSE),"") -> Cranberry Sparkling Beverage | J2: 60 | K2: 7.68 | L2: =J2*K2 -> 460.8 | M2: Fulfilled | N2: 46046 | O2: =SUMIF(inventory_snapshot!$B:$B,H2,inventory_snapshot!$E:$E) -> 1152 | P2: =IF(O2<J2,"Short","OK") -> OK | Q2: =IF(COUNTIF($A:$A,A2)>1,"Duplicate","OK") -> OK | R2: =IF(OR(C2="",H2=""),"Missing Key","OK") -> Missing Key | S2: =IF(L2>=1000,"Large",IF(L2>=500,"Medium","Small")) -> Small
A3: ORD000730 | B3: 46100 | D3: =IFERROR(VLOOKUP(C3,customer_lookup!$A:$E,2,FALSE),"") | E3: =IFERROR(VLOOKUP(C3,customer_lookup!$A:$E,3,FALSE),"") | F3: =IFERROR(VLOOKUP(C3,customer_lookup!$A:$E,5,FALSE),"") | G3: Retail | H3: SKU0012 | I3: =IFERROR(VLOOKUP(H3,product_lookup!$A:$D,2,FALSE),"") -> Sour Apple THC Gummies | J3: 120 | K3: 11.48 | L3: =J3*K3 -> 1377.6 | M3: Fulfilled | N3: 46101 | O3: =SUMIF(inventory_snapshot!$B:$B,H3,inventory_snapshot!$E:$E) -> 775 | P3: =IF(O3<J3,"Short","OK") -> OK | Q3: =IF(COUNTIF($A:$A,A3)>1,"Duplicate","OK") -> OK | R3: =IF(OR(C3="",H3=""),"Missing Key","OK") -> Missing Key | S3: =IF(L3>=1000,"Large",IF(L3>=500,"Medium","Small")) -> Large
A4: ORD000028 | B4: 46124 | C4: DSP0078 | D4: =IFERROR(VLOOKUP(C4,customer_lookup!$A:$E,2,FALSE),"") -> NV Account 0078 | E4: =IFERROR(VLOOKUP(C4,customer_lookup!$A:$E,3,FALSE),"") -> NV | F4: =IFERROR(VLOOKUP(C4,customer_lookup!$A:$E,5,FALSE),"") -> Alex | G4: Wholesale | H4: SKU0020 | I4: =IFERROR(VLOOKUP(H4,product_lookup!$A:$D,2,FALSE),"") -> Pineapple Sparkling Beverage | J4: 96 | K4: 7.32 | L4: =J4*K4 -> 702.72 | M4: Fulfilled | N4: 46132 | O4: =SUMIF(inventory_snapshot!$B:$B,H4,inventory_snapshot!$E:$E) -> 1145 | P4: =IF(O4<J4,"Short","OK") -> OK | Q4: =IF(COUNTIF($A:$A,A4)>1,"Duplicate","OK") -> OK | R4: =IF(OR(C4="",H4=""),"Missing Key","OK") -> OK | S4: =IF(L4>=1000,"Large",IF(L4>=500,"Medium","Small")) -> Medium
A5: ORD000034 | B5: 46033 | C5: DSP0064 | D5: =IFERROR(VLOOKUP(C5,customer_lookup!$A:$E,2,FALSE),"") -> CO Account 0064 | E5: =IFERROR(VLOOKUP(C5,customer_lookup!$A:$E,3,FALSE),"") -> CO | F5: =IFERROR(VLOOKUP(C5,customer_lookup!$A:$E,5,FALSE),"") -> Alex | G5: Wholesale | H5: SKU0015 | I5: =IFERROR(VLOOKUP(H5,product_lookup!$A:$D,2,FALSE),"") -> Strawberry 20:1 Gummies | J5: 96 | K5: 10.44 | L5: =J5*K5 -> 1002.24 | M5: Pending | N5: 46038 | O5: =SUMIF(inventory_snapshot!$B:$B,H5,inventory_snapshot!$E:$E) -> 2294 | P5: =IF(O5<J5,"Short","OK") -> OK | Q5: =IF(COUNTIF($A:$A,A5)>1,"Duplicate","OK") -> OK | R5: =IF(OR(C5="",H5=""),"Missing Key","OK") -> OK | S5: =IF(L5>=1000,"Large",IF(L5>=500,"Medium","Small")) -> Large
A6: ORD000042 | B6: 46105 | C6: DSP0060 | D6: =IFERROR(VLOOKUP(C6,customer_lookup!$A:$E,2,FALSE),"") -> OK Account 0060 | E6: =IFERROR(VLOOKUP(C6,customer_lookup!$A:$E,3,FALSE),"") -> OK | F6: =IFERROR(VLOOKUP(C6,customer_lookup!$A:$E,5,FALSE),"") -> Alex | G6: Wholesale | H6: SKU0004 | I6: =IFERROR(VLOOKUP(H6,product_lookup!$A:$D,2,FALSE),"") -> Grapefruit 1:1:1 Gummies | J6: 18 | K6: 10.75 | L6: =J6*K6 -> 193.5 | M6: Fulfilled | N6: 46110 | O6: =SUMIF(inventory_snapshot!$B:$B,H6,inventory_snapshot!$E:$E) -> 1751 | P6: =IF(O6<J6,"Short","OK") -> OK | Q6: =IF(COUNTIF($A:$A,A6)>1,"Duplicate","OK") -> OK | R6: =IF(OR(C6="",H6=""),"Missing Key","OK") -> OK | S6: =IF(L6>=1000,"Large",IF(L6>=500,"Medium","Small")) -> Small
A7: ORD000076 | B7: 46114 | C7: DSP0075 | D7: =IFERROR(VLOOKUP(C7,customer_lookup!$A:$E,2,FALSE),"") -> CA Account 0075 | E7: =IFERROR(VLOOKUP(C7,customer_lookup!$A:$E,3,FALSE),"") -> CA | F7: =IFERROR(VLOOKUP(C7,customer_lookup!$A:$E,5,FALSE),"") -> Alex | G7: Wholesale | H7: SKU0018 | I7: =IFERROR(VLOOKUP(H7,product_lookup!$A:$D,2,FALSE),"") -> Lemon Sparkling Beverage | J7: 36 | K7: 7.08 | L7: =J7*K7 -> 254.88 | M7: Fulfilled | N7: 46123 | O7: =SUMIF(inventory_snapshot!$B:$B,H7,inventory_snapshot!$E:$E) -> 1360 | P7: =IF(O7<J7,"Short","OK") -> OK | Q7: =IF(COUNTIF($A:$A,A7)>1,"Duplicate","OK") -> OK | R7: =IF(OR(C7="",H7=""),"Missing Key","OK") -> OK | S7: =IF(L7>=1000,"Large",IF(L7>=500,"Medium","Small")) -> Small
A8: ORD000087 | B8: 46079 | C8: DSP0063 | D8: =IFERROR(VLOOKUP(C8,customer_lookup!$A:$E,2,FALSE),"") -> CA Account 0063 | E8: =IFERROR(VLOOKUP(C8,customer_lookup!$A:$E,3,FALSE),"") -> CA | F8: =IFERROR(VLOOKUP(C8,customer_lookup!$A:$E,5,FALSE),"") -> Alex | G8: Wholesale | H8: SKU0020 | I8: =IFERROR(VLOOKUP(H8,product_lookup!$A:$D,2,FALSE),"") -> Pineapple Sparkling Beverage | J8: 48 | K8: 7.4 | L8: =J8*K8 -> 355.2 | M8: Fulfilled | N8: 46086 | O8: =SUMIF(inventory_snapshot!$B:$B,H8,inventory_snapshot!$E:$E) -> 1145 | P8: =IF(O8<J8,"Short","OK") -> OK | Q8: =IF(COUNTIF($A:$A,A8)>1,"Duplicate","OK") -> OK | R8: =IF(OR(C8="",H8=""),"Missing Key","OK") -> OK | S8: =IF(L8>=1000,"Large",IF(L8>=500,"Medium","Small")) -> Small
A9: ORD000103 | B9: 46140 | C9: DSP0075 | D9: =IFERROR(VLOOKUP(C9,customer_lookup!$A:$E,2,FALSE),"") -> CA Account 0075 | E9: =IFERROR(VLOOKUP(C9,customer_lookup!$A:$E,3,FALSE),"") -> CA | F9: =IFERROR(VLOOKUP(C9,customer_lookup!$A:$E,5,FALSE),"") -> Alex | G9: Retail | H9: SKU0005 | I9: =IFERROR(VLOOKUP(H9,product_lookup!$A:$D,2,FALSE),"") -> Huckleberry THC Gummies | J9: 36 | K9: 9.86 | L9: =J9*K9 -> 354.96 | M9: Fulfilled | N9: 46143 | O9: =SUMIF(inventory_snapshot!$B:$B,H9,inventory_snapshot!$E:$E) -> 1841 | P9: =IF(O9<J9,"Short","OK") -> OK | Q9: =IF(COUNTIF($A:$A,A9)>1,"Duplicate","OK") -> OK | R9: =IF(OR(C9="",H9=""),"Missing Key","OK") -> OK | S9: =IF(L9>=1000,"Large",IF(L9>=500,"Medium","Small")) -> Small
A10: ORD000104 | B10: 46071 | C10: DSP0040 | D10: =IFERROR(VLOOKUP(C10,customer_lookup!$A:$E,2,FALSE),"") -> CO Account 0040 | E10: =IFERROR(VLOOKUP(C10,customer_lookup!$A:$E,3,FALSE),"") -> CO | F10: =IFERROR(VLOOKUP(C10,customer_lookup!$A:$E,5,FALSE),"") -> Alex | G10: Retail | H10: SKU0018 | I10: =IFERROR(VLOOKUP(H10,product_lookup!$A:$D,2,FALSE),"") -> Lemon Sparkling Beverage | J10: 120 | K10: 7.67 | L10: =J10*K10 -> 920.4 | M10: Fulfilled | N10: 46080 | O10: =SUMIF(inventory_snapshot!$B:$B,H10,inventory_snapshot!$E:$E) -> 1360 | P10: =IF(O10<J10,"Short","OK") -> OK | Q10: =IF(COUNTIF($A:$A,A10)>1,"Duplicate","OK") -> OK | R10: =IF(OR(C10="",H10=""),"Missing Key","OK") -> OK | S10: =IF(L10>=1000,"Large",IF(L10>=500,"Medium","Small")) -> Medium
A11: ORD000156 | B11: 46044 | C11: DSP0075 | D11: =IFERROR(VLOOKUP(C11,customer_lookup!$A:$E,2,FALSE),"") -> CA Account 0075 | E11: =IFERROR(VLOOKUP(C11,customer_lookup!$A:$E,3,FALSE),"") -> CA | F11: =IFERROR(VLOOKUP(C11,customer_lookup!$A:$E,5,FALSE),"") -> Alex | G11: Distributor | H11: SKU0016 | I11: =IFERROR(VLOOKUP(H11,product_lookup!$A:$D,2,FALSE),"") -> Blackberry Sparkling Beverage | J11: 72 | K11: 7.69 | L11: =J11*K11 -> 553.68 | M11: Fulfilled | N11: 46047 | O11: =SUMIF(inventory_snapshot!$B:$B,H11,inventory_snapshot!$E:$E) -> 1292 | P11: =IF(O11<J11,"Short","OK") -> OK | Q11: =IF(COUNTIF($A:$A,A11)>1,"Duplicate","OK") -> OK | R11: =IF(OR(C11="",H11=""),"Missing Key","OK") -> OK | S11: =IF(L11>=1000,"Large",IF(L11>=500,"Medium","Small")) -> Medium
A12: ORD000161 | B12: 46084 | C12: DSP0063 | D12: =IFERROR(VLOOKUP(C12,customer_lookup!$A:$E,2,FALSE),"") -> CA Account 0063 | E12: =IFERROR(VLOOKUP(C12,customer_lookup!$A:$E,3,FALSE),"") -> CA | F12: =IFERROR(VLOOKUP(C12,customer_lookup!$A:$E,5,FALSE),"") -> Alex | G12: Retail | H12: SKU0011 | I12: =IFERROR(VLOOKUP(H12,product_lookup!$A:$D,2,FALSE),"") -> Raspberry THC Gummies | J12: 36 | K12: 10.63 | L12: =J12*K12 -> 382.68 | M12: Partial | N12: 46089 | O12: =SUMIF(inventory_snapshot!$B:$B,H12,inventory_snapshot!$E:$E) -> 1417 | P12: =IF(O12<J12,"Short","OK") -> OK | Q12: =IF(COUNTIF($A:$A,A12)>1,"Duplicate","OK") -> OK | R12: =IF(OR(C12="",H12=""),"Missing Key","OK") -> OK | S12: =IF(L12>=1000,"Large",IF(L12>=500,"Medium","Small")) -> Small
A13: ORD000189 | B13: 46067 | C13: DSP0064 | D13: =IFERROR(VLOOKUP(C13,customer_lookup!$A:$E,2,FALSE),"") -> CO Account 0064 | E13: =IFERROR(VLOOKUP(C13,customer_lookup!$A:$E,3,FALSE),"") -> CO | F13: =IFERROR(VLOOKUP(C13,customer_lookup!$A:$E,5,FALSE),"") -> Alex | G13: Wholesale | H13: SKU0002 | I13: =IFERROR(VLOOKUP(H13,product_lookup!$A:$D,2,FALSE),"") -> Boysenberry 1:1:1 Gummies | J13: 120 | K13: 10.86 | L13: =J13*K13 -> 1303.2 | M13: Fulfilled | N13: 46074 | O13: =SUMIF(inventory_snapshot!$B:$B,H13,inventory_snapshot!$E:$E) -> 2007 | P13: =IF(O13<J13,"Short","OK") -> OK | Q13: =IF(COUNTIF($A:$A,A13)>1,"Duplicate","OK") -> OK | R13: =IF(OR(C13="",H13=""),"Missing Key","OK") -> OK | S13: =IF(L13>=1000,"Large",IF(L13>=500,"Medium","Small")) -> Large
A14: ORD000196 | B14: 46125 | C14: DSP0060 | D14: =IFERROR(VLOOKUP(C14,customer_lookup!$A:$E,2,FALSE),"") -> OK Account 0060 | E14: =IFERROR(VLOOKUP(C14,customer_lookup!$A:$E,3,FALSE),"") -> OK | F14: =IFERROR(VLOOKUP(C14,customer_lookup!$A:$E,5,FALSE),"") -> Alex | G14: Wholesale | H14: SKU0004 | I14: =IFERROR(VLOOKUP(H14,product_lookup!$A:$D,2,FALSE),"") -> Grapefruit 1:1:1 Gummies | J14: 60 | K14: 11.31 | L14: =J14*K14 -> 678.6 | M14: Approved | N14: 46131 | O14: =SUMIF(inventory_snapshot!$B:$B,H14,inventory_snapshot!$E:$E) -> 1751 | P14: =IF(O14<J14,"Short","OK") -> OK | Q14: =IF(COUNTIF($A:$A,A14)>1,"Duplicate","OK") -> OK | R14: =IF(OR(C14="",H14=""),"Missing Key","OK") -> OK | S14: =IF(L14>=1000,"Large",IF(L14>=500,"Medium","Small")) -> Medium
A15: ORD000211 | B15: 46099 | C15: DSP0078 | D15: =IFERROR(VLOOKUP(C15,customer_lookup!$A:$E,2,FALSE),"") -> NV Account 0078 | E15: =IFERROR(VLOOKUP(C15,customer_lookup!$A:$E,3,FALSE),"") -> NV | F15: =IFERROR(VLOOKUP(C15,customer_lookup!$A:$E,5,FALSE),"") -> Alex | G15: Wholesale | H15: SKU0020 | I15: =IFERROR(VLOOKUP(H15,product_lookup!$A:$D,2,FALSE),"") -> Pineapple Sparkling Beverage | J15: 48 | K15: 8.48 | L15: =J15*K15 -> 407.04 | M15: Approved | N15: 46107 | O15: =SUMIF(inventory_snapshot!$B:$B,H15,inventory_snapshot!$E:$E) -> 1145 | P15: =IF(O15<J15,"Short","OK") -> OK | Q15: =IF(COUNTIF($A:$A,A15)>1,"Duplicate","OK") -> OK | R15: =IF(OR(C15="",H15=""),"Missing Key","OK") -> OK | S15: =IF(L15>=1000,"Large",IF(L15>=500,"Medium","Small")) -> Small
... A172: ORD000935 | B172: 46051 | C172: DSP0117 | D172: =IFERROR(VLOOKUP(C172,customer_lookup!$A:$E,2,FALSE),"") -> MO Account 0117 | E172: =IFERROR(VLOOKUP(C172,customer_lookup!$A:$E,3,FALSE),"") -> MO | F172: =IFERROR(VLOOKUP(C172,customer_lookup!$A:$E,5,FALSE),"") -> Avery | G172: Wholesale | H172: SKU0017 | I172: =IFERROR(VLOOKUP(H172,product_lookup!$A:$D,2,FALSE),"") -> Mango Sparkling Beverage | J172: 6 | K172: 7.63 | L172: =J172*K172 -> 45.78 | M172: Partial | N172: 46053 | O172: =SUMIF(inventory_snapshot!$B:$B,H172,inventory_snapshot!$E:$E) -> 1502 | P172: =IF(O172<J172,"Short","OK") -> OK | Q172: =IF(COUNTIF($A:$A,A172)>1,"Duplicate","OK") -> OK | R172: =IF(OR(C172="",H172=""),"Missing Key","OK") -> OK | S172: =IF(L172>=1000,"Large",IF(L172>=500,"Medium","Small")) -> Small
A173: ORD000938 | B173: 46119 | C173: DSP0084 | D173: =IFERROR(VLOOKUP(C173,customer_lookup!$A:$E,2,FALSE),"") -> OK Account 0084 | E173: =IFERROR(VLOOKUP(C173,customer_lookup!$A:$E,3,FALSE),"") -> OK | F173: =IFERROR(VLOOKUP(C173,customer_lookup!$A:$E,5,FALSE),"") -> Avery | G173: Wholesale | I173: =IFERROR(VLOOKUP(H173,product_lookup!$A:$D,2,FALSE),"") | J173: 24 | K173: 11.75 | L173: =J173*K173 -> 282 | M173: Partial | N173: 46129 | O173: =SUMIF(inventory_snapshot!$B:$B,H173,inventory_snapshot!$E:$E) -> 0 | P173: =IF(O173<J173,"Short","OK") -> Short | Q173: =IF(COUNTIF($A:$A,A173)>1,"Duplicate","OK") -> OK | R173: =IF(OR(C173="",H173=""),"Missing Key","OK") -> Missing Key | S173: =IF(L173>=1000,"Large",IF(L173>=500,"Medium","Small")) -> Small
A174: ORD000940 | B174: 46087 | C174: DSP0011 | D174: =IFERROR(VLOOKUP(C174,customer_lookup!$A:$E,2,FALSE),"") -> NY Account 0011 | E174: =IFERROR(VLOOKUP(C174,customer_lookup!$A:$E,3,FALSE),"") -> NY | F174: =IFERROR(VLOOKUP(C174,customer_lookup!$A:$E,5,FALSE),"") -> Avery | G174: Wholesale | H174: SKU0004 | I174: =IFERROR(VLOOKUP(H174,product_lookup!$A:$D,2,FALSE),"") -> Grapefruit 1:1:1 Gummies | J174: 30 | K174: 10.46 | L174: =J174*K174 -> 313.8 | M174: Fulfilled | N174: 46088 | O174: =SUMIF(inventory_snapshot!$B:$B,H174,inventory_snapshot!$E:$E) -> 1751 | P174: =IF(O174<J174,"Short","OK") -> OK | Q174: =IF(COUNTIF($A:$A,A174)>1,"Duplicate","OK") -> OK | R174: =IF(OR(C174="",H174=""),"Missing Key","OK") -> OK | S174: =IF(L174>=1000,"Large",IF(L174>=500,"Medium","Small")) -> Small
A175: ORD000967 | B175: 46029 | C175: DSP0099 | D175: =IFERROR(VLOOKUP(C175,customer_lookup!$A:$E,2,FALSE),"") -> CA Account 0099 | E175: =IFERROR(VLOOKUP(C175,customer_lookup!$A:$E,3,FALSE),"") -> CA | F175: =IFERROR(VLOOKUP(C175,customer_lookup!$A:$E,5,FALSE),"") -> Avery | G175: Wholesale | H175: SKU0008 | I175: =IFERROR(VLOOKUP(H175,product_lookup!$A:$D,2,FALSE),"") -> Peach 2:1 Gummies | J175: 36 | K175: 10.6 | L175: =J175*K175 -> 381.6 | M175: Fulfilled | N175: 46037 | O175: =SUMIF(inventory_snapshot!$B:$B,H175,inventory_snapshot!$E:$E) -> 1732 | P175: =IF(O175<J175,"Short","OK") -> OK | Q175: =IF(COUNTIF($A:$A,A175)>1,"Duplicate","OK") -> OK | R175: =IF(OR(C175="",H175=""),"Missing Key","OK") -> OK | S175: =IF(L175>=1000,"Large",IF(L175>=500,"Medium","Small")) -> Small
A176: ORD000973 | B176: 46035 | C176: DSP0117 | D176: =IFERROR(VLOOKUP(C176,customer_lookup!$A:$E,2,FALSE),"") -> MO Account 0117 | E176: =IFERROR(VLOOKUP(C176,customer_lookup!$A:$E,3,FALSE),"") -> MO | F176: =IFERROR(VLOOKUP(C176,customer_lookup!$A:$E,5,FALSE),"") -> Avery | G176: Wholesale | H176: SKU0020 | I176: =IFERROR(VLOOKUP(H176,product_lookup!$A:$D,2,FALSE),"") -> Pineapple Sparkling Beverage | J176: 30 | K176: 8.44 | L176: =J176*K176 -> 253.2 | M176: Approved | N176: 46037 | O176: =SUMIF(inventory_snapshot!$B:$B,H176,inventory_snapshot!$E:$E) -> 1145 | P176: =IF(O176<J176,"Short","OK") -> OK | Q176: =IF(COUNTIF($A:$A,A176)>1,"Duplicate","OK") -> OK | R176: =IF(OR(C176="",H176=""),"Missing Key","OK") -> OK | S176: =IF(L176>=1000,"Large",IF(L176>=500,"Medium","Small")) -> Small
A177: ORD000974 | B177: 46065 | C177: DSP0099 | D177: =IFERROR(VLOOKUP(C177,customer_lookup!$A:$E,2,FALSE),"") -> CA Account 0099 | E177: =IFERROR(VLOOKUP(C177,customer_lookup!$A:$E,3,FALSE),"") -> CA | F177: =IFERROR(VLOOKUP(C177,customer_lookup!$A:$E,5,FALSE),"") -> Avery | G177: Wholesale | H177: SKU0005 | I177: =IFERROR(VLOOKUP(H177,product_lookup!$A:$D,2,FALSE),"") -> Huckleberry THC Gummies | J177: 36 | K177: 10.75 | L177: =J177*K177 -> 387 | M177: Fulfilled | N177: 46069 | O177: =SUMIF(inventory_snapshot!$B:$B,H177,inventory_snapshot!$E:$E) -> 1841 | P177: =IF(O177<J177,"Short","OK") -> OK | Q177: =IF(COUNTIF($A:$A,A177)>1,"Duplicate","OK") -> OK | R177: =IF(OR(C177="",H177=""),"Missing Key","OK") -> OK | S177: =IF(L177>=1000,"Large",IF(L177>=500,"Medium","Small")) -> Small
A178: ORD000980 | B178: 46074 | C178: DSP0072 | D178: =IFERROR(VLOOKUP(C178,customer_lookup!$A:$E,2,FALSE),"") -> OK Account 0072 | E178: =IFERROR(VLOOKUP(C178,customer_lookup!$A:$E,3,FALSE),"") -> OK | F178: =IFERROR(VLOOKUP(C178,customer_lookup!$A:$E,5,FALSE),"") -> Avery | G178: Wholesale | H178: SKU0013 | I178: =IFERROR(VLOOKUP(H178,product_lookup!$A:$D,2,FALSE),"") -> Sour Cherry THC Gummies | J178: 24 | K178: 10.07 | L178: =J178*K178 -> 241.68 | M178: Approved | N178: 46075 | O178: =SUMIF(inventory_snapshot!$B:$B,H178,inventory_snapshot!$E:$E) -> 1313 | P178: =IF(O178<J178,"Short","OK") -> OK | Q178: =IF(COUNTIF($A:$A,A178)>1,"Duplicate","OK") -> OK | R178: =IF(OR(C178="",H178=""),"Missing Key","OK") -> OK | S178: =IF(L178>=1000,"Large",IF(L178>=500,"Medium","Small")) -> Small
A179: ORD000012 | B179: 46100 | C179: DSP0048 | D179: =IFERROR(VLOOKUP(C179,customer_lookup!$A:$E,2,FALSE),"") -> OK Account 0048 | E179: =IFERROR(VLOOKUP(C179,customer_lookup!$A:$E,3,FALSE),"") -> OK | F179: =IFERROR(VLOOKUP(C179,customer_lookup!$A:$E,5,FALSE),"") -> Casey | G179: Retail | H179: SKU0006 | I179: =IFERROR(VLOOKUP(H179,product_lookup!$A:$D,2,FALSE),"") -> Kiwi 1:1 Gummies | J179: 96 | K179: 11.75 | L179: =J179*K179 -> 1128 | M179: Fulfilled | N179: 46103 | O179: =SUMIF(inventory_snapshot!$B:$B,H179,inventory_snapshot!$E:$E) -> 1136 | P179: =IF(O179<J179,"Short","OK") -> OK | Q179: =IF(COUNTIF($A:$A,A179)>1,"Duplicate","OK") -> OK | R179: =IF(OR(C179="",H179=""),"Missing Key","OK") -> OK | S179: =IF(L179>=1000,"Large",IF(L179>=500,"Medium","Small")) -> Large
A180: ORD000021 | B180: 46074 | C180: DSP0038 | D180: =IFERROR(VLOOKUP(C180,customer_lookup!$A:$E,2,FALSE),"") -> WA Account 0038 | E180: =IFERROR(VLOOKUP(C180,customer_lookup!$A:$E,3,FALSE),"") -> WA | F180: =IFERROR(VLOOKUP(C180,customer_lookup!$A:$E,5,FALSE),"") -> Casey | G180: Wholesale | H180: SKU0008 | I180: =IFERROR(VLOOKUP(H180,product_lookup!$A:$D,2,FALSE),"") -> Peach 2:1 Gummies | J180: 24 | K180: 10.33 | L180: =J180*K180 -> 247.92 | M180: Fulfilled | N180: 46083 | O180: =SUMIF(inventory_snapshot!$B:$B,H180,inventory_snapshot!$E:$E) -> 1732 | P180: =IF(O180<J180,"Short","OK") -> OK | Q180: =IF(COUNTIF($A:$A,A180)>1,"Duplicate","OK") -> OK | R180: =IF(OR(C180="",H180=""),"Missing Key","OK") -> OK | S180: =IF(L180>=1000,"Large",IF(L180>=500,"Medium","Small")) -> Small
A181: ORD000033 | B181: 46140 | C181: DSP0077 | D181: =IFERROR(VLOOKUP(C181,customer_lookup!$A:$E,2,FALSE),"") -> AZ Account 0077 | E181: =IFERROR(VLOOKUP(C181,customer_lookup!$A:$E,3,FALSE),"") -> AZ | F181: =IFERROR(VLOOKUP(C181,customer_lookup!$A:$E,5,FALSE),"") -> Casey | G181: Wholesale | H181: SKU0019 | I181: =IFERROR(VLOOKUP(H181,product_lookup!$A:$D,2,FALSE),"") -> Cranberry Sparkling Beverage | J181: 30 | K181: 7.66 | L181: =J181*K181 -> 229.8 | M181: Rejected | N181: 46147 | O181: =SUMIF(inventory_snapshot!$B:$B,H181,inventory_snapshot!$E:$E) -> 1152 | P181: =IF(O181<J181,"Short","OK") -> OK | Q181: =IF(COUNTIF($A:$A,A181)>1,"Duplicate","OK") -> OK | R181: =IF(OR(C181="",H181=""),"Missing Key","OK") -> OK | S181: =IF(L181>=1000,"Large",IF(L181>=500,"Medium","Small")) -> Small
A182: ORD000037 | B182: 46064 | C182: DSP0053 | D182: =IFERROR(VLOOKUP(C182,customer_lookup!$A:$E,2,FALSE),"") -> AZ Account 0053 | E182: =IFERROR(VLOOKUP(C182,customer_lookup!$A:$E,3,FALSE),"") -> AZ | F182: =IFERROR(VLOOKUP(C182,customer_lookup!$A:$E,5,FALSE),"") -> Casey | G182: Wholesale | H182: SKU0011 | I182: =IFERROR(VLOOKUP(H182,product_lookup!$A:$D,2,FALSE),"") -> Raspberry THC Gummies | J182: 120 | K182: 9.67 | L182: =J182*K182 -> 1160.4 | M182: Approved | N182: 46072 | O182: =SUMIF(inventory_snapshot!$B:$B,H182,inventory_snapshot!$E:$E) -> 1417 | P182: =IF(O182<J182,"Short","OK") -> OK | Q182: =IF(COUNTIF($A:$A,A182)>1,"Duplicate","OK") -> OK | R182: =IF(OR(C182="",H182=""),"Missing Key","OK") -> OK | S182: =IF(L182>=1000,"Large",IF(L182>=500,"Medium","Small")) -> Large
A183: ORD000040 | B183: 46093 | C183: DSP0027 | D183: =IFERROR(VLOOKUP(C183,customer_lookup!$A:$E,2,FALSE),"") -> CA Account 0027 | E183: =IFERROR(VLOOKUP(C183,customer_lookup!$A:$E,3,FALSE),"") -> CA | F183: =IFERROR(VLOOKUP(C183,customer_lookup!$A:$E,5,FALSE),"") -> Casey | G183: Retail | H183: SKU0009 | I183: =IFERROR(VLOOKUP(H183,product_lookup!$A:$D,2,FALSE),"") -> Pear 1:1 Gummies | J183: 18 | K183: 12.21 | L183: =J183*K183 -> 219.78 | M183: Pending | N183: 46095 | O183: =SUMIF(inventory_snapshot!$B:$B,H183,inventory_snapshot!$E:$E) -> 981 | P183: =IF(O183<J183,"Short","OK") -> OK | Q183: =IF(COUNTIF($A:$A,A183)>1,"Duplicate","OK") -> OK | R183: =IF(OR(C183="",H183=""),"Missing Key","OK") -> OK | S183: =IF(L183>=1000,"Large",IF(L183>=500,"Medium","Small")) -> Small
A184: ORD000049 | B184: 46106 | C184: DSP0080 | D184: =IFERROR(VLOOKUP(C184,customer_lookup!$A:$E,2,FALSE),"") -> MI Account 0080 | E184: =IFERROR(VLOOKUP(C184,customer_lookup!$A:$E,3,FALSE),"") -> MI | F184: =IFERROR(VLOOKUP(C184,customer_lookup!$A:$E,5,FALSE),"") -> Casey | G184: Distributor | H184: SKU0013 | I184: =IFERROR(VLOOKUP(H184,product_lookup!$A:$D,2,FALSE),"") -> Sour Cherry THC Gummies | J184: 12 | K184: 11.51 | L184: =J184*K184 -> 138.12 | M184: Fulfilled | N184: 46113 | O184: =SUMIF(inventory_snapshot!$B:$B,H184,inventory_snapshot!$E:$E) -> 1313 | P184: =IF(O184<J184,"Short","OK") -> OK | Q184: =IF(COUNTIF($A:$A,A184)>1,"Duplicate","OK") -> OK | R184: =IF(OR(C184="",H184=""),"Missing Key","OK") -> OK | S184: =IF(L184>=1000,"Large",IF(L184>=500,"Medium","Small")) -> Small
A185: ORD000051 | B185: 46120 | C185: DSP0056 | D185: =IFERROR(VLOOKUP(C185,customer_lookup!$A:$E,2,FALSE),"") -> MI Account 0056 | E185: =IFERROR(VLOOKUP(C185,customer_lookup!$A:$E,3,FALSE),"") -> MI | F185: =IFERROR(VLOOKUP(C185,customer_lookup!$A:$E,5,FALSE),"") -> Casey | G185: Wholesale | H185: SKU0004 | I185: =IFERROR(VLOOKUP(H185,product_lookup!$A:$D,2,FALSE),"") -> Grapefruit 1:1:1 Gummies | J185: 120 | K185: 11.19 | L185: =J185*K185 -> 1342.8 | M185: Submitted | N185: 46125 | O185: =SUMIF(inventory_snapshot!$B:$B,H185,inventory_snapshot!$E:$E) -> 1751 | P185: =IF(O185<J185,"Short","OK") -> OK | Q185: =IF(COUNTIF($A:$A,A185)>1,"Duplicate","OK") -> OK | R185: =IF(OR(C185="",H185=""),"Missing Key","OK") -> OK | S185: =IF(L185>=1000,"Large",IF(L185>=500,"Medium","Small")) -> Large
... A367: ORD000489 | B367: 46082 | C367: DSP0107 | D367: =IFERROR(VLOOKUP(C367,customer_lookup!$A:$E,2,FALSE),"") -> NY Account 0107 | E367: =IFERROR(VLOOKUP(C367,customer_lookup!$A:$E,3,FALSE),"") -> NY | F367: =IFERROR(VLOOKUP(C367,customer_lookup!$A:$E,5,FALSE),"") -> Drew | G367: Distributor | H367: SKU0003 | I367: =IFERROR(VLOOKUP(H367,product_lookup!$A:$D,2,FALSE),"") -> Elderberry 2:1 Gummies | J367: 120 | K367: 10.03 | L367: =J367*K367 -> 1203.6 | M367: Fulfilled | N367: 46089 | O367: =SUMIF(inventory_snapshot!$B:$B,H367,inventory_snapshot!$E:$E) -> 1633 | P367: =IF(O367<J367,"Short","OK") -> OK | Q367: =IF(COUNTIF($A:$A,A367)>1,"Duplicate","OK") -> OK | R367: =IF(OR(C367="",H367=""),"Missing Key","OK") -> OK | S367: =IF(L367>=1000,"Large",IF(L367>=500,"Medium","Small")) -> Large
A368: ORD000495 | B368: 46121 | C368: DSP0028 | D368: =IFERROR(VLOOKUP(C368,customer_lookup!$A:$E,2,FALSE),"") -> CO Account 0028 | E368: =IFERROR(VLOOKUP(C368,customer_lookup!$A:$E,3,FALSE),"") -> CO | F368: =IFERROR(VLOOKUP(C368,customer_lookup!$A:$E,5,FALSE),"") -> Drew | G368: Distributor | I368: =IFERROR(VLOOKUP(H368,product_lookup!$A:$D,2,FALSE),"") | J368: 72 | K368: 11.67 | L368: =J368*K368 -> 840.24 | M368: Approved | N368: 46129 | O368: =SUMIF(inventory_snapshot!$B:$B,H368,inventory_snapshot!$E:$E) -> 0 | P368: =IF(O368<J368,"Short","OK") -> Short | Q368: =IF(COUNTIF($A:$A,A368)>1,"Duplicate","OK") -> OK | R368: =IF(OR(C368="",H368=""),"Missing Key","OK") -> Missing Key | S368: =IF(L368>=1000,"Large",IF(L368>=500,"Medium","Small")) -> Medium
A369: ORD000499 | B369: 46116 | C369: DSP0118 | D369: =IFERROR(VLOOKUP(C369,customer_lookup!$A:$E,2,FALSE),"") -> NM Account 0118 | E369: =IFERROR(VLOOKUP(C369,customer_lookup!$A:$E,3,FALSE),"") -> NM | F369: =IFERROR(VLOOKUP(C369,customer_lookup!$A:$E,5,FALSE),"") -> Drew | G369: Wholesale | H369: SKU0007 | I369: =IFERROR(VLOOKUP(H369,product_lookup!$A:$D,2,FALSE),"") -> Marionberry THC Gummies | J369: 12 | K369: 10.71 | L369: =J369*K369 -> 128.52 | M369: Fulfilled | N369: 46126 | O369: =SUMIF(inventory_snapshot!$B:$B,H369,inventory_snapshot!$E:$E) -> 1599 | P369: =IF(O369<J369,"Short","OK") -> OK | Q369: =IF(COUNTIF($A:$A,A369)>1,"Duplicate","OK") -> OK | R369: =IF(OR(C369="",H369=""),"Missing Key","OK") -> OK | S369: =IF(L369>=1000,"Large",IF(L369>=500,"Medium","Small")) -> Small
A370: ORD000515 | B370: 46141 | C370: DSP0006 | D370: =IFERROR(VLOOKUP(C370,customer_lookup!$A:$E,2,FALSE),"") -> NV Account 0006 | E370: =IFERROR(VLOOKUP(C370,customer_lookup!$A:$E,3,FALSE),"") -> NV | F370: =IFERROR(VLOOKUP(C370,customer_lookup!$A:$E,5,FALSE),"") -> Drew | G370: Retail | H370: SKU0008 | I370: =IFERROR(VLOOKUP(H370,product_lookup!$A:$D,2,FALSE),"") -> Peach 2:1 Gummies | J370: 72 | K370: 10.33 | L370: =J370*K370 -> 743.76 | M370: Fulfilled | N370: 46142 | O370: =SUMIF(inventory_snapshot!$B:$B,H370,inventory_snapshot!$E:$E) -> 1732 | P370: =IF(O370<J370,"Short","OK") -> OK | Q370: =IF(COUNTIF($A:$A,A370)>1,"Duplicate","OK") -> OK | R370: =IF(OR(C370="",H370=""),"Missing Key","OK") -> OK | S370: =IF(L370>=1000,"Large",IF(L370>=500,"Medium","Small")) -> Medium
A371: ORD000529 | B371: 46089 | C371: DSP0006 | D371: =IFERROR(VLOOKUP(C371,customer_lookup!$A:$E,2,FALSE),"") -> NV Account 0006 | E371: =IFERROR(VLOOKUP(C371,customer_lookup!$A:$E,3,FALSE),"") -> NV | F371: =IFERROR(VLOOKUP(C371,customer_lookup!$A:$E,5,FALSE),"") -> Drew | G371: Wholesale | H371: SKU0008 | I371: =IFERROR(VLOOKUP(H371,product_lookup!$A:$D,2,FALSE),"") -> Peach 2:1 Gummies | J371: 72 | K371: 10.53 | L371: =J371*K371 -> 758.16 | M371: Fulfilled | N371: 46098 | O371: =SUMIF(inventory_snapshot!$B:$B,H371,inventory_snapshot!$E:$E) -> 1732 | P371: =IF(O371<J371,"Short","OK") -> OK | Q371: =IF(COUNTIF($A:$A,A371)>1,"Duplicate","OK") -> OK | R371: =IF(OR(C371="",H371=""),"Missing Key","OK") -> OK | S371: =IF(L371>=1000,"Large",IF(L371>=500,"Medium","Small")) -> Medium
A372: ORD000538 | B372: 46107 | C372: DSP0028 | D372: =IFERROR(VLOOKUP(C372,customer_lookup!$A:$E,2,FALSE),"") -> CO Account 0028 | E372: =IFERROR(VLOOKUP(C372,customer_lookup!$A:$E,3,FALSE),"") -> CO | F372: =IFERROR(VLOOKUP(C372,customer_lookup!$A:$E,5,FALSE),"") -> Drew | G372: Wholesale | H372: SKU0019 | I372: =IFERROR(VLOOKUP(H372,product_lookup!$A:$D,2,FALSE),"") -> Cranberry Sparkling Beverage | J372: 60 | K372: 7.68 | L372: =J372*K372 -> 460.8 | M372: Pending | N372: 46108 | O372: =SUMIF(inventory_snapshot!$B:$B,H372,inventory_snapshot!$E:$E) -> 1152 | P372: =IF(O372<J372,"Short","OK") -> OK | Q372: =IF(COUNTIF($A:$A,A372)>1,"Duplicate","OK") -> OK | R372: =IF(OR(C372="",H372=""),"Missing Key","OK") -> OK | S372: =IF(L372>=1000,"Large",IF(L372>=500,"Medium","Small")) -> Small
A373: ORD000573 | B373: 46060 | C373: DSP0058 | D373: =IFERROR(VLOOKUP(C373,customer_lookup!$A:$E,2,FALSE),"") -> NM Account 0058 | E373: =IFERROR(VLOOKUP(C373,customer_lookup!$A:$E,3,FALSE),"") -> NM | F373: =IFERROR(VLOOKUP(C373,customer_lookup!$A:$E,5,FALSE),"") -> Drew | G373: Wholesale | H373: SKU0018 | I373: =IFERROR(VLOOKUP(H373,product_lookup!$A:$D,2,FALSE),"") -> Lemon Sparkling Beverage | J373: 48 | K373: 7.42 | L373: =J373*K373 -> 356.16 | M373: Pending | N373: 46066 | O373: =SUMIF(inventory_snapshot!$B:$B,H373,inventory_snapshot!$E:$E) -> 1360 | P373: =IF(O373<J373,"Short","OK") -> OK | Q373: =IF(COUNTIF($A:$A,A373)>1,"Duplicate","OK") -> OK | R373: =IF(OR(C373="",H373=""),"Missing Key","OK") -> OK | S373: =IF(L373>=1000,"Large",IF(L373>=500,"Medium","Small")) -> Small
A374: ORD000657 | B374: 46034 | C374: DSP0058 | D374: =IFERROR(VLOOKUP(C374,customer_lookup!$A:$E,2,FALSE),"") -> NM Account 0058 | E374: =IFERROR(VLOOKUP(C374,customer_lookup!$A:$E,3,FALSE),"") -> NM | F374: =IFERROR(VLOOKUP(C374,customer_lookup!$A:$E,5,FALSE),"") -> Drew | G374: Distributor | H374: SKU0018 | I374: =IFERROR(VLOOKUP(H374,product_lookup!$A:$D,2,FALSE),"") -> Lemon Sparkling Beverage | J374: 24 | K374: 7.58 | L374: =J374*K374 -> 181.92 | M374: Pending | N374: 46042 | O374: =SUMIF(inventory_snapshot!$B:$B,H374,inventory_snapshot!$E:$E) -> 1360 | P374: =IF(O374<J374,"Short","OK") -> OK | Q374: =IF(COUNTIF($A:$A,A374)>1,"Duplicate","OK") -> OK | R374: =IF(OR(C374="",H374=""),"Missing Key","OK") -> OK | S374: =IF(L374>=1000,"Large",IF(L374>=500,"Medium","Small")) -> Small
A375: ORD000661 | B375: 46061 | C375: DSP0107 | D375: =IFERROR(VLOOKUP(C375,customer_lookup!$A:$E,2,FALSE),"") -> NY Account 0107 | E375: =IFERROR(VLOOKUP(C375,customer_lookup!$A:$E,3,FALSE),"") -> NY | F375: =IFERROR(VLOOKUP(C375,customer_lookup!$A:$E,5,FALSE),"") -> Drew | G375: Wholesale | H375: SKU0019 | I375: =IFERROR(VLOOKUP(H375,product_lookup!$A:$D,2,FALSE),"") -> Cranberry Sparkling Beverage | J375: 60 | K375: 7.84 | L375: =J375*K375 -> 470.4 | M375: Rejected | N375: 46062 | O375: =SUMIF(inventory_snapshot!$B:$B,H375,inventory_snapshot!$E:$E) -> 1152 | P375: =IF(O375<J375,"Short","OK") -> OK | Q375: =IF(COUNTIF($A:$A,A375)>1,"Duplicate","OK") -> OK | R375: =IF(OR(C375="",H375=""),"Missing Key","OK") -> OK | S375: =IF(L375>=1000,"Large",IF(L375>=500,"Medium","Small")) -> Small
A376: ORD000673 | B376: 46124 | C376: DSP0014 | D376: =IFERROR(VLOOKUP(C376,customer_lookup!$A:$E,2,FALSE),"") -> WA Account 0014 | E376: =IFERROR(VLOOKUP(C376,customer_lookup!$A:$E,3,FALSE),"") -> WA | F376: =IFERROR(VLOOKUP(C376,customer_lookup!$A:$E,5,FALSE),"") -> Drew | G376: Wholesale | H376: SKU0002 | I376: =IFERROR(VLOOKUP(H376,product_lookup!$A:$D,2,FALSE),"") -> Boysenberry 1:1:1 Gummies | J376: 120 | K376: 10.53 | L376: =J376*K376 -> 1263.6 | M376: Submitted | N376: 46129 | O376: =SUMIF(inventory_snapshot!$B:$B,H376,inventory_snapshot!$E:$E) -> 2007 | P376: =IF(O376<J376,"Short","OK") -> OK | Q376: =IF(COUNTIF($A:$A,A376)>1,"Duplicate","OK") -> OK | R376: =IF(OR(C376="",H376=""),"Missing Key","OK") -> OK | S376: =IF(L376>=1000,"Large",IF(L376>=500,"Medium","Small")) -> Large
A377: ORD000678 | B377: 46129 | C377: DSP0014 | D377: =IFERROR(VLOOKUP(C377,customer_lookup!$A:$E,2,FALSE),"") -> WA Account 0014 | E377: =IFERROR(VLOOKUP(C377,customer_lookup!$A:$E,3,FALSE),"") -> WA | F377: =IFERROR(VLOOKUP(C377,customer_lookup!$A:$E,5,FALSE),"") -> Drew | G377: Wholesale | H377: SKU0006 | I377: =IFERROR(VLOOKUP(H377,product_lookup!$A:$D,2,FALSE),"") -> Kiwi 1:1 Gummies | J377: 36 | K377: 11.78 | L377: =J377*K377 -> 424.08 | M377: Pending | N377: 46136 | O377: =SUMIF(inventory_snapshot!$B:$B,H377,inventory_snapshot!$E:$E) -> 1136 | P377: =IF(O377<J377,"Short","OK") -> OK | Q377: =IF(COUNTIF($A:$A,A377)>1,"Duplicate","OK") -> OK | R377: =IF(OR(C377="",H377=""),"Missing Key","OK") -> OK | S377: =IF(L377>=1000,"Large",IF(L377>=500,"Medium","Small")) -> Small
A378: ORD000683 | B378: 46031 | C378: DSP0014 | D378: =IFERROR(VLOOKUP(C378,customer_lookup!$A:$E,2,FALSE),"") -> WA Account 0014 | E378: =IFERROR(VLOOKUP(C378,customer_lookup!$A:$E,3,FALSE),"") -> WA | F378: =IFERROR(VLOOKUP(C378,customer_lookup!$A:$E,5,FALSE),"") -> Drew | G378: Wholesale | H378: SKU0006 | I378: =IFERROR(VLOOKUP(H378,product_lookup!$A:$D,2,FALSE),"") -> Kiwi 1:1 Gummies | J378: 36 | K378: 11.77 | L378: =J378*K378 -> 423.72 | M378: Approved | N378: 46038 | O378: =SUMIF(inventory_snapshot!$B:$B,H378,inventory_snapshot!$E:$E) -> 1136 | P378: =IF(O378<J378,"Short","OK") -> OK | Q378: =IF(COUNTIF($A:$A,A378)>1,"Duplicate","OK") -> OK | R378: =IF(OR(C378="",H378=""),"Missing Key","OK") -> OK | S378: =IF(L378>=1000,"Large",IF(L378>=500,"Medium","Small")) -> Small
A379: ORD000723 | B379: 46051 | C379: DSP0107 | D379: =IFERROR(VLOOKUP(C379,customer_lookup!$A:$E,2,FALSE),"") -> NY Account 0107 | E379: =IFERROR(VLOOKUP(C379,customer_lookup!$A:$E,3,FALSE),"") -> NY | F379: =IFERROR(VLOOKUP(C379,customer_lookup!$A:$E,5,FALSE),"") -> Drew | G379: Wholesale | H379: SKU0019 | I379: =IFERROR(VLOOKUP(H379,product_lookup!$A:$D,2,FALSE),"") -> Cranberry Sparkling Beverage | J379: 6 | K379: 8.44 | L379: =J379*K379 -> 50.64 | M379: Partial | N379: 46055 | O379: =SUMIF(inventory_snapshot!$B:$B,H379,inventory_snapshot!$E:$E) -> 1152 | P379: =IF(O379<J379,"Short","OK") -> OK | Q379: =IF(COUNTIF($A:$A,A379)>1,"Duplicate","OK") -> OK | R379: =IF(OR(C379="",H379=""),"Missing Key","OK") -> OK | S379: =IF(L379>=1000,"Large",IF(L379>=500,"Medium","Small")) -> Small
A380: ORD000729 | B380: 46113 | C380: DSP0028 | D380: =IFERROR(VLOOKUP(C380,customer_lookup!$A:$E,2,FALSE),"") -> CO Account 0028 | E380: =IFERROR(VLOOKUP(C380,customer_lookup!$A:$E,3,FALSE),"") -> CO | F380: =IFERROR(VLOOKUP(C380,customer_lookup!$A:$E,5,FALSE),"") -> Drew | G380: Wholesale | H380: SKU0013 | I380: =IFERROR(VLOOKUP(H380,product_lookup!$A:$D,2,FALSE),"") -> Sour Cherry THC Gummies | J380: 48 | K380: 11.26 | L380: =J380*K380 -> 540.48 | M380: Approved | N380: 46114 | O380: =SUMIF(inventory_snapshot!$B:$B,H380,inventory_snapshot!$E:$E) -> 1313 | P380: =IF(O380<J380,"Short","OK") -> OK | Q380: =IF(COUNTIF($A:$A,A380)>1,"Duplicate","OK") -> OK | R380: =IF(OR(C380="",H380=""),"Missing Key","OK") -> OK | S380: =IF(L380>=1000,"Large",IF(L380>=500,"Medium","Small")) -> Medium
... A694: ORD000116 | B694: 46037 | C694: DSP0068 | D694: =IFERROR(VLOOKUP(C694,customer_lookup!$A:$E,2,FALSE),"") -> MI Account 0068 | E694: =IFERROR(VLOOKUP(C694,customer_lookup!$A:$E,3,FALSE),"") -> MI | F694: =IFERROR(VLOOKUP(C694,customer_lookup!$A:$E,5,FALSE),"") -> Quinn | G694: Wholesale | H694: SKU0014 | I694: =IFERROR(VLOOKUP(H694,product_lookup!$A:$D,2,FALSE),"") -> Sour Tangerine THC Gummies | J694: 30 | K694: 10.19 | L694: =J694*K694 -> 305.7 | M694: Approved | N694: 46047 | O694: =SUMIF(inventory_snapshot!$B:$B,H694,inventory_snapshot!$E:$E) -> 1679 | P694: =IF(O694<J694,"Short","OK") -> OK | Q694: =IF(COUNTIF($A:$A,A694)>1,"Duplicate","OK") -> OK | R694: =IF(OR(C694="",H694=""),"Missing Key","OK") -> OK | S694: =IF(L694>=1000,"Large",IF(L694>=500,"Medium","Small")) -> Small
A695: ORD000117 | B695: 46099 | C695: DSP0116 | D695: =IFERROR(VLOOKUP(C695,customer_lookup!$A:$E,2,FALSE),"") -> MI Account 0116 | E695: =IFERROR(VLOOKUP(C695,customer_lookup!$A:$E,3,FALSE),"") -> MI | F695: =IFERROR(VLOOKUP(C695,customer_lookup!$A:$E,5,FALSE),"") -> Quinn | G695: Wholesale | I695: =IFERROR(VLOOKUP(H695,product_lookup!$A:$D,2,FALSE),"") | J695: 72 | K695: 6.77 | L695: =J695*K695 -> 487.44 | M695: Fulfilled | N695: 46102 | O695: =SUMIF(inventory_snapshot!$B:$B,H695,inventory_snapshot!$E:$E) -> 0 | P695: =IF(O695<J695,"Short","OK") -> Short | Q695: =IF(COUNTIF($A:$A,A695)>1,"Duplicate","OK") -> OK | R695: =IF(OR(C695="",H695=""),"Missing Key","OK") -> Missing Key | S695: =IF(L695>=1000,"Large",IF(L695>=500,"Medium","Small")) -> Small
A696: ORD000125 | B696: 46057 | C696: DSP0119 | D696: =IFERROR(VLOOKUP(C696,customer_lookup!$A:$E,2,FALSE),"") -> NY Account 0119 | E696: =IFERROR(VLOOKUP(C696,customer_lookup!$A:$E,3,FALSE),"") -> NY | F696: =IFERROR(VLOOKUP(C696,customer_lookup!$A:$E,5,FALSE),"") -> Quinn | G696: Wholesale | H696: SKU0017 | I696: =IFERROR(VLOOKUP(H696,product_lookup!$A:$D,2,FALSE),"") -> Mango Sparkling Beverage | J696: 12 | K696: 7.84 | L696: =J696*K696 -> 94.08 | M696: Submitted | N696: 46060 | O696: =SUMIF(inventory_snapshot!$B:$B,H696,inventory_snapshot!$E:$E) -> 1502 | P696: =IF(O696<J696,"Short","OK") -> OK | Q696: =IF(COUNTIF($A:$A,A696)>1,"Duplicate","OK") -> OK | R696: =IF(OR(C696="",H696=""),"Missing Key","OK") -> OK | S696: =IF(L696>=1000,"Large",IF(L696>=500,"Medium","Small")) -> Small
A697: ORD000134 | B697: 46124 | C697: DSP0119 | D697: =IFERROR(VLOOKUP(C697,customer_lookup!$A:$E,2,FALSE),"") -> NY Account 0119 | E697: =IFERROR(VLOOKUP(C697,customer_lookup!$A:$E,3,FALSE),"") -> NY | F697: =IFERROR(VLOOKUP(C697,customer_lookup!$A:$E,5,FALSE),"") -> Quinn | G697: Wholesale | H697: SKU0006 | I697: =IFERROR(VLOOKUP(H697,product_lookup!$A:$D,2,FALSE),"") -> Kiwi 1:1 Gummies | J697: 36 | K697: 10.77 | L697: =J697*K697 -> 387.72 | M697: Approved | N697: 46127 | O697: =SUMIF(inventory_snapshot!$B:$B,H697,inventory_snapshot!$E:$E) -> 1136 | P697: =IF(O697<J697,"Short","OK") -> OK | Q697: =IF(COUNTIF($A:$A,A697)>1,"Duplicate","OK") -> OK | R697: =IF(OR(C697="",H697=""),"Missing Key","OK") -> OK | S697: =IF(L697>=1000,"Large",IF(L697>=500,"Medium","Small")) -> Small
A698: ORD000136 | B698: 46090 | C698: DSP0092 | D698: =IFERROR(VLOOKUP(C698,customer_lookup!$A:$E,2,FALSE),"") -> MI Account 0092 | E698: =IFERROR(VLOOKUP(C698,customer_lookup!$A:$E,3,FALSE),"") -> MI | F698: =IFERROR(VLOOKUP(C698,customer_lookup!$A:$E,5,FALSE),"") -> Quinn | G698: Wholesale | H698: SKU0016 | I698: =IFERROR(VLOOKUP(H698,product_lookup!$A:$D,2,FALSE),"") -> Blackberry Sparkling Beverage | J698: 48 | K698: 7.9 | L698: =J698*K698 -> 379.2 | M698: Fulfilled | N698: 46096 | O698: =SUMIF(inventory_snapshot!$B:$B,H698,inventory_snapshot!$E:$E) -> 1292 | P698: =IF(O698<J698,"Short","OK") -> OK | Q698: =IF(COUNTIF($A:$A,A698)>1,"Duplicate","OK") -> OK | R698: =IF(OR(C698="",H698=""),"Missing Key","OK") -> OK | S698: =IF(L698>=1000,"Large",IF(L698>=500,"Medium","Small")) -> Small
A699: ORD000163 | B699: 46106 | C699: DSP0119 | D699: =IFERROR(VLOOKUP(C699,customer_lookup!$A:$E,2,FALSE),"") -> NY Account 0119 | E699: =IFERROR(VLOOKUP(C699,customer_lookup!$A:$E,3,FALSE),"") -> NY | F699: =IFERROR(VLOOKUP(C699,customer_lookup!$A:$E,5,FALSE),"") -> Quinn | G699: Distributor | H699: SKU0015 | I699: =IFERROR(VLOOKUP(H699,product_lookup!$A:$D,2,FALSE),"") -> Strawberry 20:1 Gummies | J699: 30 | K699: 12.07 | L699: =J699*K699 -> 362.1 | M699: Approved | N699: 46111 | O699: =SUMIF(inventory_snapshot!$B:$B,H699,inventory_snapshot!$E:$E) -> 2294 | P699: =IF(O699<J699,"Short","OK") -> OK | Q699: =IF(COUNTIF($A:$A,A699)>1,"Duplicate","OK") -> OK | R699: =IF(OR(C699="",H699=""),"Missing Key","OK") -> OK | S699: =IF(L699>=1000,"Large",IF(L699>=500,"Medium","Small")) -> Small
A700: ORD000183 | B700: 46039 | C700: DSP0051 | D700: =IFERROR(VLOOKUP(C700,customer_lookup!$A:$E,2,FALSE),"") -> CA Account 0051 | E700: =IFERROR(VLOOKUP(C700,customer_lookup!$A:$E,3,FALSE),"") -> CA | F700: =IFERROR(VLOOKUP(C700,customer_lookup!$A:$E,5,FALSE),"") -> Quinn | G700: Distributor | H700: SKU0017 | I700: =IFERROR(VLOOKUP(H700,product_lookup!$A:$D,2,FALSE),"") -> Mango Sparkling Beverage | J700: 24 | K700: 8 | L700: =J700*K700 -> 192 | M700: Fulfilled | N700: 46047 | O700: =SUMIF(inventory_snapshot!$B:$B,H700,inventory_snapshot!$E:$E) -> 1502 | P700: =IF(O700<J700,"Short","OK") -> OK | Q700: =IF(COUNTIF($A:$A,A700)>1,"Duplicate","OK") -> OK | R700: =IF(OR(C700="",H700=""),"Missing Key","OK") -> OK | S700: =IF(L700>=1000,"Large",IF(L700>=500,"Medium","Small")) -> Small
A701: ORD000190 | B701: 46083 | C701: DSP0024 | D701: =IFERROR(VLOOKUP(C701,customer_lookup!$A:$E,2,FALSE),"") -> OK Account 0024 | E701: =IFERROR(VLOOKUP(C701,customer_lookup!$A:$E,3,FALSE),"") -> OK | F701: =IFERROR(VLOOKUP(C701,customer_lookup!$A:$E,5,FALSE),"") -> Quinn | G701: Retail | H701: SKU0018 | I701: =IFERROR(VLOOKUP(H701,product_lookup!$A:$D,2,FALSE),"") -> Lemon Sparkling Beverage | J701: 24 | K701: 7.76 | L701: =J701*K701 -> 186.24 | M701: Approved | N701: 46091 | O701: =SUMIF(inventory_snapshot!$B:$B,H701,inventory_snapshot!$E:$E) -> 1360 | P701: =IF(O701<J701,"Short","OK") -> OK | Q701: =IF(COUNTIF($A:$A,A701)>1,"Duplicate","OK") -> OK | R701: =IF(OR(C701="",H701=""),"Missing Key","OK") -> OK | S701: =IF(L701>=1000,"Large",IF(L701>=500,"Medium","Small")) -> Small
A702: ORD000221 | B702: 46058 | C702: DSP0042 | D702: =IFERROR(VLOOKUP(C702,customer_lookup!$A:$E,2,FALSE),"") -> NV Account 0042 | E702: =IFERROR(VLOOKUP(C702,customer_lookup!$A:$E,3,FALSE),"") -> NV | F702: =IFERROR(VLOOKUP(C702,customer_lookup!$A:$E,5,FALSE),"") -> Quinn | G702: Wholesale | H702: SKU0013 | I702: =IFERROR(VLOOKUP(H702,product_lookup!$A:$D,2,FALSE),"") -> Sour Cherry THC Gummies | J702: 48 | K702: 10.46 | L702: =J702*K702 -> 502.08 | M702: Partial | N702: 46067 | O702: =SUMIF(inventory_snapshot!$B:$B,H702,inventory_snapshot!$E:$E) -> 1313 | P702: =IF(O702<J702,"Short","OK") -> OK | Q702: =IF(COUNTIF($A:$A,A702)>1,"Duplicate","OK") -> OK | R702: =IF(OR(C702="",H702=""),"Missing Key","OK") -> OK | S702: =IF(L702>=1000,"Large",IF(L702>=500,"Medium","Small")) -> Medium
A703: ORD000224 | B703: 46087 | C703: DSP0052 | D703: =IFERROR(VLOOKUP(C703,customer_lookup!$A:$E,2,FALSE),"") -> CO Account 0052 | E703: =IFERROR(VLOOKUP(C703,customer_lookup!$A:$E,3,FALSE),"") -> CO | F703: =IFERROR(VLOOKUP(C703,customer_lookup!$A:$E,5,FALSE),"") -> Quinn | G703: Wholesale | H703: SKU0018 | I703: =IFERROR(VLOOKUP(H703,product_lookup!$A:$D,2,FALSE),"") -> Lemon Sparkling Beverage | J703: 48 | K703: 7.31 | L703: =J703*K703 -> 350.88 | M703: Fulfilled | N703: 46096 | O703: =SUMIF(inventory_snapshot!$B:$B,H703,inventory_snapshot!$E:$E) -> 1360 | P703: =IF(O703<J703,"Short","OK") -> OK | Q703: =IF(COUNTIF($A:$A,A703)>1,"Duplicate","OK") -> OK | R703: =IF(OR(C703="",H703=""),"Missing Key","OK") -> OK | S703: =IF(L703>=1000,"Large",IF(L703>=500,"Medium","Small")) -> Small
A704: ORD000248 | B704: 46081 | C704: DSP0120 | D704: =IFERROR(VLOOKUP(C704,customer_lookup!$A:$E,2,FALSE),"") -> OK Account 0120 | E704: =IFERROR(VLOOKUP(C704,customer_lookup!$A:$E,3,FALSE),"") -> OK | F704: =IFERROR(VLOOKUP(C704,customer_lookup!$A:$E,5,FALSE),"") -> Quinn | G704: Retail | H704: SKU0012 | I704: =IFERROR(VLOOKUP(H704,product_lookup!$A:$D,2,FALSE),"") -> Sour Apple THC Gummies | J704: 60 | K704: 10.14 | L704: =J704*K704 -> 608.4 | M704: Submitted | N704: 46083 | O704: =SUMIF(inventory_snapshot!$B:$B,H704,inventory_snapshot!$E:$E) -> 775 | P704: =IF(O704<J704,"Short","OK") -> OK | Q704: =IF(COUNTIF($A:$A,A704)>1,"Duplicate","OK") -> OK | R704: =IF(OR(C704="",H704=""),"Missing Key","OK") -> OK | S704: =IF(L704>=1000,"Large",IF(L704>=500,"Medium","Small")) -> Medium
A705: ORD000260 | B705: 46105 | C705: DSP0051 | D705: =IFERROR(VLOOKUP(C705,customer_lookup!$A:$E,2,FALSE),"") -> CA Account 0051 | E705: =IFERROR(VLOOKUP(C705,customer_lookup!$A:$E,3,FALSE),"") -> CA | F705: =IFERROR(VLOOKUP(C705,customer_lookup!$A:$E,5,FALSE),"") -> Quinn | G705: Wholesale | H705: SKU0010 | I705: =IFERROR(VLOOKUP(H705,product_lookup!$A:$D,2,FALSE),"") -> Pomegranate 1:1 Gummies | J705: 6 | K705: 11.62 | L705: =J705*K705 -> 69.72 | M705: Fulfilled | N705: 46112 | O705: =SUMIF(inventory_snapshot!$B:$B,H705,inventory_snapshot!$E:$E) -> 1493 | P705: =IF(O705<J705,"Short","OK") -> OK | Q705: =IF(COUNTIF($A:$A,A705)>1,"Duplicate","OK") -> OK | R705: =IF(OR(C705="",H705=""),"Missing Key","OK") -> OK | S705: =IF(L705>=1000,"Large",IF(L705>=500,"Medium","Small")) -> Small
A706: ORD000263 | B706: 46059 | C706: DSP0051 | D706: =IFERROR(VLOOKUP(C706,customer_lookup!$A:$E,2,FALSE),"") -> CA Account 0051 | E706: =IFERROR(VLOOKUP(C706,customer_lookup!$A:$E,3,FALSE),"") -> CA | F706: =IFERROR(VLOOKUP(C706,customer_lookup!$A:$E,5,FALSE),"") -> Quinn | G706: Wholesale | H706: SKU0017 | I706: =IFERROR(VLOOKUP(H706,product_lookup!$A:$D,2,FALSE),"") -> Mango Sparkling Beverage | J706: 120 | K706: 7.82 | L706: =J706*K706 -> 938.4 | M706: Fulfilled | N706: 46066 | O706: =SUMIF(inventory_snapshot!$B:$B,H706,inventory_snapshot!$E:$E) -> 1502 | P706: =IF(O706<J706,"Short","OK") -> OK | Q706: =IF(COUNTIF($A:$A,A706)>1,"Duplicate","OK") -> OK | R706: =IF(OR(C706="",H706=""),"Missing Key","OK") -> OK | S706: =IF(L706>=1000,"Large",IF(L706>=500,"Medium","Small")) -> Medium
A707: ORD000280 | B707: 46063 | C707: DSP0051 | D707: =IFERROR(VLOOKUP(C707,customer_lookup!$A:$E,2,FALSE),"") -> CA Account 0051 | E707: =IFERROR(VLOOKUP(C707,customer_lookup!$A:$E,3,FALSE),"") -> CA | F707: =IFERROR(VLOOKUP(C707,customer_lookup!$A:$E,5,FALSE),"") -> Quinn | G707: Wholesale | H707: SKU0011 | I707: =IFERROR(VLOOKUP(H707,product_lookup!$A:$D,2,FALSE),"") -> Raspberry THC Gummies | J707: 60 | K707: 10.02 | L707: =J707*K707 -> 601.2 | M707: Submitted | N707: 46073 | O707: =SUMIF(inventory_snapshot!$B:$B,H707,inventory_snapshot!$E:$E) -> 1417 | P707: =IF(O707<J707,"Short","OK") -> OK | Q707: =IF(COUNTIF($A:$A,A707)>1,"Duplicate","OK") -> OK | R707: =IF(OR(C707="",H707=""),"Missing Key","OK") -> OK | S707: =IF(L707>=1000,"Large",IF(L707>=500,"Medium","Small")) -> Medium
... A1001: ORD000999 | B1001: 46100 | C1001: DSP0062 | D1001: =IFERROR(VLOOKUP(C1001,customer_lookup!$A:$E,2,FALSE),"") -> WA Account 0062 | E1001: =IFERROR(VLOOKUP(C1001,customer_lookup!$A:$E,3,FALSE),"") -> WA | F1001: =IFERROR(VLOOKUP(C1001,customer_lookup!$A:$E,5,FALSE),"") -> Taylor | G1001: Distributor | H1001: SKU0014 | I1001: =IFERROR(VLOOKUP(H1001,product_lookup!$A:$D,2,FALSE),"") -> Sour Tangerine THC Gummies | J1001: 36 | K1001: 9.97 | L1001: =J1001*K1001 -> 358.92 | M1001: Partial | N1001: 46107 | O1001: =SUMIF(inventory_snapshot!$B:$B,H1001,inventory_snapshot!$E:$E) -> 1679 | P1001: =IF(O1001<J1001,"Short","OK") -> OK | Q1001: =IF(COUNTIF($A:$A,A1001)>1,"Duplicate","OK") -> OK | R1001: =IF(OR(C1001="",H1001=""),"Missing Key","OK") -> OK | S1001: =IF(L1001>=1000,"Large",IF(L1001>=500,"Medium","Small")) -> Small

Sheet erp_invoices
A1: invoice_id | B1: order_id | C1: invoice_date | D1: customer_id | E1: sku | F1: qty_invoiced | G1: invoice_amount | H1: invoice_status | I1: qty_variance_vs_order | J1: amount_variance_vs_order | K1: orphan_invoice_flag
A2: INV000001 | B2: ORD000001 | C2: 46065 | D2: DSP0072 | E2: SKU0020 | F2: 66 | G2: 522.72 | H2: Review | I2: =F2-IFERROR(VLOOKUP(B2,crm_orders!$A:$S,10,FALSE),0) -> 6 | J2: =G2-IFERROR(VLOOKUP(B2,crm_orders!$A:$S,12,FALSE),0) -> 47.52 | K2: =IF(COUNTIF(crm_orders!$A:$A,B2)=0,"Orphan","OK") -> OK
A3: INV000002 | B3: ORD000002 | C3: 46083 | D3: DSP0111 | E3: SKU0016 | F3: 30 | G3: 236.4 | H3: Posted | I3: =F3-IFERROR(VLOOKUP(B3,crm_orders!$A:$S,10,FALSE),0) -> 0 | J3: =G3-IFERROR(VLOOKUP(B3,crm_orders!$A:$S,12,FALSE),0) -> 0 | K3: =IF(COUNTIF(crm_orders!$A:$A,B3)=0,"Orphan","OK") -> OK
A4: INV000003 | B4: ORD000003 | C4: 46128 | D4: DSP0057 | E4: SKU0003 | F4: 30 | G4: 312.6 | H4: Posted | I4: =F4-IFERROR(VLOOKUP(B4,crm_orders!$A:$S,10,FALSE),0) -> 0 | J4: =G4-IFERROR(VLOOKUP(B4,crm_orders!$A:$S,12,FALSE),0) -> 0 | K4: =IF(COUNTIF(crm_orders!$A:$A,B4)=0,"Orphan","OK") -> OK
A5: INV000004 | B5: ORD000004 | C5: 46122 | D5: DSP0089 | E5: SKU0005 | F5: 24 | G5: 224.64 | H5: Posted | I5: =F5-IFERROR(VLOOKUP(B5,crm_orders!$A:$S,10,FALSE),0) -> 0 | J5: =G5-IFERROR(VLOOKUP(B5,crm_orders!$A:$S,12,FALSE),0) -> 0 | K5: =IF(COUNTIF(crm_orders!$A:$A,B5)=0,"Orphan","OK") -> OK
A6: INV000005 | B6: ORD000005 | C6: 46113 | D6: DSP0050 | E6: SKU0019 | F6: 6 | G6: 49.8 | H6: Posted | I6: =F6-IFERROR(VLOOKUP(B6,crm_orders!$A:$S,10,FALSE),0) -> 0 | J6: =G6-IFERROR(VLOOKUP(B6,crm_orders!$A:$S,12,FALSE),0) -> 0 | K6: =IF(COUNTIF(crm_orders!$A:$A,B6)=0,"Orphan","OK") -> OK
A7: INV000006 | B7: ORD000006 | C7: 46103 | D7: DSP0050 | E7: SKU0014 | F7: 48 | G7: 546.72 | H7: Partial | I7: =F7-IFERROR(VLOOKUP(B7,crm_orders!$A:$S,10,FALSE),0) -> -24 | J7: =G7-IFERROR(VLOOKUP(B7,crm_orders!$A:$S,12,FALSE),0) -> -273.36 | K7: =IF(COUNTIF(crm_orders!$A:$A,B7)=0,"Orphan","OK") -> OK
A8: INV000007 | B8: ORD000007 | C8: 46117 | D8: DSP0044 | E8: SKU0013 | F8: 18 | G8: 206.64 | H8: Posted | I8: =F8-IFERROR(VLOOKUP(B8,crm_orders!$A:$S,10,FALSE),0) -> 0 | J8: =G8-IFERROR(VLOOKUP(B8,crm_orders!$A:$S,12,FALSE),0) -> 0 | K8: =IF(COUNTIF(crm_orders!$A:$A,B8)=0,"Orphan","OK") -> OK
A9: INV000008 | B9: ORD000008 | C9: 46036 | D9: DSP0073 | E9: SKU0001 | F9: 132 | G9: 1301.52 | H9: Review | I9: =F9-IFERROR(VLOOKUP(B9,crm_orders!$A:$S,10,FALSE),0) -> 12 | J9: =G9-IFERROR(VLOOKUP(B9,crm_orders!$A:$S,12,FALSE),0) -> 118.32 | K9: =IF(COUNTIF(crm_orders!$A:$A,B9)=0,"Orphan","OK") -> OK
A10: INV000009 | B10: ORD000009 | C10: 46132 | D10: DSP0042 | E10: SKU0011 | F10: 48 | G10: 481.44 | H10: Posted | I10: =F10-IFERROR(VLOOKUP(B10,crm_orders!$A:$S,10,FALSE),0) -> 0 | J10: =G10-IFERROR(VLOOKUP(B10,crm_orders!$A:$S,12,FALSE),0) -> 0 | K10: =IF(COUNTIF(crm_orders!$A:$A,B10)=0,"Orphan","OK") -> OK
A11: INV000010 | B11: ORD000010 | C11: 46063 | D11: DSP0007 | E11: SKU0012 | F11: 120 | G11: 1150.8 | H11: Posted | I11: =F11-IFERROR(VLOOKUP(B11,crm_orders!$A:$S,10,FALSE),0) -> 0 | J11: =G11-IFERROR(VLOOKUP(B11,crm_orders!$A:$S,12,FALSE),0) -> 0 | K11: =IF(COUNTIF(crm_orders!$A:$A,B11)=0,"Orphan","OK") -> OK
A12: INV000011 | B12: ORD000011 | C12: 46045 | D12: DSP0003 | E12: SKU0020 | F12: 18 | G12: 129.06 | H12: Partial | I12: =F12-IFERROR(VLOOKUP(B12,crm_orders!$A:$S,10,FALSE),0) -> -6 | J12: =G12-IFERROR(VLOOKUP(B12,crm_orders!$A:$S,12,FALSE),0) -> -43.02 | K12: =IF(COUNTIF(crm_orders!$A:$A,B12)=0,"Orphan","OK") -> OK
A13: INV000012 | B13: ORD000012 | C13: 46107 | D13: DSP0048 | E13: SKU0006 | F13: 96 | G13: 1128 | H13: Posted | I13: =F13-IFERROR(VLOOKUP(B13,crm_orders!$A:$S,10,FALSE),0) -> 0 | J13: =G13-IFERROR(VLOOKUP(B13,crm_orders!$A:$S,12,FALSE),0) -> 0 | K13: =IF(COUNTIF(crm_orders!$A:$A,B13)=0,"Orphan","OK") -> OK
... A110: INV000109 | B110: ORD000116 | C110: 46047 | D110: DSP0068 | E110: SKU0014 | F110: 30 | G110: 305.7 | H110: Posted | I110: =F110-IFERROR(VLOOKUP(B110,crm_orders!$A:$S,10,FALSE),0) -> 0 | J110: =G110-IFERROR(VLOOKUP(B110,crm_orders!$A:$S,12,FALSE),0) -> 0 | K110: =IF(COUNTIF(crm_orders!$A:$A,B110)=0,"Orphan","OK") -> OK
A111: INV000110 | B111: ORD000117 | C111: 46109 | D111: DSP0116 | F111: 72 | G111: 487.44 | H111: Posted | I111: =F111-IFERROR(VLOOKUP(B111,crm_orders!$A:$S,10,FALSE),0) -> 0 | J111: =G111-IFERROR(VLOOKUP(B111,crm_orders!$A:$S,12,FALSE),0) -> 0 | K111: =IF(COUNTIF(crm_orders!$A:$A,B111)=0,"Orphan","OK") -> OK
A112: INV000111 | B112: ORD000118 | C112: 46109 | D112: DSP0046 | E112: SKU0008 | F112: 48 | G112: 483.84 | H112: Posted | I112: =F112-IFERROR(VLOOKUP(B112,crm_orders!$A:$S,10,FALSE),0) -> 0 | J112: =G112-IFERROR(VLOOKUP(B112,crm_orders!$A:$S,12,FALSE),0) -> 0 | K112: =IF(COUNTIF(crm_orders!$A:$A,B112)=0,"Orphan","OK") -> OK
A113: INV000112 | B113: ORD000119 | C113: 46106 | D113: DSP0065 | E113: SKU0017 | F113: 6 | G113: 44.04 | H113: Posted | I113: =F113-IFERROR(VLOOKUP(B113,crm_orders!$A:$S,10,FALSE),0) -> 0 | J113: =G113-IFERROR(VLOOKUP(B113,crm_orders!$A:$S,12,FALSE),0) -> 0 | K113: =IF(COUNTIF(crm_orders!$A:$A,B113)=0,"Orphan","OK") -> OK
A114: INV000113 | B114: ORD000121 | C114: 46130 | D114: DSP0044 | E114: SKU0006 | F114: 120 | G114: 1280.4 | H114: Posted | I114: =F114-IFERROR(VLOOKUP(B114,crm_orders!$A:$S,10,FALSE),0) -> 0 | J114: =G114-IFERROR(VLOOKUP(B114,crm_orders!$A:$S,12,FALSE),0) -> 0 | K114: =IF(COUNTIF(crm_orders!$A:$A,B114)=0,"Orphan","OK") -> OK
A115: INV000114 | B115: ORD000122 | C115: 46066 | D115: DSP0059 | E115: SKU0002 | F115: 24 | G115: 220.13 | H115: Review | I115: =F115-IFERROR(VLOOKUP(B115,crm_orders!$A:$S,10,FALSE),0) -> 0 | J115: =G115-IFERROR(VLOOKUP(B115,crm_orders!$A:$S,12,FALSE),0) -> -8.83 | K115: =IF(COUNTIF(crm_orders!$A:$A,B115)=0,"Orphan","OK") -> OK
A116: INV000115 | B116: ORD000123 | C116: 46065 | D116: DSP0070 | E116: SKU0016 | F116: 6 | G116: 47.28 | H116: Posted | I116: =F116-IFERROR(VLOOKUP(B116,crm_orders!$A:$S,10,FALSE),0) -> 0 | J116: =G116-IFERROR(VLOOKUP(B116,crm_orders!$A:$S,12,FALSE),0) -> 0 | K116: =IF(COUNTIF(crm_orders!$A:$A,B116)=0,"Orphan","OK") -> OK
A117: INV000116 | B117: ORD000124 | C117: 46085 | D117: DSP0016 | E117: SKU0012 | F117: 42 | G117: 461.31 | H117: Review | I117: =F117-IFERROR(VLOOKUP(B117,crm_orders!$A:$S,10,FALSE),0) -> -6 | J117: =G117-IFERROR(VLOOKUP(B117,crm_orders!$A:$S,12,FALSE),0) -> -67.17 | K117: =IF(COUNTIF(crm_orders!$A:$A,B117)=0,"Orphan","OK") -> OK
A118: INV000117 | B118: ORD000125 | C118: 46064 | D118: DSP0119 | E118: SKU0017 | F118: 12 | G118: 94.08 | H118: Posted | I118: =F118-IFERROR(VLOOKUP(B118,crm_orders!$A:$S,10,FALSE),0) -> 0 | J118: =G118-IFERROR(VLOOKUP(B118,crm_orders!$A:$S,12,FALSE),0) -> 0 | K118: =IF(COUNTIF(crm_orders!$A:$A,B118)=0,"Orphan","OK") -> OK
A119: INV000118 | B119: ORD000126 | C119: 46116 | D119: DSP0011 | E119: SKU0011 | F119: 30 | G119: 297.82 | H119: Review | I119: =F119-IFERROR(VLOOKUP(B119,crm_orders!$A:$S,10,FALSE),0) -> 0 | J119: =G119-IFERROR(VLOOKUP(B119,crm_orders!$A:$S,12,FALSE),0) -> -4.88 | K119: =IF(COUNTIF(crm_orders!$A:$A,B119)=0,"Orphan","OK") -> OK
A120: INV000119 | B120: ORD000127 | C120: 46109 | D120: DSP0112 | E120: SKU0012 | F120: 48 | G120: 481.44 | H120: Posted | I120: =F120-IFERROR(VLOOKUP(B120,crm_orders!$A:$S,10,FALSE),0) -> 0 | J120: =G120-IFERROR(VLOOKUP(B120,crm_orders!$A:$S,12,FALSE),0) -> 0 | K120: =IF(COUNTIF(crm_orders!$A:$A,B120)=0,"Orphan","OK") -> OK
A121: INV000120 | B121: ORD000128 | C121: 46036 | D121: DSP0066 | E121: SKU0006 | F121: 6 | G121: 66.82 | H121: Review | I121: =F121-IFERROR(VLOOKUP(B121,crm_orders!$A:$S,10,FALSE),0) -> -12 | J121: =G121-IFERROR(VLOOKUP(B121,crm_orders!$A:$S,12,FALSE),0) -> -140.18 | K121: =IF(COUNTIF(crm_orders!$A:$A,B121)=0,"Orphan","OK") -> OK
A122: INV000121 | B122: ORD000129 | C122: 46084 | D122: DSP0047 | E122: SKU0012 | F122: 96 | G122: 913.92 | H122: Posted | I122: =F122-IFERROR(VLOOKUP(B122,crm_orders!$A:$S,10,FALSE),0) -> 0 | J122: =G122-IFERROR(VLOOKUP(B122,crm_orders!$A:$S,12,FALSE),0) -> 0 | K122: =IF(COUNTIF(crm_orders!$A:$A,B122)=0,"Orphan","OK") -> OK
A123: INV000122 | B123: ORD000130 | C123: 46103 | D123: DSP0074 | E123: SKU0005 | F123: 36 | G123: 361.44 | H123: Posted | I123: =F123-IFERROR(VLOOKUP(B123,crm_orders!$A:$S,10,FALSE),0) -> 0 | J123: =G123-IFERROR(VLOOKUP(B123,crm_orders!$A:$S,12,FALSE),0) -> 0 | K123: =IF(COUNTIF(crm_orders!$A:$A,B123)=0,"Orphan","OK") -> OK
... A453: INV000452 | B453: ORD000494 | C453: 46139 | D453: DSP0071 | E453: SKU0011 | F453: 36 | G453: 371.52 | H453: Posted | I453: =F453-IFERROR(VLOOKUP(B453,crm_orders!$A:$S,10,FALSE),0) -> 0 | J453: =G453-IFERROR(VLOOKUP(B453,crm_orders!$A:$S,12,FALSE),0) -> 0 | K453: =IF(COUNTIF(crm_orders!$A:$A,B453)=0,"Orphan","OK") -> OK
A454: INV000453 | B454: ORD000495 | C454: 46133 | D454: DSP0028 | F454: 72 | G454: 828.58 | H454: Review | I454: =F454-IFERROR(VLOOKUP(B454,crm_orders!$A:$S,10,FALSE),0) -> 0 | J454: =G454-IFERROR(VLOOKUP(B454,crm_orders!$A:$S,12,FALSE),0) -> -11.66 | K454: =IF(COUNTIF(crm_orders!$A:$A,B454)=0,"Orphan","OK") -> OK
A455: INV000454 | B455: ORD000497 | C455: 46133 | D455: DSP0041 | E455: SKU0001 | F455: 30 | G455: 325.2 | H455: Posted | I455: =F455-IFERROR(VLOOKUP(B455,crm_orders!$A:$S,10,FALSE),0) -> 0 | J455: =G455-IFERROR(VLOOKUP(B455,crm_orders!$A:$S,12,FALSE),0) -> 0 | K455: =IF(COUNTIF(crm_orders!$A:$A,B455)=0,"Orphan","OK") -> OK
A456: INV000455 | B456: ORD000498 | C456: 46042 | D456: DSP0046 | E456: SKU0005 | F456: 30 | G456: 299.4 | H456: Posted | I456: =F456-IFERROR(VLOOKUP(B456,crm_orders!$A:$S,10,FALSE),0) -> 0 | J456: =G456-IFERROR(VLOOKUP(B456,crm_orders!$A:$S,12,FALSE),0) -> 0 | K456: =IF(COUNTIF(crm_orders!$A:$A,B456)=0,"Orphan","OK") -> OK
A457: INV000456 | B457: ORD000499 | C457: 46119 | D457: DSP0118 | E457: SKU0007 | F457: 12 | G457: 128.52 | H457: Posted | I457: =F457-IFERROR(VLOOKUP(B457,crm_orders!$A:$S,10,FALSE),0) -> 0 | J457: =G457-IFERROR(VLOOKUP(B457,crm_orders!$A:$S,12,FALSE),0) -> 0 | K457: =IF(COUNTIF(crm_orders!$A:$A,B457)=0,"Orphan","OK") -> OK
A458: INV000457 | B458: ORD000500 | C458: 46041 | D458: DSP0083 | E458: SKU0010 | F458: 96 | G458: 1031.04 | H458: Posted | I458: =F458-IFERROR(VLOOKUP(B458,crm_orders!$A:$S,10,FALSE),0) -> 0 | J458: =G458-IFERROR(VLOOKUP(B458,crm_orders!$A:$S,12,FALSE),0) -> 0 | K458: =IF(COUNTIF(crm_orders!$A:$A,B458)=0,"Orphan","OK") -> OK
A459: INV000458 | B459: ORD000501 | C459: 46139 | D459: DSP0054 | E459: SKU0004 | F459: 24 | G459: 270.72 | H459: Posted | I459: =F459-IFERROR(VLOOKUP(B459,crm_orders!$A:$S,10,FALSE),0) -> 0 | J459: =G459-IFERROR(VLOOKUP(B459,crm_orders!$A:$S,12,FALSE),0) -> 0 | K459: =IF(COUNTIF(crm_orders!$A:$A,B459)=0,"Orphan","OK") -> OK
A460: INV000459 | B460: ORD000502 | C460: 46096 | D460: DSP0041 | E460: SKU0018 | F460: 18 | G460: 126 | H460: Posted | I460: =F460-IFERROR(VLOOKUP(B460,crm_orders!$A:$S,10,FALSE),0) -> 0 | J460: =G460-IFERROR(VLOOKUP(B460,crm_orders!$A:$S,12,FALSE),0) -> 0 | K460: =IF(COUNTIF(crm_orders!$A:$A,B460)=0,"Orphan","OK") -> OK
A461: INV000460 | B461: ORD000503 | C461: 46046 | D461: DSP0074 | E461: SKU0017 | F461: 24 | G461: 177.6 | H461: Posted | I461: =F461-IFERROR(VLOOKUP(B461,crm_orders!$A:$S,10,FALSE),0) -> 0 | J461: =G461-IFERROR(VLOOKUP(B461,crm_orders!$A:$S,12,FALSE),0) -> 0 | K461: =IF(COUNTIF(crm_orders!$A:$A,B461)=0,"Orphan","OK") -> OK
A462: INV000461 | B462: ORD000505 | C462: 46076 | D462: DSP0026 | E462: SKU0016 | F462: 120 | G462: 913.2 | H462: Posted | I462: =F462-IFERROR(VLOOKUP(B462,crm_orders!$A:$S,10,FALSE),0) -> 0 | J462: =G462-IFERROR(VLOOKUP(B462,crm_orders!$A:$S,12,FALSE),0) -> 0 | K462: =IF(COUNTIF(crm_orders!$A:$A,B462)=0,"Orphan","OK") -> OK
A463: INV000462 | B463: ORD000507 | C463: 46109 | D463: DSP0045 | E463: SKU0020 | F463: 6 | G463: 49.02 | H463: Posted | I463: =F463-IFERROR(VLOOKUP(B463,crm_orders!$A:$S,10,FALSE),0) -> 0 | J463: =G463-IFERROR(VLOOKUP(B463,crm_orders!$A:$S,12,FALSE),0) -> 0 | K463: =IF(COUNTIF(crm_orders!$A:$A,B463)=0,"Orphan","OK") -> OK
A464: INV000463 | B464: ORD000508 | C464: 46050 | D464: DSP0119 | E464: SKU0008 | F464: 132 | G464: 1383.36 | H464: Review | I464: =F464-IFERROR(VLOOKUP(B464,crm_orders!$A:$S,10,FALSE),0) -> 12 | J464: =G464-IFERROR(VLOOKUP(B464,crm_orders!$A:$S,12,FALSE),0) -> 125.76 | K464: =IF(COUNTIF(crm_orders!$A:$A,B464)=0,"Orphan","OK") -> OK
A465: INV000464 | B465: ORD000509 | C465: 46146 | D465: DSP0080 | E465: SKU0005 | F465: 30 | G465: 277.5 | H465: Posted | I465: =F465-IFERROR(VLOOKUP(B465,crm_orders!$A:$S,10,FALSE),0) -> 0 | J465: =G465-IFERROR(VLOOKUP(B465,crm_orders!$A:$S,12,FALSE),0) -> 0 | K465: =IF(COUNTIF(crm_orders!$A:$A,B465)=0,"Orphan","OK") -> OK
A466: INV000465 | B466: ORD000510 | C466: 46056 | D466: DSP0095 | E466: SKU0018 | F466: 24 | G466: 175.68 | H466: Posted | I466: =F466-IFERROR(VLOOKUP(B466,crm_orders!$A:$S,10,FALSE),0) -> 0 | J466: =G466-IFERROR(VLOOKUP(B466,crm_orders!$A:$S,12,FALSE),0) -> 0 | K466: =IF(COUNTIF(crm_orders!$A:$A,B466)=0,"Orphan","OK") -> OK
... A671: INV000670 | B671: ORD000729 | C671: 46121 | D671: DSP0028 | E671: SKU0013 | F671: 48 | G671: 540.48 | H671: Posted | I671: =F671-IFERROR(VLOOKUP(B671,crm_orders!$A:$S,10,FALSE),0) -> 0 | J671: =G671-IFERROR(VLOOKUP(B671,crm_orders!$A:$S,12,FALSE),0) -> 0 | K671: =IF(COUNTIF(crm_orders!$A:$A,B671)=0,"Orphan","OK") -> OK
A672: INV000671 | B672: ORD000730 | C672: 46103 | E672: SKU0012 | F672: 96 | G672: 1102.08 | H672: Partial | I672: =F672-IFERROR(VLOOKUP(B672,crm_orders!$A:$S,10,FALSE),0) -> -24 | J672: =G672-IFERROR(VLOOKUP(B672,crm_orders!$A:$S,12,FALSE),0) -> -275.52 | K672: =IF(COUNTIF(crm_orders!$A:$A,B672)=0,"Orphan","OK") -> OK
A673: INV000672 | B673: ORD000731 | C673: 46087 | D673: DSP0049 | E673: SKU0010 | F673: 120 | G673: 1286.4 | H673: Posted | I673: =F673-IFERROR(VLOOKUP(B673,crm_orders!$A:$S,10,FALSE),0) -> 0 | J673: =G673-IFERROR(VLOOKUP(B673,crm_orders!$A:$S,12,FALSE),0) -> 0 | K673: =IF(COUNTIF(crm_orders!$A:$A,B673)=0,"Orphan","OK") -> OK
A674: INV000673 | B674: ORD000732 | C674: 46140 | D674: DSP0064 | E674: SKU0011 | F674: 60 | G674: 583.8 | H674: Posted | I674: =F674-IFERROR(VLOOKUP(B674,crm_orders!$A:$S,10,FALSE),0) -> 0 | J674: =G674-IFERROR(VLOOKUP(B674,crm_orders!$A:$S,12,FALSE),0) -> 0 | K674: =IF(COUNTIF(crm_orders!$A:$A,B674)=0,"Orphan","OK") -> OK
A675: INV000674 | B675: ORD000733 | C675: 46142 | D675: DSP0017 | E675: SKU0016 | F675: 30 | G675: 236.1 | H675: Posted | I675: =F675-IFERROR(VLOOKUP(B675,crm_orders!$A:$S,10,FALSE),0) -> 0 | J675: =G675-IFERROR(VLOOKUP(B675,crm_orders!$A:$S,12,FALSE),0) -> 0 | K675: =IF(COUNTIF(crm_orders!$A:$A,B675)=0,"Orphan","OK") -> OK
A676: INV000675 | B676: ORD000734 | C676: 46074 | D676: DSP0034 | E676: SKU0017 | F676: 48 | G676: 388.32 | H676: Posted | I676: =F676-IFERROR(VLOOKUP(B676,crm_orders!$A:$S,10,FALSE),0) -> 0 | J676: =G676-IFERROR(VLOOKUP(B676,crm_orders!$A:$S,12,FALSE),0) -> 0 | K676: =IF(COUNTIF(crm_orders!$A:$A,B676)=0,"Orphan","OK") -> OK
A677: INV000676 | B677: ORD000735 | C677: 46039 | D677: DSP0082 | E677: SKU0015 | F677: 24 | G677: 256.56 | H677: Posted | I677: =F677-IFERROR(VLOOKUP(B677,crm_orders!$A:$S,10,FALSE),0) -> 0 | J677: =G677-IFERROR(VLOOKUP(B677,crm_orders!$A:$S,12,FALSE),0) -> 0 | K677: =IF(COUNTIF(crm_orders!$A:$A,B677)=0,"Orphan","OK") -> OK
A678: INV000677 | B678: ORD000736 | C678: 46039 | D678: DSP0015 | E678: SKU0016 | F678: 60 | G678: 436.8 | H678: Posted | I678: =F678-IFERROR(VLOOKUP(B678,crm_orders!$A:$S,10,FALSE),0) -> 0 | J678: =G678-IFERROR(VLOOKUP(B678,crm_orders!$A:$S,12,FALSE),0) -> 0 | K678: =IF(COUNTIF(crm_orders!$A:$A,B678)=0,"Orphan","OK") -> OK
A679: INV000678 | B679: ORD000738 | C679: 46060 | D679: DSP0085 | E679: SKU0019 | F679: 90 | G679: 766.8 | H679: Partial | I679: =F679-IFERROR(VLOOKUP(B679,crm_orders!$A:$S,10,FALSE),0) -> -6 | J679: =G679-IFERROR(VLOOKUP(B679,crm_orders!$A:$S,12,FALSE),0) -> -51.12 | K679: =IF(COUNTIF(crm_orders!$A:$A,B679)=0,"Orphan","OK") -> OK
A680: INV000679 | B680: ORD000739 | C680: 46121 | D680: DSP0099 | E680: SKU0016 | F680: 12 | G680: 96.96 | H680: Posted | I680: =F680-IFERROR(VLOOKUP(B680,crm_orders!$A:$S,10,FALSE),0) -> 0 | J680: =G680-IFERROR(VLOOKUP(B680,crm_orders!$A:$S,12,FALSE),0) -> 0 | K680: =IF(COUNTIF(crm_orders!$A:$A,B680)=0,"Orphan","OK") -> OK
A681: INV000680 | B681: ORD000740 | C681: 46056 | D681: DSP0014 | E681: SKU0011 | F681: 6 | G681: 57.72 | H681: Posted | I681: =F681-IFERROR(VLOOKUP(B681,crm_orders!$A:$S,10,FALSE),0) -> 0 | J681: =G681-IFERROR(VLOOKUP(B681,crm_orders!$A:$S,12,FALSE),0) -> 0 | K681: =IF(COUNTIF(crm_orders!$A:$A,B681)=0,"Orphan","OK") -> OK
A682: INV000681 | B682: ORD000741 | C682: 46067 | D682: DSP0085 | E682: SKU0001 | F682: 0 | G682: 0 | H682: Partial | I682: =F682-IFERROR(VLOOKUP(B682,crm_orders!$A:$S,10,FALSE),0) -> -6 | J682: =G682-IFERROR(VLOOKUP(B682,crm_orders!$A:$S,12,FALSE),0) -> -61.86 | K682: =IF(COUNTIF(crm_orders!$A:$A,B682)=0,"Orphan","OK") -> OK
A683: INV000682 | B683: ORD000742 | C683: 46071 | D683: DSP0103 | E683: SKU0010 | F683: 6 | G683: 69.24 | H683: Posted | I683: =F683-IFERROR(VLOOKUP(B683,crm_orders!$A:$S,10,FALSE),0) -> 0 | J683: =G683-IFERROR(VLOOKUP(B683,crm_orders!$A:$S,12,FALSE),0) -> 0 | K683: =IF(COUNTIF(crm_orders!$A:$A,B683)=0,"Orphan","OK") -> OK
A684: INV000683 | B684: ORD000743 | C684: 46039 | D684: DSP0099 | E684: SKU0013 | F684: 6 | G684: 69.06 | H684: Posted | I684: =F684-IFERROR(VLOOKUP(B684,crm_orders!$A:$S,10,FALSE),0) -> 0 | J684: =G684-IFERROR(VLOOKUP(B684,crm_orders!$A:$S,12,FALSE),0) -> 0 | K684: =IF(COUNTIF(crm_orders!$A:$A,B684)=0,"Orphan","OK") -> OK
... A861: INV000860 | B861: ORD000937 | C861: 46108 | D861: DSP0003 | E861: SKU0013 | F861: 54 | G861: 613.44 | H861: Partial | I861: =F861-IFERROR(VLOOKUP(B861,crm_orders!$A:$S,10,FALSE),0) -> -18 | J861: =G861-IFERROR(VLOOKUP(B861,crm_orders!$A:$S,12,FALSE),0) -> -204.48 | K861: =IF(COUNTIF(crm_orders!$A:$A,B861)=0,"Orphan","OK") -> OK
A862: INV000861 | B862: ORD000938 | C862: 46129 | D862: DSP0084 | F862: 24 | G862: 282 | H862: Posted | I862: =F862-IFERROR(VLOOKUP(B862,crm_orders!$A:$S,10,FALSE),0) -> 0 | J862: =G862-IFERROR(VLOOKUP(B862,crm_orders!$A:$S,12,FALSE),0) -> 0 | K862: =IF(COUNTIF(crm_orders!$A:$A,B862)=0,"Orphan","OK") -> OK
A863: INV000862 | B863: ORD000939 | C863: 46045 | D863: DSP0058 | E863: SKU0011 | F863: 6 | G863: 58.32 | H863: Posted | I863: =F863-IFERROR(VLOOKUP(B863,crm_orders!$A:$S,10,FALSE),0) -> 0 | J863: =G863-IFERROR(VLOOKUP(B863,crm_orders!$A:$S,12,FALSE),0) -> 0 | K863: =IF(COUNTIF(crm_orders!$A:$A,B863)=0,"Orphan","OK") -> OK
A864: INV000863 | B864: ORD000940 | C864: 46092 | D864: DSP0011 | E864: SKU0004 | F864: 30 | G864: 313.8 | H864: Posted | I864: =F864-IFERROR(VLOOKUP(B864,crm_orders!$A:$S,10,FALSE),0) -> 0 | J864: =G864-IFERROR(VLOOKUP(B864,crm_orders!$A:$S,12,FALSE),0) -> 0 | K864: =IF(COUNTIF(crm_orders!$A:$A,B864)=0,"Orphan","OK") -> OK
A865: INV000864 | B865: ORD000941 | C865: 46120 | D865: DSP0067 | E865: SKU0010 | F865: 72 | G865: 783.36 | H865: Posted | I865: =F865-IFERROR(VLOOKUP(B865,crm_orders!$A:$S,10,FALSE),0) -> 0 | J865: =G865-IFERROR(VLOOKUP(B865,crm_orders!$A:$S,12,FALSE),0) -> 0 | K865: =IF(COUNTIF(crm_orders!$A:$A,B865)=0,"Orphan","OK") -> OK
A866: INV000865 | B866: ORD000942 | C866: 46101 | D866: DSP0078 | E866: SKU0018 | F866: 0 | G866: 0 | H866: Partial | I866: =F866-IFERROR(VLOOKUP(B866,crm_orders!$A:$S,10,FALSE),0) -> -24 | J866: =G866-IFERROR(VLOOKUP(B866,crm_orders!$A:$S,12,FALSE),0) -> -180.48 | K866: =IF(COUNTIF(crm_orders!$A:$A,B866)=0,"Orphan","OK") -> OK
A867: INV000866 | B867: ORD000943 | C867: 46048 | D867: DSP0107 | E867: SKU0007 | F867: 96 | G867: 994.56 | H867: Posted | I867: =F867-IFERROR(VLOOKUP(B867,crm_orders!$A:$S,10,FALSE),0) -> 0 | J867: =G867-IFERROR(VLOOKUP(B867,crm_orders!$A:$S,12,FALSE),0) -> 0 | K867: =IF(COUNTIF(crm_orders!$A:$A,B867)=0,"Orphan","OK") -> OK
A868: INV000867 | B868: ORD000944 | C868: 46118 | D868: DSP0034 | E868: SKU0013 | F868: 18 | G868: 189.72 | H868: Posted | I868: =F868-IFERROR(VLOOKUP(B868,crm_orders!$A:$S,10,FALSE),0) -> 0 | J868: =G868-IFERROR(VLOOKUP(B868,crm_orders!$A:$S,12,FALSE),0) -> 0 | K868: =IF(COUNTIF(crm_orders!$A:$A,B868)=0,"Orphan","OK") -> OK
A869: INV000868 | B869: ORD000945 | C869: 46110 | D869: DSP0027 | E869: SKU0003 | F869: 42 | G869: 507.78 | H869: Review | I869: =F869-IFERROR(VLOOKUP(B869,crm_orders!$A:$S,10,FALSE),0) -> 12 | J869: =G869-IFERROR(VLOOKUP(B869,crm_orders!$A:$S,12,FALSE),0) -> 145.08 | K869: =IF(COUNTIF(crm_orders!$A:$A,B869)=0,"Orphan","OK") -> OK
A870: INV000869 | B870: ORD000946 | C870: 46046 | D870: DSP0066 | E870: SKU0020 | F870: 48 | G870: 382.16 | H870: Review | I870: =F870-IFERROR(VLOOKUP(B870,crm_orders!$A:$S,10,FALSE),0) -> 0 | J870: =G870-IFERROR(VLOOKUP(B870,crm_orders!$A:$S,12,FALSE),0) -> -13.84 | K870: =IF(COUNTIF(crm_orders!$A:$A,B870)=0,"Orphan","OK") -> OK
A871: INV000870 | B871: ORD000947 | C871: 46043 | D871: DSP0010 | E871: SKU0009 | F871: 72 | G871: 746.64 | H871: Posted | I871: =F871-IFERROR(VLOOKUP(B871,crm_orders!$A:$S,10,FALSE),0) -> 0 | J871: =G871-IFERROR(VLOOKUP(B871,crm_orders!$A:$S,12,FALSE),0) -> 0 | K871: =IF(COUNTIF(crm_orders!$A:$A,B871)=0,"Orphan","OK") -> OK
A872: INV000871 | B872: ORD000948 | C872: 46145 | D872: DSP0035 | E872: SKU0005 | F872: 24 | G872: 234.96 | H872: Posted | I872: =F872-IFERROR(VLOOKUP(B872,crm_orders!$A:$S,10,FALSE),0) -> 0 | J872: =G872-IFERROR(VLOOKUP(B872,crm_orders!$A:$S,12,FALSE),0) -> 0 | K872: =IF(COUNTIF(crm_orders!$A:$A,B872)=0,"Orphan","OK") -> OK
A873: INV000872 | B873: ORD000949 | C873: 46046 | D873: DSP0119 | E873: SKU0004 | F873: 72 | G873: 809.28 | H873: Posted | I873: =F873-IFERROR(VLOOKUP(B873,crm_orders!$A:$S,10,FALSE),0) -> 0 | J873: =G873-IFERROR(VLOOKUP(B873,crm_orders!$A:$S,12,FALSE),0) -> 0 | K873: =IF(COUNTIF(crm_orders!$A:$A,B873)=0,"Orphan","OK") -> OK
A874: INV000873 | B874: ORD000950 | C874: 46102 | D874: DSP0074 | E874: SKU0010 | F874: 30 | G874: 337.2 | H874: Posted | I874: =F874-IFERROR(VLOOKUP(B874,crm_orders!$A:$S,10,FALSE),0) -> 0 | J874: =G874-IFERROR(VLOOKUP(B874,crm_orders!$A:$S,12,FALSE),0) -> 0 | K874: =IF(COUNTIF(crm_orders!$A:$A,B874)=0,"Orphan","OK") -> OK
... A935: INV000934 | B935: ORDX0014 | C935: 46128 | D935: DSP0078 | E935: SKU0015 | F935: 12 | G935: 138 | H935: Posted | I935: =F935-IFERROR(VLOOKUP(B935,crm_orders!$A:$S,10,FALSE),0) -> 12 | J935: =G935-IFERROR(VLOOKUP(B935,crm_orders!$A:$S,12,FALSE),0) -> 138 | K935: =IF(COUNTIF(crm_orders!$A:$A,B935)=0,"Orphan","OK") -> Orphan

Sheet reconciliation_summary
A1: Sales Ops Reconciliation Summary
A2: Compare CRM orders, ERP invoices, inventory flags, returns, and exception counts.
A3: Metric | B3: Formula / Value | C3: Status / Notes
A4: CRM Gross Sales | B4: =SUM(crm_orders!L:L) -> 472328.52 | C4: Total submitted CRM order value
A5: ERP Invoice Amount | B5: =SUM(erp_invoices!G:G) -> 429804.52 | C5: Total posted / reviewed invoice value
A6: Gross Sales Variance | B6: =B5-B4 -> -42524 | C6: ERP minus CRM
A7: Variance % of CRM | B7: =(B6/B4) -> -0.090030558 | C7: Should be investigated when material
A8: CRM Order Count | B8: =COUNTA(crm_orders!A:A)-1 -> 1000 | C8: Expected: 1,000 rows
A9: ERP Invoice Count | B9: =COUNTA(erp_invoices!A:A)-1 -> 934 | C9: Some orders intentionally not invoiced
A10: Open Exceptions | B10: =COUNTIF(exception_log!F:F,"Open") -> 116 | C10: Operational backlog
A11: Critical Exceptions | B11: =COUNTIF(exception_log!D:D,"Critical") -> 24 | C11: Highest priority
A12: Inventory Short Orders | B12: =COUNTIF(crm_orders!P:P,"Short") -> 3 | C12: Orders where available inventory < qty ordered
A13: Duplicate CRM Orders | B13: =COUNTIF(crm_orders!Q:Q,"Duplicate") -> 16 | C13: Duplicate order IDs
A14: Missing Key Orders | B14: =COUNTIF(crm_orders!R:R,"Missing Key") -> 5 | C14: Missing customer_id or sku
A15: Orphan ERP Invoice Count | B15: =COUNTIF(erp_invoices!K:K,"Orphan") -> 15 | C15: Invoices without matching CRM order
A16: Credit Memo Total | B16: =SUM(returns_credit_memos!E:E) -> -15112.55 | C16: Credits / returns reduce revenue
A18: Expanded Operational Controls
A19: Shipment Rows | B19: =COUNTA(warehouse_shipments!A:A)-1 -> 786 | C19: Shipment layer completeness
A20: OTIF Failures | B20: =COUNTIF(warehouse_shipments!L:L,"No") -> 615 | C20: Orders not on time and in full
A21: Compliance Holds | B21: =COUNTIF(order_compliance_review!J:J,"Yes") -> 238 | C21: Orders blocked by license/manifest/SKU rules
A22: AR Outstanding Balance | B22: =SUM(accounts_receivable!I:I) -> 149386.46 | C22: Uncollected invoice balance
A23: AR 90+ Count | B23: =COUNTIF(accounts_receivable!K:K,"90+") -> 26 | C23: Highest-risk receivables bucket
A24: Support Case Count | B24: =COUNTA(customer_support_cases!A:A)-1 -> 340 | C24: Customer-facing issue volume
A25: SLA Breach Count | B25: =COUNTIF(customer_support_cases!L:L,"Breach") -> 268 | C25: Open/closed cases outside SLA
A26: Crosswalk Review Count | B26: =COUNTIF(customer_crosswalk!G:G,"Review") -> 14 | C26: Customer master data mapping risk
A28: Rates
A29: Invoice Coverage Rate | B29: =B9/B8 -> 0.934
A30: Exception Rate of CRM Order Count | B30: =B10/B8 -> 0.116
A31: Critical Exception Rate | B31: =B11/B10 -> 0.20689655
A32: Credit Memo % of CRM | B32: =B16/B4 -> -0.031995845
A33: AR Outstanding % of Invoice Amount | B33: =B22/B5 -> 0.34756838
A34: OTIF Failure Rate | B34: =B20/B19 -> 0.78244275
A35: SLA Breach Rate | B35: =B25/B24 -> 0.78823529

Sheet sla_metrics
A1: SLA Metrics
A2: Operational speed and backlog health across order lifecycle.
A3: Metric | B3: Formula / Value | C3: Target | D3: Status | E3: Notes
A4: Avg hours to ship | B4: =AVERAGE(warehouse_shipments!N:N) -> 186.16794 | C4: 72 | D4: =IF(B4<=C4,"PASS","REVIEW") -> REVIEW | E4: Order date to ship date
A5: OTIF % | B5: =COUNTIF(warehouse_shipments!L:L,"Yes")/(COUNTA(warehouse_shipments!L:L)-1) -> 0.21755725 | C5: 0.85 | D5: =IF(B5>=C5,"PASS","REVIEW") -> REVIEW | E5: On-time and in-full rate
A6: Avg support hours to resolve | B6: =AVERAGE(customer_support_cases!K:K) -> 679.84118 | C6: 72 | D6: =IF(B6<=C6,"PASS","REVIEW") -> REVIEW | E6: Open cases age against SLA too
A7: Support SLA breach count | B7: =COUNTIF(customer_support_cases!L:L,"Breach") -> 268 | C7: 20 | D7: =IF(B7<=C7,"PASS","REVIEW") -> REVIEW | E7: Number of cases past SLA
A8: Open compliance holds | B8: =COUNTIF(order_compliance_review!J:J,"Yes") -> 238 | C8: 15 | D8: =IF(B8<=C8,"PASS","REVIEW") -> REVIEW | E8: Orders blocked by compliance
A9: Credit hold recommendations | B9: =COUNTIF(accounts_receivable!M:M,"Yes") -> 93 | C9: 25 | D9: =IF(B9<=C9,"PASS","REVIEW") -> REVIEW | E9: AR aging based credit risk

Sheet warehouse_shipments
A1: shipment_id | B1: order_id | C1: ship_date | D1: warehouse | E1: carrier | F1: tracking_number | G1: requested_units | H1: shipped_units | I1: short_ship_units | J1: on_time_flag | K1: in_full_flag | L1: otif_flag | M1: fulfillment_status | N1: hours_to_ship | O1: customer_id | P1: state | Q1: channel | R1: sku
A2: SHP000001 | B2: ORD000003 | C2: 46117 | D2: WHSE_OR | E2: FedEx | F2: TRK103295517 | G2: 30 | H2: 30 | I2: 0 | J2: No | K2: Yes | L2: No | M2: Shipped | N2: =IFERROR((C2-VLOOKUP(B2,crm_orders!$A:$S,2,FALSE))*24,0) -> 72 | O2: =IFERROR(VLOOKUP(B2,crm_orders!$A:$S,3,FALSE),"") -> DSP0057 | P2: =IFERROR(VLOOKUP(B2,crm_orders!$A:$S,5,FALSE),"") -> MO | Q2: =IFERROR(VLOOKUP(B2,crm_orders!$A:$S,7,FALSE),"") -> Distributor | R2: =IFERROR(VLOOKUP(B2,crm_orders!$A:$S,8,FALSE),"") -> SKU0003
A3: SHP000002 | B3: ORD000007 | C3: 46126 | D3: WHSE_CA | E3: USPS | F3: TRK938275454 | G3: 18 | H3: 18 | I3: 0 | J3: No | K3: Yes | L3: No | M3: Shipped | N3: =IFERROR((C3-VLOOKUP(B3,crm_orders!$A:$S,2,FALSE))*24,0) -> 264 | O3: =IFERROR(VLOOKUP(B3,crm_orders!$A:$S,3,FALSE),"") -> DSP0044 | P3: =IFERROR(VLOOKUP(B3,crm_orders!$A:$S,5,FALSE),"") -> MI | Q3: =IFERROR(VLOOKUP(B3,crm_orders!$A:$S,7,FALSE),"") -> Distributor | R3: =IFERROR(VLOOKUP(B3,crm_orders!$A:$S,8,FALSE),"") -> SKU0013
A4: SHP000003 | B4: ORD000008 | C4: 46043 | D4: WHSE_MW | E4: UPS | F4: TRK517409720 | G4: 120 | H4: 120 | I4: 0 | J4: No | K4: Yes | L4: No | M4: Shipped | N4: =IFERROR((C4-VLOOKUP(B4,crm_orders!$A:$S,2,FALSE))*24,0) -> 240 | O4: =IFERROR(VLOOKUP(B4,crm_orders!$A:$S,3,FALSE),"") -> DSP0073 | P4: =IFERROR(VLOOKUP(B4,crm_orders!$A:$S,5,FALSE),"") -> OR | Q4: =IFERROR(VLOOKUP(B4,crm_orders!$A:$S,7,FALSE),"") -> Wholesale | R4: =IFERROR(VLOOKUP(B4,crm_orders!$A:$S,8,FALSE),"") -> SKU0001
A5: SHP000004 | B5: ORD000009 | C5: 46123 | D5: WHSE_CA | E5: UPS | F5: TRK381941642 | G5: 48 | H5: 48 | I5: 0 | J5: No | K5: Yes | L5: No | M5: Shipped | N5: =IFERROR((C5-VLOOKUP(B5,crm_orders!$A:$S,2,FALSE))*24,0) -> 72 | O5: =IFERROR(VLOOKUP(B5,crm_orders!$A:$S,3,FALSE),"") -> DSP0042 | P5: =IFERROR(VLOOKUP(B5,crm_orders!$A:$S,5,FALSE),"") -> NV | Q5: =IFERROR(VLOOKUP(B5,crm_orders!$A:$S,7,FALSE),"") -> Wholesale | R5: =IFERROR(VLOOKUP(B5,crm_orders!$A:$S,8,FALSE),"") -> SKU0011
A6: SHP000005 | B6: ORD000010 | C6: 46054 | D6: WHSE_CO | E6: OnTrac | F6: TRK834504404 | G6: 120 | H6: 120 | I6: 0 | J6: No | K6: Yes | L6: No | M6: Shipped | N6: =IFERROR((C6-VLOOKUP(B6,crm_orders!$A:$S,2,FALSE))*24,0) -> 72 | O6: =IFERROR(VLOOKUP(B6,crm_orders!$A:$S,3,FALSE),"") -> DSP0007 | P6: =IFERROR(VLOOKUP(B6,crm_orders!$A:$S,5,FALSE),"") -> IL | Q6: =IFERROR(VLOOKUP(B6,crm_orders!$A:$S,7,FALSE),"") -> Wholesale | R6: =IFERROR(VLOOKUP(B6,crm_orders!$A:$S,8,FALSE),"") -> SKU0012
A7: SHP000006 | B7: ORD000011 | C7: 46047 | D7: WHSE_CO | E7: OnTrac | F7: TRK456854813 | G7: 24 | H7: 24 | I7: 0 | J7: No | K7: Yes | L7: No | M7: Shipped | N7: =IFERROR((C7-VLOOKUP(B7,crm_orders!$A:$S,2,FALSE))*24,0) -> 120 | O7: =IFERROR(VLOOKUP(B7,crm_orders!$A:$S,3,FALSE),"") -> DSP0003 | P7: =IFERROR(VLOOKUP(B7,crm_orders!$A:$S,5,FALSE),"") -> CA | Q7: =IFERROR(VLOOKUP(B7,crm_orders!$A:$S,7,FALSE),"") -> Wholesale | R7: =IFERROR(VLOOKUP(B7,crm_orders!$A:$S,8,FALSE),"") -> SKU0020
A8: SHP000007 | B8: ORD000014 | C8: 46051 | D8: WHSE_CA | E8: OnTrac | F8: TRK592115082 | G8: 30 | H8: 24 | I8: 6 | J8: No | K8: No | L8: No | M8: Short Shipped | N8: =IFERROR((C8-VLOOKUP(B8,crm_orders!$A:$S,2,FALSE))*24,0) -> 360 | O8: =IFERROR(VLOOKUP(B8,crm_orders!$A:$S,3,FALSE),"") -> DSP0081 | P8: =IFERROR(VLOOKUP(B8,crm_orders!$A:$S,5,FALSE),"") -> MO | Q8: =IFERROR(VLOOKUP(B8,crm_orders!$A:$S,7,FALSE),"") -> Wholesale | R8: =IFERROR(VLOOKUP(B8,crm_orders!$A:$S,8,FALSE),"") -> SKU0008
A9: SHP000008 | B9: ORD000016 | C9: 46118 | D9: WHSE_WA | E9: USPS | F9: TRK155479649 | G9: 18 | H9: 18 | I9: 0 | J9: Yes | K9: Yes | L9: Yes | M9: Shipped | N9: =IFERROR((C9-VLOOKUP(B9,crm_orders!$A:$S,2,FALSE))*24,0) -> 120 | O9: =IFERROR(VLOOKUP(B9,crm_orders!$A:$S,3,FALSE),"") -> DSP0082 | P9: =IFERROR(VLOOKUP(B9,crm_orders!$A:$S,5,FALSE),"") -> NM | Q9: =IFERROR(VLOOKUP(B9,crm_orders!$A:$S,7,FALSE),"") -> Distributor | R9: =IFERROR(VLOOKUP(B9,crm_orders!$A:$S,8,FALSE),"") -> SKU0015
A10: SHP000009 | B10: ORD000017 | C10: 46088 | D10: WHSE_WA | E10: FedEx | F10: TRK969495682 | G10: 48 | H10: 48 | I10: 0 | J10: No | K10: Yes | L10: No | M10: Shipped | N10: =IFERROR((C10-VLOOKUP(B10,crm_orders!$A:$S,2,FALSE))*24,0) -> 144 | O10: =IFERROR(VLOOKUP(B10,crm_orders!$A:$S,3,FALSE),"") -> DSP0100 | P10: =IFERROR(VLOOKUP(B10,crm_orders!$A:$S,5,FALSE),"") -> CO | Q10: =IFERROR(VLOOKUP(B10,crm_orders!$A:$S,7,FALSE),"") -> Wholesale | R10: =IFERROR(VLOOKUP(B10,crm_orders!$A:$S,8,FALSE),"") -> SKU0016
A11: SHP000010 | B11: ORD000018 | C11: 46063 | D11: WHSE_CO | E11: UPS | F11: TRK147692456 | G11: 60 | H11: 60 | I11: 0 | J11: No | K11: Yes | L11: No | M11: Shipped | N11: =IFERROR((C11-VLOOKUP(B11,crm_orders!$A:$S,2,FALSE))*24,0) -> 216 | O11: =IFERROR(VLOOKUP(B11,crm_orders!$A:$S,3,FALSE),"") -> DSP0113 | P11: =IFERROR(VLOOKUP(B11,crm_orders!$A:$S,5,FALSE),"") -> AZ | Q11: =IFERROR(VLOOKUP(B11,crm_orders!$A:$S,7,FALSE),"") -> Wholesale | R11: =IFERROR(VLOOKUP(B11,crm_orders!$A:$S,8,FALSE),"") -> SKU0015
A12: SHP000011 | B12: ORD000019 | C12: 46132 | D12: WHSE_OR | E12: OnTrac | F12: TRK702198472 | G12: 30 | H12: 30 | I12: 0 | J12: No | K12: Yes | L12: No | M12: Shipped | N12: =IFERROR((C12-VLOOKUP(B12,crm_orders!$A:$S,2,FALSE))*24,0) -> 168 | O12: =IFERROR(VLOOKUP(B12,crm_orders!$A:$S,3,FALSE),"") -> DSP0028 | P12: =IFERROR(VLOOKUP(B12,crm_orders!$A:$S,5,FALSE),"") -> CO | Q12: =IFERROR(VLOOKUP(B12,crm_orders!$A:$S,7,FALSE),"") -> Retail | R12: =IFERROR(VLOOKUP(B12,crm_orders!$A:$S,8,FALSE),"") -> SKU0012
A13: SHP000012 | B13: ORD000020 | C13: 46063 | D13: WHSE_CO | E13: UPS | F13: TRK806139531 | G13: 48 | H13: 42 | I13: 6 | J13: No | K13: No | L13: No | M13: Short Shipped | N13: =IFERROR((C13-VLOOKUP(B13,crm_orders!$A:$S,2,FALSE))*24,0) -> 240 | O13: =IFERROR(VLOOKUP(B13,crm_orders!$A:$S,3,FALSE),"") -> DSP0025 | P13: =IFERROR(VLOOKUP(B13,crm_orders!$A:$S,5,FALSE),"") -> OR | Q13: =IFERROR(VLOOKUP(B13,crm_orders!$A:$S,7,FALSE),"") -> Retail | R13: =IFERROR(VLOOKUP(B13,crm_orders!$A:$S,8,FALSE),"") -> SKU0003
... A787: SHP000786 | B787: ORD001000 | C787: 46103 | D787: WHSE_CO | E787: Regional Courier | F787: TRK828456114 | G787: 24 | H787: 24 | I787: 0 | J787: No | K787: Yes | L787: No | M787: Shipped | N787: =IFERROR((C787-VLOOKUP(B787,crm_orders!$A:$S,2,FALSE))*24,0) -> 288 | O787: =IFERROR(VLOOKUP(B787,crm_orders!$A:$S,3,FALSE),"") -> DSP0069 | P787: =IFERROR(VLOOKUP(B787,crm_orders!$A:$S,5,FALSE),"") -> MO | Q787: =IFERROR(VLOOKUP(B787,crm_orders!$A:$S,7,FALSE),"") -> Wholesale | R787: =IFERROR(VLOOKUP(B787,crm_orders!$A:$S,8,FALSE),"") -> SKU0016

Sheet accounts_receivable
A1: invoice_id | B1: order_id | C1: customer_id | D1: invoice_date | E1: due_date | F1: invoice_amount | G1: paid_date | H1: payment_amount | I1: outstanding_balance | J1: days_past_due | K1: aging_bucket | L1: collections_status | M1: credit_hold_recommendation
A2: INV000001 | B2: ORD000001 | C2: DSP0072 | D2: 46065 | E2: 46095 | F2: 522.72 | G2: 46135 | H2: 522.72 | I2: =F2-H2 -> 0 | J2: =MAX(0,TODAY()-E2) -> 63 | K2: =IF(I2=0,"Paid",IF(J2<=30,"0-30",IF(J2<=60,"31-60",IF(J2<=90,"61-90","90+")))) -> Paid | L2: =IF(I2=0,"Closed",IF(J2>90,"Escalate",IF(J2>60,"Collections Review",IF(J2>30,"Reminder Sent","Current")))) -> Closed | M2: =IF(OR(K2="61-90",K2="90+"),"Yes","No") -> No
A3: INV000002 | B3: ORD000002 | C3: DSP0111 | D3: 46083 | E3: 46113 | F3: 236.4 | H3: 0 | I3: =F3-H3 -> 236.4 | J3: =MAX(0,TODAY()-E3) -> 45 | K3: =IF(I3=0,"Paid",IF(J3<=30,"0-30",IF(J3<=60,"31-60",IF(J3<=90,"61-90","90+")))) -> 31-60 | L3: =IF(I3=0,"Closed",IF(J3>90,"Escalate",IF(J3>60,"Collections Review",IF(J3>30,"Reminder Sent","Current")))) -> Reminder Sent | M3: =IF(OR(K3="61-90",K3="90+"),"Yes","No") -> No
A4: INV000003 | B4: ORD000003 | C4: DSP0057 | D4: 46128 | E4: 46143 | F4: 312.6 | G4: 46160 | H4: 312.6 | I4: =F4-H4 -> 0 | J4: =MAX(0,TODAY()-E4) -> 15 | K4: =IF(I4=0,"Paid",IF(J4<=30,"0-30",IF(J4<=60,"31-60",IF(J4<=90,"61-90","90+")))) -> Paid | L4: =IF(I4=0,"Closed",IF(J4>90,"Escalate",IF(J4>60,"Collections Review",IF(J4>30,"Reminder Sent","Current")))) -> Closed | M4: =IF(OR(K4="61-90",K4="90+"),"Yes","No") -> No
A5: INV000004 | B5: ORD000004 | C5: DSP0089 | D5: 46122 | E5: 46152 | F5: 224.64 | H5: 0 | I5: =F5-H5 -> 224.64 | J5: =MAX(0,TODAY()-E5) -> 6 | K5: =IF(I5=0,"Paid",IF(J5<=30,"0-30",IF(J5<=60,"31-60",IF(J5<=90,"61-90","90+")))) -> 0-30 | L5: =IF(I5=0,"Closed",IF(J5>90,"Escalate",IF(J5>60,"Collections Review",IF(J5>30,"Reminder Sent","Current")))) -> Current | M5: =IF(OR(K5="61-90",K5="90+"),"Yes","No") -> No
A6: INV000005 | B6: ORD000005 | C6: DSP0050 | D6: 46113 | E6: 46143 | F6: 49.8 | G6: 46155 | H6: 49.8 | I6: =F6-H6 -> 0 | J6: =MAX(0,TODAY()-E6) -> 15 | K6: =IF(I6=0,"Paid",IF(J6<=30,"0-30",IF(J6<=60,"31-60",IF(J6<=90,"61-90","90+")))) -> Paid | L6: =IF(I6=0,"Closed",IF(J6>90,"Escalate",IF(J6>60,"Collections Review",IF(J6>30,"Reminder Sent","Current")))) -> Closed | M6: =IF(OR(K6="61-90",K6="90+"),"Yes","No") -> No
A7: INV000006 | B7: ORD000006 | C7: DSP0050 | D7: 46103 | E7: 46133 | F7: 546.72 | H7: 0 | I7: =F7-H7 -> 546.72 | J7: =MAX(0,TODAY()-E7) -> 25 | K7: =IF(I7=0,"Paid",IF(J7<=30,"0-30",IF(J7<=60,"31-60",IF(J7<=90,"61-90","90+")))) -> 0-30 | L7: =IF(I7=0,"Closed",IF(J7>90,"Escalate",IF(J7>60,"Collections Review",IF(J7>30,"Reminder Sent","Current")))) -> Current | M7: =IF(OR(K7="61-90",K7="90+"),"Yes","No") -> No
A8: INV000007 | B8: ORD000007 | C8: DSP0044 | D8: 46117 | E8: 46132 | F8: 206.64 | G8: 46147 | H8: 206.64 | I8: =F8-H8 -> 0 | J8: =MAX(0,TODAY()-E8) -> 26 | K8: =IF(I8=0,"Paid",IF(J8<=30,"0-30",IF(J8<=60,"31-60",IF(J8<=90,"61-90","90+")))) -> Paid | L8: =IF(I8=0,"Closed",IF(J8>90,"Escalate",IF(J8>60,"Collections Review",IF(J8>30,"Reminder Sent","Current")))) -> Closed | M8: =IF(OR(K8="61-90",K8="90+"),"Yes","No") -> No
A9: INV000008 | B9: ORD000008 | C9: DSP0073 | D9: 46036 | E9: 46066 | F9: 1301.52 | H9: 0 | I9: =F9-H9 -> 1301.52 | J9: =MAX(0,TODAY()-E9) -> 92 | K9: =IF(I9=0,"Paid",IF(J9<=30,"0-30",IF(J9<=60,"31-60",IF(J9<=90,"61-90","90+")))) -> 90+ | L9: =IF(I9=0,"Closed",IF(J9>90,"Escalate",IF(J9>60,"Collections Review",IF(J9>30,"Reminder Sent","Current")))) -> Escalate | M9: =IF(OR(K9="61-90",K9="90+"),"Yes","No") -> Yes
A10: INV000009 | B10: ORD000009 | C10: DSP0042 | D10: 46132 | E10: 46147 | F10: 481.44 | G10: 46189 | H10: 481.44 | I10: =F10-H10 -> 0 | J10: =MAX(0,TODAY()-E10) -> 11 | K10: =IF(I10=0,"Paid",IF(J10<=30,"0-30",IF(J10<=60,"31-60",IF(J10<=90,"61-90","90+")))) -> Paid | L10: =IF(I10=0,"Closed",IF(J10>90,"Escalate",IF(J10>60,"Collections Review",IF(J10>30,"Reminder Sent","Current")))) -> Closed | M10: =IF(OR(K10="61-90",K10="90+"),"Yes","No") -> No
A11: INV000010 | B11: ORD000010 | C11: DSP0007 | D11: 46063 | E11: 46108 | F11: 1150.8 | H11: 0 | I11: =F11-H11 -> 1150.8 | J11: =MAX(0,TODAY()-E11) -> 50 | K11: =IF(I11=0,"Paid",IF(J11<=30,"0-30",IF(J11<=60,"31-60",IF(J11<=90,"61-90","90+")))) -> 31-60 | L11: =IF(I11=0,"Closed",IF(J11>90,"Escalate",IF(J11>60,"Collections Review",IF(J11>30,"Reminder Sent","Current")))) -> Reminder Sent | M11: =IF(OR(K11="61-90",K11="90+"),"Yes","No") -> No
A12: INV000011 | B12: ORD000011 | C12: DSP0003 | D12: 46045 | E12: 46075 | F12: 129.06 | H12: 0 | I12: =F12-H12 -> 129.06 | J12: =MAX(0,TODAY()-E12) -> 83 | K12: =IF(I12=0,"Paid",IF(J12<=30,"0-30",IF(J12<=60,"31-60",IF(J12<=90,"61-90","90+")))) -> 61-90 | L12: =IF(I12=0,"Closed",IF(J12>90,"Escalate",IF(J12>60,"Collections Review",IF(J12>30,"Reminder Sent","Current")))) -> Collections Review | M12: =IF(OR(K12="61-90",K12="90+"),"Yes","No") -> Yes
A13: INV000012 | B13: ORD000012 | C13: DSP0048 | D13: 46107 | E13: 46137 | F13: 1128 | G13: 46150 | H13: 1128 | I13: =F13-H13 -> 0 | J13: =MAX(0,TODAY()-E13) -> 21 | K13: =IF(I13=0,"Paid",IF(J13<=30,"0-30",IF(J13<=60,"31-60",IF(J13<=90,"61-90","90+")))) -> Paid | L13: =IF(I13=0,"Closed",IF(J13>90,"Escalate",IF(J13>60,"Collections Review",IF(J13>30,"Reminder Sent","Current")))) -> Closed | M13: =IF(OR(K13="61-90",K13="90+"),"Yes","No") -> No
A14: INV000013 | B14: ORD000013 | C14: DSP0004 | D14: 46110 | E14: 46140 | F14: 1428 | G14: 46173 | H14: 1120.4 | I14: =F14-H14 -> 307.6 | J14: =MAX(0,TODAY()-E14) -> 18 | K14: =IF(I14=0,"Paid",IF(J14<=30,"0-30",IF(J14<=60,"31-60",IF(J14<=90,"61-90","90+")))) -> 0-30 | L14: =IF(I14=0,"Closed",IF(J14>90,"Escalate",IF(J14>60,"Collections Review",IF(J14>30,"Reminder Sent","Current")))) -> Current | M14: =IF(OR(K14="61-90",K14="90+"),"Yes","No") -> No
A15: INV000014 | B15: ORD000014 | C15: DSP0081 | D15: 46039 | E15: 46084 | F15: 345 | G15: 46086 | H15: 345 | I15: =F15-H15 -> 0 | J15: =MAX(0,TODAY()-E15) -> 74 | K15: =IF(I15=0,"Paid",IF(J15<=30,"0-30",IF(J15<=60,"31-60",IF(J15<=90,"61-90","90+")))) -> Paid | L15: =IF(I15=0,"Closed",IF(J15>90,"Escalate",IF(J15>60,"Collections Review",IF(J15>30,"Reminder Sent","Current")))) -> Closed | M15: =IF(OR(K15="61-90",K15="90+"),"Yes","No") -> No
A16: INV000015 | B16: ORD000015 | C16: DSP0055 | D16: 46043 | E16: 46073 | F16: 778.32 | G16: 46067 | H16: 778.32 | I16: =F16-H16 -> 0 | J16: =MAX(0,TODAY()-E16) -> 85 | K16: =IF(I16=0,"Paid",IF(J16<=30,"0-30",IF(J16<=60,"31-60",IF(J16<=90,"61-90","90+")))) -> Paid | L16: =IF(I16=0,"Closed",IF(J16>90,"Escalate",IF(J16>60,"Collections Review",IF(J16>30,"Reminder Sent","Current")))) -> Closed | M16: =IF(OR(K16="61-90",K16="90+"),"Yes","No") -> No
A17: INV000016 | B17: ORD000016 | C17: DSP0082 | D17: 46125 | E17: 46140 | F17: 204.3 | G17: 46184 | H17: 204.3 | I17: =F17-H17 -> 0 | J17: =MAX(0,TODAY()-E17) -> 18 | K17: =IF(I17=0,"Paid",IF(J17<=30,"0-30",IF(J17<=60,"31-60",IF(J17<=90,"61-90","90+")))) -> Paid | L17: =IF(I17=0,"Closed",IF(J17>90,"Escalate",IF(J17>60,"Collections Review",IF(J17>30,"Reminder Sent","Current")))) -> Closed | M17: =IF(OR(K17="61-90",K17="90+"),"Yes","No") -> No
A18: INV000017 | B18: ORD000017 | C18: DSP0100 | D18: 46090 | E18: 46135 | F18: 383.52 | G18: 46172 | H18: 383.52 | I18: =F18-H18 -> 0 | J18: =MAX(0,TODAY()-E18) -> 23 | K18: =IF(I18=0,"Paid",IF(J18<=30,"0-30",IF(J18<=60,"31-60",IF(J18<=90,"61-90","90+")))) -> Paid | L18: =IF(I18=0,"Closed",IF(J18>90,"Escalate",IF(J18>60,"Collections Review",IF(J18>30,"Reminder Sent","Current")))) -> Closed | M18: =IF(OR(K18="61-90",K18="90+"),"Yes","No") -> No
A19: INV000018 | B19: ORD000018 | C19: DSP0113 | D19: 46067 | E19: 46097 | F19: 699.6 | G19: 46119 | H19: 699.6 | I19: =F19-H19 -> 0 | J19: =MAX(0,TODAY()-E19) -> 61 | K19: =IF(I19=0,"Paid",IF(J19<=30,"0-30",IF(J19<=60,"31-60",IF(J19<=90,"61-90","90+")))) -> Paid | L19: =IF(I19=0,"Closed",IF(J19>90,"Escalate",IF(J19>60,"Collections Review",IF(J19>30,"Reminder Sent","Current")))) -> Closed | M19: =IF(OR(K19="61-90",K19="90+"),"Yes","No") -> No
A20: INV000019 | B20: ORD000019 | C20: DSP0028 | D20: 46131 | E20: 46161 | F20: 299.49 | H20: 0 | I20: =F20-H20 -> 299.49 | J20: =MAX(0,TODAY()-E20) -> 0 | K20: =IF(I20=0,"Paid",IF(J20<=30,"0-30",IF(J20<=60,"31-60",IF(J20<=90,"61-90","90+")))) -> 0-30 | L20: =IF(I20=0,"Closed",IF(J20>90,"Escalate",IF(J20>60,"Collections Review",IF(J20>30,"Reminder Sent","Current")))) -> Current | M20: =IF(OR(K20="61-90",K20="90+"),"Yes","No") -> No
A21: INV000020 | B21: ORD000020 | C21: DSP0025 | D21: 46055 | E21: 46070 | F21: 658.2 | G21: 46094 | H21: 658.2 | I21: =F21-H21 -> 0 | J21: =MAX(0,TODAY()-E21) -> 88 | K21: =IF(I21=0,"Paid",IF(J21<=30,"0-30",IF(J21<=60,"31-60",IF(J21<=90,"61-90","90+")))) -> Paid | L21: =IF(I21=0,"Closed",IF(J21>90,"Escalate",IF(J21>60,"Collections Review",IF(J21>30,"Reminder Sent","Current")))) -> Closed | M21: =IF(OR(K21="61-90",K21="90+"),"Yes","No") -> No
A22: INV000021 | B22: ORD000021 | C22: DSP0038 | D22: 46075 | E22: 46105 | F22: 247.92 | G22: 46097 | H22: 247.92 | I22: =F22-H22 -> 0 | J22: =MAX(0,TODAY()-E22) -> 53 | K22: =IF(I22=0,"Paid",IF(J22<=30,"0-30",IF(J22<=60,"31-60",IF(J22<=90,"61-90","90+")))) -> Paid | L22: =IF(I22=0,"Closed",IF(J22>90,"Escalate",IF(J22>60,"Collections Review",IF(J22>30,"Reminder Sent","Current")))) -> Closed | M22: =IF(OR(K22="61-90",K22="90+"),"Yes","No") -> No
A23: INV000022 | B23: ORD000023 | C23: DSP0098 | D23: 46055 | E23: 46100 | F23: 67.56 | G23: 46117 | H23: 67.56 | I23: =F23-H23 -> 0 | J23: =MAX(0,TODAY()-E23) -> 58 | K23: =IF(I23=0,"Paid",IF(J23<=30,"0-30",IF(J23<=60,"31-60",IF(J23<=90,"61-90","90+")))) -> Paid | L23: =IF(I23=0,"Closed",IF(J23>90,"Escalate",IF(J23>60,"Collections Review",IF(J23>30,"Reminder Sent","Current")))) -> Closed | M23: =IF(OR(K23="61-90",K23="90+"),"Yes","No") -> No
A24: INV000023 | B24: ORD000024 | C24: DSP0107 | D24: 46073 | E24: 46088 | F24: 239.04 | G24: 46099 | H24: 239.04 | I24: =F24-H24 -> 0 | J24: =MAX(0,TODAY()-E24) -> 70 | K24: =IF(I24=0,"Paid",IF(J24<=30,"0-30",IF(J24<=60,"31-60",IF(J24<=90,"61-90","90+")))) -> Paid | L24: =IF(I24=0,"Closed",IF(J24>90,"Escalate",IF(J24>60,"Collections Review",IF(J24>30,"Reminder Sent","Current")))) -> Closed | M24: =IF(OR(K24="61-90",K24="90+"),"Yes","No") -> No
A25: INV000024 | B25: ORD000025 | C25: DSP0071 | D25: 46124 | E25: 46154 | F25: 203.4 | G25: 46177 | H25: 203.4 | I25: =F25-H25 -> 0 | J25: =MAX(0,TODAY()-E25) -> 4 | K25: =IF(I25=0,"Paid",IF(J25<=30,"0-30",IF(J25<=60,"31-60",IF(J25<=90,"61-90","90+")))) -> Paid | L25: =IF(I25=0,"Closed",IF(J25>90,"Escalate",IF(J25>60,"Collections Review",IF(J25>30,"Reminder Sent","Current")))) -> Closed | M25: =IF(OR(K25="61-90",K25="90+"),"Yes","No") -> No
A26: INV000025 | B26: ORD000026 | C26: DSP0057 | D26: 46058 | E26: 46088 | F26: 59.88 | H26: 0 | I26: =F26-H26 -> 59.88 | J26: =MAX(0,TODAY()-E26) -> 70 | K26: =IF(I26=0,"Paid",IF(J26<=30,"0-30",IF(J26<=60,"31-60",IF(J26<=90,"61-90","90+")))) -> 61-90 | L26: =IF(I26=0,"Closed",IF(J26>90,"Escalate",IF(J26>60,"Collections Review",IF(J26>30,"Reminder Sent","Current")))) -> Collections Review | M26: =IF(OR(K26="61-90",K26="90+"),"Yes","No") -> Yes
A27: INV000026 | B27: ORD000028 | C27: DSP0078 | D27: 46132 | E27: 46147 | F27: 702.72 | H27: 0 | I27: =F27-H27 -> 702.72 | J27: =MAX(0,TODAY()-E27) -> 11 | K27: =IF(I27=0,"Paid",IF(J27<=30,"0-30",IF(J27<=60,"31-60",IF(J27<=90,"61-90","90+")))) -> 0-30 | L27: =IF(I27=0,"Closed",IF(J27>90,"Escalate",IF(J27>60,"Collections Review",IF(J27>30,"Reminder Sent","Current")))) -> Current | M27: =IF(OR(K27="61-90",K27="90+"),"Yes","No") -> No
A28: INV000027 | B28: ORD000029 | C28: DSP0055 | D28: 46103 | E28: 46118 | F28: 902.7 | G28: 46135 | H28: 902.7 | I28: =F28-H28 -> 0 | J28: =MAX(0,TODAY()-E28) -> 40 | K28: =IF(I28=0,"Paid",IF(J28<=30,"0-30",IF(J28<=60,"31-60",IF(J28<=90,"61-90","90+")))) -> Paid | L28: =IF(I28=0,"Closed",IF(J28>90,"Escalate",IF(J28>60,"Collections Review",IF(J28>30,"Reminder Sent","Current")))) -> Closed | M28: =IF(OR(K28="61-90",K28="90+"),"Yes","No") -> No
A29: INV000028 | B29: ORD000030 | C29: DSP0011 | D29: 46064 | E29: 46094 | F29: 195.48 | G29: 46129 | H29: 195.48 | I29: =F29-H29 -> 0 | J29: =MAX(0,TODAY()-E29) -> 64 | K29: =IF(I29=0,"Paid",IF(J29<=30,"0-30",IF(J29<=60,"31-60",IF(J29<=90,"61-90","90+")))) -> Paid | L29: =IF(I29=0,"Closed",IF(J29>90,"Escalate",IF(J29>60,"Collections Review",IF(J29>30,"Reminder Sent","Current")))) -> Closed | M29: =IF(OR(K29="61-90",K29="90+"),"Yes","No") -> No
A30: INV000029 | B30: ORD000031 | C30: DSP0037 | D30: 46121 | E30: 46166 | F30: 603.6 | G30: 46196 | H30: 603.6 | I30: =F30-H30 -> 0 | J30: =MAX(0,TODAY()-E30) -> 0 | K30: =IF(I30=0,"Paid",IF(J30<=30,"0-30",IF(J30<=60,"31-60",IF(J30<=90,"61-90","90+")))) -> Paid | L30: =IF(I30=0,"Closed",IF(J30>90,"Escalate",IF(J30>60,"Collections Review",IF(J30>30,"Reminder Sent","Current")))) -> Closed | M30: =IF(OR(K30="61-90",K30="90+"),"Yes","No") -> No
A31: INV000030 | B31: ORD000032 | C31: DSP0055 | D31: 46100 | E31: 46115 | F31: 265.68 | G31: 46139 | H31: 265.68 | I31: =F31-H31 -> 0 | J31: =MAX(0,TODAY()-E31) -> 43 | K31: =IF(I31=0,"Paid",IF(J31<=30,"0-30",IF(J31<=60,"31-60",IF(J31<=90,"61-90","90+")))) -> Paid | L31: =IF(I31=0,"Closed",IF(J31>90,"Escalate",IF(J31>60,"Collections Review",IF(J31>30,"Reminder Sent","Current")))) -> Closed | M31: =IF(OR(K31="61-90",K31="90+"),"Yes","No") -> No
A32: INV000031 | B32: ORD000033 | C32: DSP0077 | D32: 46147 | E32: 46192 | F32: 45.96 | G32: 46208 | H32: 45.96 | I32: =F32-H32 -> 0 | J32: =MAX(0,TODAY()-E32) -> 0 | K32: =IF(I32=0,"Paid",IF(J32<=30,"0-30",IF(J32<=60,"31-60",IF(J32<=90,"61-90","90+")))) -> Paid | L32: =IF(I32=0,"Closed",IF(J32>90,"Escalate",IF(J32>60,"Collections Review",IF(J32>30,"Reminder Sent","Current")))) -> Closed | M32: =IF(OR(K32="61-90",K32="90+"),"Yes","No") -> No
A33: INV000032 | B33: ORD000034 | C33: DSP0064 | D33: 46036 | E33: 46051 | F33: 1002.24 | G33: 46071 | H33: 1002.24 | I33: =F33-H33 -> 0 | J33: =MAX(0,TODAY()-E33) -> 107 | K33: =IF(I33=0,"Paid",IF(J33<=30,"0-30",IF(J33<=60,"31-60",IF(J33<=90,"61-90","90+")))) -> Paid | L33: =IF(I33=0,"Closed",IF(J33>90,"Escalate",IF(J33>60,"Collections Review",IF(J33>30,"Reminder Sent","Current")))) -> Closed | M33: =IF(OR(K33="61-90",K33="90+"),"Yes","No") -> No
A34: INV000033 | B34: ORD000036 | C34: DSP0067 | D34: 46145 | E34: 46175 | F34: 323.1 | H34: 0 | I34: =F34-H34 -> 323.1 | J34: =MAX(0,TODAY()-E34) -> 0 | K34: =IF(I34=0,"Paid",IF(J34<=30,"0-30",IF(J34<=60,"31-60",IF(J34<=90,"61-90","90+")))) -> 0-30 | L34: =IF(I34=0,"Closed",IF(J34>90,"Escalate",IF(J34>60,"Collections Review",IF(J34>30,"Reminder Sent","Current")))) -> Current | M34: =IF(OR(K34="61-90",K34="90+"),"Yes","No") -> No
A35: INV000034 | B35: ORD000038 | C35: DSP0105 | D35: 46033 | E35: 46063 | F35: 399 | H35: 0 | I35: =F35-H35 -> 399 | J35: =MAX(0,TODAY()-E35) -> 95 | K35: =IF(I35=0,"Paid",IF(J35<=30,"0-30",IF(J35<=60,"31-60",IF(J35<=90,"61-90","90+")))) -> 90+ | L35: =IF(I35=0,"Closed",IF(J35>90,"Escalate",IF(J35>60,"Collections Review",IF(J35>30,"Reminder Sent","Current")))) -> Escalate | M35: =IF(OR(K35="61-90",K35="90+"),"Yes","No") -> Yes
A36: INV000035 | B36: ORD000039 | C36: DSP0001 | D36: 46088 | E36: 46118 | F36: 237.6 | H36: 0 | I36: =F36-H36 -> 237.6 | J36: =MAX(0,TODAY()-E36) -> 40 | K36: =IF(I36=0,"Paid",IF(J36<=30,"0-30",IF(J36<=60,"31-60",IF(J36<=90,"61-90","90+")))) -> 31-60 | L36: =IF(I36=0,"Closed",IF(J36>90,"Escalate",IF(J36>60,"Collections Review",IF(J36>30,"Reminder Sent","Current")))) -> Reminder Sent | M36: =IF(OR(K36="61-90",K36="90+"),"Yes","No") -> No
A37: INV000036 | B37: ORD000040 | C37: DSP0027 | D37: 46098 | E37: 46113 | F37: 219.78 | H37: 0 | I37: =F37-H37 -> 219.78 | J37: =MAX(0,TODAY()-E37) -> 45 | K37: =IF(I37=0,"Paid",IF(J37<=30,"0-30",IF(J37<=60,"31-60",IF(J37<=90,"61-90","90+")))) -> 31-60 | L37: =IF(I37=0,"Closed",IF(J37>90,"Escalate",IF(J37>60,"Collections Review",IF(J37>30,"Reminder Sent","Current")))) -> Reminder Sent | M37: =IF(OR(K37="61-90",K37="90+"),"Yes","No") -> No
A38: INV000037 | B38: ORD000041 | C38: DSP0103 | D38: 46123 | E38: 46153 | F38: 186.12 | G38: 46180 | H38: 186.12 | I38: =F38-H38 -> 0 | J38: =MAX(0,TODAY()-E38) -> 5 | K38: =IF(I38=0,"Paid",IF(J38<=30,"0-30",IF(J38<=60,"31-60",IF(J38<=90,"61-90","90+")))) -> Paid | L38: =IF(I38=0,"Closed",IF(J38>90,"Escalate",IF(J38>60,"Collections Review",IF(J38>30,"Reminder Sent","Current")))) -> Closed | M38: =IF(OR(K38="61-90",K38="90+"),"Yes","No") -> No
A39: INV000038 | B39: ORD000042 | C39: DSP0060 | D39: 46115 | E39: 46130 | F39: 193.5 | H39: 0 | I39: =F39-H39 -> 193.5 | J39: =MAX(0,TODAY()-E39) -> 28 | K39: =IF(I39=0,"Paid",IF(J39<=30,"0-30",IF(J39<=60,"31-60",IF(J39<=90,"61-90","90+")))) -> 0-30 | L39: =IF(I39=0,"Closed",IF(J39>90,"Escalate",IF(J39>60,"Collections Review",IF(J39>30,"Reminder Sent","Current")))) -> Current | M39: =IF(OR(K39="61-90",K39="90+"),"Yes","No") -> No
A40: INV000039 | B40: ORD000043 | C40: DSP0061 | D40: 46087 | E40: 46132 | F40: 719.28 | G40: 46128 | H40: 719.28 | I40: =F40-H40 -> 0 | J40: =MAX(0,TODAY()-E40) -> 26 | K40: =IF(I40=0,"Paid",IF(J40<=30,"0-30",IF(J40<=60,"31-60",IF(J40<=90,"61-90","90+")))) -> Paid | L40: =IF(I40=0,"Closed",IF(J40>90,"Escalate",IF(J40>60,"Collections Review",IF(J40>30,"Reminder Sent","Current")))) -> Closed | M40: =IF(OR(K40="61-90",K40="90+"),"Yes","No") -> No
A41: INV000040 | B41: ORD000044 | C41: DSP0102 | D41: 46077 | E41: 46122 | F41: 676.5 | G41: 46144 | H41: 676.5 | I41: =F41-H41 -> 0 | J41: =MAX(0,TODAY()-E41) -> 36 | K41: =IF(I41=0,"Paid",IF(J41<=30,"0-30",IF(J41<=60,"31-60",IF(J41<=90,"61-90","90+")))) -> Paid | L41: =IF(I41=0,"Closed",IF(J41>90,"Escalate",IF(J41>60,"Collections Review",IF(J41>30,"Reminder Sent","Current")))) -> Closed | M41: =IF(OR(K41="61-90",K41="90+"),"Yes","No") -> No
A42: INV000041 | B42: ORD000045 | C42: DSP0111 | D42: 46081 | E42: 46111 | F42: 735.84 | G42: 46114 | H42: 735.84 | I42: =F42-H42 -> 0 | J42: =MAX(0,TODAY()-E42) -> 47 | K42: =IF(I42=0,"Paid",IF(J42<=30,"0-30",IF(J42<=60,"31-60",IF(J42<=90,"61-90","90+")))) -> Paid | L42: =IF(I42=0,"Closed",IF(J42>90,"Escalate",IF(J42>60,"Collections Review",IF(J42>30,"Reminder Sent","Current")))) -> Closed | M42: =IF(OR(K42="61-90",K42="90+"),"Yes","No") -> No
A43: INV000042 | B43: ORD000046 | C43: DSP0025 | D43: 46110 | E43: 46125 | F43: 244.32 | H43: 0 | I43: =F43-H43 -> 244.32 | J43: =MAX(0,TODAY()-E43) -> 33 | K43: =IF(I43=0,"Paid",IF(J43<=30,"0-30",IF(J43<=60,"31-60",IF(J43<=90,"61-90","90+")))) -> 31-60 | L43: =IF(I43=0,"Closed",IF(J43>90,"Escalate",IF(J43>60,"Collections Review",IF(J43>30,"Reminder Sent","Current")))) -> Reminder Sent | M43: =IF(OR(K43="61-90",K43="90+"),"Yes","No") -> No
A44: INV000043 | B44: ORD000047 | C44: DSP0050 | D44: 46094 | E44: 46124 | F44: 56.88 | H44: 0 | I44: =F44-H44 -> 56.88 | J44: =MAX(0,TODAY()-E44) -> 34 | K44: =IF(I44=0,"Paid",IF(J44<=30,"0-30",IF(J44<=60,"31-60",IF(J44<=90,"61-90","90+")))) -> 31-60 | L44: =IF(I44=0,"Closed",IF(J44>90,"Escalate",IF(J44>60,"Collections Review",IF(J44>30,"Reminder Sent","Current")))) -> Reminder Sent | M44: =IF(OR(K44="61-90",K44="90+"),"Yes","No") -> No
A45: INV000044 | B45: ORD000049 | C45: DSP0080 | D45: 46113 | E45: 46143 | F45: 138.12 | G45: 46139 | H45: 138.12 | I45: =F45-H45 -> 0 | J45: =MAX(0,TODAY()-E45) -> 15 | K45: =IF(I45=0,"Paid",IF(J45<=30,"0-30",IF(J45<=60,"31-60",IF(J45<=90,"61-90","90+")))) -> Paid | L45: =IF(I45=0,"Closed",IF(J45>90,"Escalate",IF(J45>60,"Collections Review",IF(J45>30,"Reminder Sent","Current")))) -> Closed | M45: =IF(OR(K45="61-90",K45="90+"),"Yes","No") -> No
A46: INV000045 | B46: ORD000050 | C46: DSP0114 | D46: 46144 | E46: 46174 | F46: 489.6 | G46: 46172 | H46: 489.6 | I46: =F46-H46 -> 0 | J46: =MAX(0,TODAY()-E46) -> 0 | K46: =IF(I46=0,"Paid",IF(J46<=30,"0-30",IF(J46<=60,"31-60",IF(J46<=90,"61-90","90+")))) -> Paid | L46: =IF(I46=0,"Closed",IF(J46>90,"Escalate",IF(J46>60,"Collections Review",IF(J46>30,"Reminder Sent","Current")))) -> Closed | M46: =IF(OR(K46="61-90",K46="90+"),"Yes","No") -> No
A47: INV000046 | B47: ORD000051 | C47: DSP0056 | D47: 46121 | E47: 46136 | F47: 1342.8 | G47: 46170 | H47: 1342.8 | I47: =F47-H47 -> 0 | J47: =MAX(0,TODAY()-E47) -> 22 | K47: =IF(I47=0,"Paid",IF(J47<=30,"0-30",IF(J47<=60,"31-60",IF(J47<=90,"61-90","90+")))) -> Paid | L47: =IF(I47=0,"Closed",IF(J47>90,"Escalate",IF(J47>60,"Collections Review",IF(J47>30,"Reminder Sent","Current")))) -> Closed | M47: =IF(OR(K47="61-90",K47="90+"),"Yes","No") -> No
A48: INV000047 | B48: ORD000052 | C48: DSP0102 | D48: 46070 | E48: 46100 | F48: 122.88 | G48: 46123 | H48: 122.88 | I48: =F48-H48 -> 0 | J48: =MAX(0,TODAY()-E48) -> 58 | K48: =IF(I48=0,"Paid",IF(J48<=30,"0-30",IF(J48<=60,"31-60",IF(J48<=90,"61-90","90+")))) -> Paid | L48: =IF(I48=0,"Closed",IF(J48>90,"Escalate",IF(J48>60,"Collections Review",IF(J48>30,"Reminder Sent","Current")))) -> Closed | M48: =IF(OR(K48="61-90",K48="90+"),"Yes","No") -> No
A49: INV000048 | B49: ORD000053 | C49: DSP0023 | D49: 46109 | E49: 46154 | F49: 551.66 | G49: 46173 | H49: 551.66 | I49: =F49-H49 -> 0 | J49: =MAX(0,TODAY()-E49) -> 4 | K49: =IF(I49=0,"Paid",IF(J49<=30,"0-30",IF(J49<=60,"31-60",IF(J49<=90,"61-90","90+")))) -> Paid | L49: =IF(I49=0,"Closed",IF(J49>90,"Escalate",IF(J49>60,"Collections Review",IF(J49>30,"Reminder Sent","Current")))) -> Closed | M49: =IF(OR(K49="61-90",K49="90+"),"Yes","No") -> No
A50: INV000049 | B50: ORD000054 | C50: DSP0059 | D50: 46113 | E50: 46143 | F50: 72.9 | H50: 0 | I50: =F50-H50 -> 72.9 | J50: =MAX(0,TODAY()-E50) -> 15 | K50: =IF(I50=0,"Paid",IF(J50<=30,"0-30",IF(J50<=60,"31-60",IF(J50<=90,"61-90","90+")))) -> 0-30 | L50: =IF(I50=0,"Closed",IF(J50>90,"Escalate",IF(J50>60,"Collections Review",IF(J50>30,"Reminder Sent","Current")))) -> Current | M50: =IF(OR(K50="61-90",K50="90+"),"Yes","No") -> No
A51: INV000050 | B51: ORD000055 | C51: DSP0045 | D51: 46066 | E51: 46096 | F51: 1016.4 | H51: 0 | I51: =F51-H51 -> 1016.4 | J51: =MAX(0,TODAY()-E51) -> 62 | K51: =IF(I51=0,"Paid",IF(J51<=30,"0-30",IF(J51<=60,"31-60",IF(J51<=90,"61-90","90+")))) -> 61-90 | L51: =IF(I51=0,"Closed",IF(J51>90,"Escalate",IF(J51>60,"Collections Review",IF(J51>30,"Reminder Sent","Current")))) -> Collections Review | M51: =IF(OR(K51="61-90",K51="90+"),"Yes","No") -> Yes
A52: INV000051 | B52: ORD000056 | C52: DSP0062 | D52: 46058 | E52: 46073 | F52: 523.2 | H52: 0 | I52: =F52-H52 -> 523.2 | J52: =MAX(0,TODAY()-E52) -> 85 | K52: =IF(I52=0,"Paid",IF(J52<=30,"0-30",IF(J52<=60,"31-60",IF(J52<=90,"61-90","90+")))) -> 61-90 | L52: =IF(I52=0,"Closed",IF(J52>90,"Escalate",IF(J52>60,"Collections Review",IF(J52>30,"Reminder Sent","Current")))) -> Collections Review | M52: =IF(OR(K52="61-90",K52="90+"),"Yes","No") -> Yes
A53: INV000052 | B53: ORD000057 | C53: DSP0051 | D53: 46037 | E53: 46082 | F53: 1158.72 | G53: 46094 | H53: 462.08 | I53: =F53-H53 -> 696.64 | J53: =MAX(0,TODAY()-E53) -> 76 | K53: =IF(I53=0,"Paid",IF(J53<=30,"0-30",IF(J53<=60,"31-60",IF(J53<=90,"61-90","90+")))) -> 61-90 | L53: =IF(I53=0,"Closed",IF(J53>90,"Escalate",IF(J53>60,"Collections Review",IF(J53>30,"Reminder Sent","Current")))) -> Collections Review | M53: =IF(OR(K53="61-90",K53="90+"),"Yes","No") -> Yes
A54: INV000053 | B54: ORD000058 | C54: DSP0116 | D54: 46131 | E54: 46176 | F54: 269.76 | G54: 46191 | H54: 269.76 | I54: =F54-H54 -> 0 | J54: =MAX(0,TODAY()-E54) -> 0 | K54: =IF(I54=0,"Paid",IF(J54<=30,"0-30",IF(J54<=60,"31-60",IF(J54<=90,"61-90","90+")))) -> Paid | L54: =IF(I54=0,"Closed",IF(J54>90,"Escalate",IF(J54>60,"Collections Review",IF(J54>30,"Reminder Sent","Current")))) -> Closed | M54: =IF(OR(K54="61-90",K54="90+"),"Yes","No") -> No
A55: INV000054 | B55: ORD000059 | C55: DSP0099 | D55: 46115 | E55: 46145 | F55: 132.96 | G55: 46153 | H55: 132.96 | I55: =F55-H55 -> 0 | J55: =MAX(0,TODAY()-E55) -> 13 | K55: =IF(I55=0,"Paid",IF(J55<=30,"0-30",IF(J55<=60,"31-60",IF(J55<=90,"61-90","90+")))) -> Paid | L55: =IF(I55=0,"Closed",IF(J55>90,"Escalate",IF(J55>60,"Collections Review",IF(J55>30,"Reminder Sent","Current")))) -> Closed | M55: =IF(OR(K55="61-90",K55="90+"),"Yes","No") -> No
A56: INV000055 | B56: ORD000060 | C56: DSP0017 | D56: 46143 | E56: 46173 | F56: 191.16 | G56: 46176 | H56: 191.16 | I56: =F56-H56 -> 0 | J56: =MAX(0,TODAY()-E56) -> 0 | K56: =IF(I56=0,"Paid",IF(J56<=30,"0-30",IF(J56<=60,"31-60",IF(J56<=90,"61-90","90+")))) -> Paid | L56: =IF(I56=0,"Closed",IF(J56>90,"Escalate",IF(J56>60,"Collections Review",IF(J56>30,"Reminder Sent","Current")))) -> Closed | M56: =IF(OR(K56="61-90",K56="90+"),"Yes","No") -> No
A57: INV000056 | B57: ORD000061 | C57: DSP0065 | D57: 46141 | E57: 46171 | F57: 198.71 | G57: 46169 | H57: 198.71 | I57: =F57-H57 -> 0 | J57: =MAX(0,TODAY()-E57) -> 0 | K57: =IF(I57=0,"Paid",IF(J57<=30,"0-30",IF(J57<=60,"31-60",IF(J57<=90,"61-90","90+")))) -> Paid | L57: =IF(I57=0,"Closed",IF(J57>90,"Escalate",IF(J57>60,"Collections Review",IF(J57>30,"Reminder Sent","Current")))) -> Closed | M57: =IF(OR(K57="61-90",K57="90+"),"Yes","No") -> No
A58: INV000057 | B58: ORD000062 | C58: DSP0015 | D58: 46040 | E58: 46070 | F58: 217.44 | H58: 0 | I58: =F58-H58 -> 217.44 | J58: =MAX(0,TODAY()-E58) -> 88 | K58: =IF(I58=0,"Paid",IF(J58<=30,"0-30",IF(J58<=60,"31-60",IF(J58<=90,"61-90","90+")))) -> 61-90 | L58: =IF(I58=0,"Closed",IF(J58>90,"Escalate",IF(J58>60,"Collections Review",IF(J58>30,"Reminder Sent","Current")))) -> Collections Review | M58: =IF(OR(K58="61-90",K58="90+"),"Yes","No") -> Yes
A59: INV000058 | B59: ORD000063 | C59: DSP0047 | D59: 46133 | E59: 46163 | F59: 476.64 | G59: 46202 | H59: 476.64 | I59: =F59-H59 -> 0 | J59: =MAX(0,TODAY()-E59) -> 0 | K59: =IF(I59=0,"Paid",IF(J59<=30,"0-30",IF(J59<=60,"31-60",IF(J59<=90,"61-90","90+")))) -> Paid | L59: =IF(I59=0,"Closed",IF(J59>90,"Escalate",IF(J59>60,"Collections Review",IF(J59>30,"Reminder Sent","Current")))) -> Closed | M59: =IF(OR(K59="61-90",K59="90+"),"Yes","No") -> No
A60: INV000059 | B60: ORD000064 | C60: DSP0048 | D60: 46120 | E60: 46135 | F60: 256.56 | G60: 46177 | H60: 256.56 | I60: =F60-H60 -> 0 | J60: =MAX(0,TODAY()-E60) -> 23 | K60: =IF(I60=0,"Paid",IF(J60<=30,"0-30",IF(J60<=60,"31-60",IF(J60<=90,"61-90","90+")))) -> Paid | L60: =IF(I60=0,"Closed",IF(J60>90,"Escalate",IF(J60>60,"Collections Review",IF(J60>30,"Reminder Sent","Current")))) -> Closed | M60: =IF(OR(K60="61-90",K60="90+"),"Yes","No") -> No
A61: INV000060 | B61: ORD000065 | C61: DSP0009 | D61: 46143 | E61: 46188 | F61: 355.2 | G61: 46192 | H61: 355.2 | I61: =F61-H61 -> 0 | J61: =MAX(0,TODAY()-E61) -> 0 | K61: =IF(I61=0,"Paid",IF(J61<=30,"0-30",IF(J61<=60,"31-60",IF(J61<=90,"61-90","90+")))) -> Paid | L61: =IF(I61=0,"Closed",IF(J61>90,"Escalate",IF(J61>60,"Collections Review",IF(J61>30,"Reminder Sent","Current")))) -> Closed | M61: =IF(OR(K61="61-90",K61="90+"),"Yes","No") -> No
A62: INV000061 | B62: ORD000066 | C62: DSP0013 | D62: 46142 | E62: 46172 | F62: 717.84 | H62: 0 | I62: =F62-H62 -> 717.84 | J62: =MAX(0,TODAY()-E62) -> 0 | K62: =IF(I62=0,"Paid",IF(J62<=30,"0-30",IF(J62<=60,"31-60",IF(J62<=90,"61-90","90+")))) -> 0-30 | L62: =IF(I62=0,"Closed",IF(J62>90,"Escalate",IF(J62>60,"Collections Review",IF(J62>30,"Reminder Sent","Current")))) -> Current | M62: =IF(OR(K62="61-90",K62="90+"),"Yes","No") -> No
A63: INV000062 | B63: ORD000067 | C63: DSP0020 | D63: 46112 | E63: 46157 | F63: 275.28 | H63: 0 | I63: =F63-H63 -> 275.28 | J63: =MAX(0,TODAY()-E63) -> 1 | K63: =IF(I63=0,"Paid",IF(J63<=30,"0-30",IF(J63<=60,"31-60",IF(J63<=90,"61-90","90+")))) -> 0-30 | L63: =IF(I63=0,"Closed",IF(J63>90,"Escalate",IF(J63>60,"Collections Review",IF(J63>30,"Reminder Sent","Current")))) -> Current | M63: =IF(OR(K63="61-90",K63="90+"),"Yes","No") -> No
A64: INV000063 | B64: ORD000068 | C64: DSP0057 | D64: 46065 | E64: 46080 | F64: 380.88 | G64: 46098 | H64: 380.88 | I64: =F64-H64 -> 0 | J64: =MAX(0,TODAY()-E64) -> 78 | K64: =IF(I64=0,"Paid",IF(J64<=30,"0-30",IF(J64<=60,"31-60",IF(J64<=90,"61-90","90+")))) -> Paid | L64: =IF(I64=0,"Closed",IF(J64>90,"Escalate",IF(J64>60,"Collections Review",IF(J64>30,"Reminder Sent","Current")))) -> Closed | M64: =IF(OR(K64="61-90",K64="90+"),"Yes","No") -> No
A65: INV000064 | B65: ORD000069 | C65: DSP0016 | D65: 46048 | E65: 46078 | F65: 1300.8 | G65: 46120 | H65: 1300.8 | I65: =F65-H65 -> 0 | J65: =MAX(0,TODAY()-E65) -> 80 | K65: =IF(I65=0,"Paid",IF(J65<=30,"0-30",IF(J65<=60,"31-60",IF(J65<=90,"61-90","90+")))) -> Paid | L65: =IF(I65=0,"Closed",IF(J65>90,"Escalate",IF(J65>60,"Collections Review",IF(J65>30,"Reminder Sent","Current")))) -> Closed | M65: =IF(OR(K65="61-90",K65="90+"),"Yes","No") -> No
A66: INV000065 | B66: ORD000070 | C66: DSP0017 | D66: 46052 | E66: 46082 | F66: 99.12 | G66: 46086 | H66: 99.12 | I66: =F66-H66 -> 0 | J66: =MAX(0,TODAY()-E66) -> 76 | K66: =IF(I66=0,"Paid",IF(J66<=30,"0-30",IF(J66<=60,"31-60",IF(J66<=90,"61-90","90+")))) -> Paid | L66: =IF(I66=0,"Closed",IF(J66>90,"Escalate",IF(J66>60,"Collections Review",IF(J66>30,"Reminder Sent","Current")))) -> Closed | M66: =IF(OR(K66="61-90",K66="90+"),"Yes","No") -> No
A67: INV000066 | B67: ORD000071 | C67: DSP0116 | D67: 46030 | E67: 46060 | F67: 249.3 | H67: 0 | I67: =F67-H67 -> 249.3 | J67: =MAX(0,TODAY()-E67) -> 98 | K67: =IF(I67=0,"Paid",IF(J67<=30,"0-30",IF(J67<=60,"31-60",IF(J67<=90,"61-90","90+")))) -> 90+ | L67: =IF(I67=0,"Closed",IF(J67>90,"Escalate",IF(J67>60,"Collections Review",IF(J67>30,"Reminder Sent","Current")))) -> Escalate | M67: =IF(OR(K67="61-90",K67="90+"),"Yes","No") -> Yes
A68: INV000067 | B68: ORD000072 | C68: DSP0111 | D68: 46044 | E68: 46089 | F68: 58.32 | H68: 0 | I68: =F68-H68 -> 58.32 | J68: =MAX(0,TODAY()-E68) -> 69 | K68: =IF(I68=0,"Paid",IF(J68<=30,"0-30",IF(J68<=60,"31-60",IF(J68<=90,"61-90","90+")))) -> 61-90 | L68: =IF(I68=0,"Closed",IF(J68>90,"Escalate",IF(J68>60,"Collections Review",IF(J68>30,"Reminder Sent","Current")))) -> Collections Review | M68: =IF(OR(K68="61-90",K68="90+"),"Yes","No") -> Yes
A69: INV000068 | B69: ORD000073 | C69: DSP0095 | D69: 46092 | E69: 46122 | F69: 135.36 | G69: 46140 | H69: 135.36 | I69: =F69-H69 -> 0 | J69: =MAX(0,TODAY()-E69) -> 36 | K69: =IF(I69=0,"Paid",IF(J69<=30,"0-30",IF(J69<=60,"31-60",IF(J69<=90,"61-90","90+")))) -> Paid | L69: =IF(I69=0,"Closed",IF(J69>90,"Escalate",IF(J69>60,"Collections Review",IF(J69>30,"Reminder Sent","Current")))) -> Closed | M69: =IF(OR(K69="61-90",K69="90+"),"Yes","No") -> No
A70: INV000069 | B70: ORD000074 | C70: DSP0029 | D70: 46035 | E70: 46065 | F70: 886.92 | H70: 0 | I70: =F70-H70 -> 886.92 | J70: =MAX(0,TODAY()-E70) -> 93 | K70: =IF(I70=0,"Paid",IF(J70<=30,"0-30",IF(J70<=60,"31-60",IF(J70<=90,"61-90","90+")))) -> 90+ | L70: =IF(I70=0,"Closed",IF(J70>90,"Escalate",IF(J70>60,"Collections Review",IF(J70>30,"Reminder Sent","Current")))) -> Escalate | M70: =IF(OR(K70="61-90",K70="90+"),"Yes","No") -> Yes
A71: INV000070 | B71: ORD000075 | C71: DSP0055 | D71: 46096 | E71: 46141 | F71: 589.8 | H71: 0 | I71: =F71-H71 -> 589.8 | J71: =MAX(0,TODAY()-E71) -> 17 | K71: =IF(I71=0,"Paid",IF(J71<=30,"0-30",IF(J71<=60,"31-60",IF(J71<=90,"61-90","90+")))) -> 0-30 | L71: =IF(I71=0,"Closed",IF(J71>90,"Escalate",IF(J71>60,"Collections Review",IF(J71>30,"Reminder Sent","Current")))) -> Current | M71: =IF(OR(K71="61-90",K71="90+"),"Yes","No") -> No
A72: INV000071 | B72: ORD000076 | C72: DSP0075 | D72: 46121 | E72: 46151 | F72: 84.96 | H72: 0 | I72: =F72-H72 -> 84.96 | J72: =MAX(0,TODAY()-E72) -> 7 | K72: =IF(I72=0,"Paid",IF(J72<=30,"0-30",IF(J72<=60,"31-60",IF(J72<=90,"61-90","90+")))) -> 0-30 | L72: =IF(I72=0,"Closed",IF(J72>90,"Escalate",IF(J72>60,"Collections Review",IF(J72>30,"Reminder Sent","Current")))) -> Current | M72: =IF(OR(K72="61-90",K72="90+"),"Yes","No") -> No
A73: INV000072 | B73: ORD000077 | C73: DSP0090 | D73: 46140 | E73: 46170 | F73: 1328.4 | G73: 46179 | H73: 1328.4 | I73: =F73-H73 -> 0 | J73: =MAX(0,TODAY()-E73) -> 0 | K73: =IF(I73=0,"Paid",IF(J73<=30,"0-30",IF(J73<=60,"31-60",IF(J73<=90,"61-90","90+")))) -> Paid | L73: =IF(I73=0,"Closed",IF(J73>90,"Escalate",IF(J73>60,"Collections Review",IF(J73>30,"Reminder Sent","Current")))) -> Closed | M73: =IF(OR(K73="61-90",K73="90+"),"Yes","No") -> No
A74: INV000073 | B74: ORD000078 | C74: DSP0053 | D74: 46129 | E74: 46144 | F74: 617.4 | G74: 46160 | H74: 617.4 | I74: =F74-H74 -> 0 | J74: =MAX(0,TODAY()-E74) -> 14 | K74: =IF(I74=0,"Paid",IF(J74<=30,"0-30",IF(J74<=60,"31-60",IF(J74<=90,"61-90","90+")))) -> Paid | L74: =IF(I74=0,"Closed",IF(J74>90,"Escalate",IF(J74>60,"Collections Review",IF(J74>30,"Reminder Sent","Current")))) -> Closed | M74: =IF(OR(K74="61-90",K74="90+"),"Yes","No") -> No
A75: INV000074 | B75: ORD000079 | C75: DSP0020 | D75: 46042 | E75: 46072 | F75: 96 | G75: 46093 | H75: 96 | I75: =F75-H75 -> 0 | J75: =MAX(0,TODAY()-E75) -> 86 | K75: =IF(I75=0,"Paid",IF(J75<=30,"0-30",IF(J75<=60,"31-60",IF(J75<=90,"61-90","90+")))) -> Paid | L75: =IF(I75=0,"Closed",IF(J75>90,"Escalate",IF(J75>60,"Collections Review",IF(J75>30,"Reminder Sent","Current")))) -> Closed | M75: =IF(OR(K75="61-90",K75="90+"),"Yes","No") -> No
A76: INV000075 | B76: ORD000080 | C76: DSP0076 | D76: 46098 | E76: 46128 | F76: 315 | G76: 46145 | H76: 315 | I76: =F76-H76 -> 0 | J76: =MAX(0,TODAY()-E76) -> 30 | K76: =IF(I76=0,"Paid",IF(J76<=30,"0-30",IF(J76<=60,"31-60",IF(J76<=90,"61-90","90+")))) -> Paid | L76: =IF(I76=0,"Closed",IF(J76>90,"Escalate",IF(J76>60,"Collections Review",IF(J76>30,"Reminder Sent","Current")))) -> Closed | M76: =IF(OR(K76="61-90",K76="90+"),"Yes","No") -> No
A77: INV000076 | B77: ORD000081 | C77: DSP0037 | D77: 46076 | E77: 46106 | F77: 257.04 | H77: 0 | I77: =F77-H77 -> 257.04 | J77: =MAX(0,TODAY()-E77) -> 52 | K77: =IF(I77=0,"Paid",IF(J77<=30,"0-30",IF(J77<=60,"31-60",IF(J77<=90,"61-90","90+")))) -> 31-60 | L77: =IF(I77=0,"Closed",IF(J77>90,"Escalate",IF(J77>60,"Collections Review",IF(J77>30,"Reminder Sent","Current")))) -> Reminder Sent | M77: =IF(OR(K77="61-90",K77="90+"),"Yes","No") -> No
A78: INV000077 | B78: ORD000082 | C78: DSP0109 | D78: 46080 | E78: 46110 | F78: 91.56 | H78: 0 | I78: =F78-H78 -> 91.56 | J78: =MAX(0,TODAY()-E78) -> 48 | K78: =IF(I78=0,"Paid",IF(J78<=30,"0-30",IF(J78<=60,"31-60",IF(J78<=90,"61-90","90+")))) -> 31-60 | L78: =IF(I78=0,"Closed",IF(J78>90,"Escalate",IF(J78>60,"Collections Review",IF(J78>30,"Reminder Sent","Current")))) -> Reminder Sent | M78: =IF(OR(K78="61-90",K78="90+"),"Yes","No") -> No
A79: INV000078 | B79: ORD000083 | C79: DSP0079 | D79: 46037 | E79: 46067 | F79: 755.52 | H79: 0 | I79: =F79-H79 -> 755.52 | J79: =MAX(0,TODAY()-E79) -> 91 | K79: =IF(I79=0,"Paid",IF(J79<=30,"0-30",IF(J79<=60,"31-60",IF(J79<=90,"61-90","90+")))) -> 90+ | L79: =IF(I79=0,"Closed",IF(J79>90,"Escalate",IF(J79>60,"Collections Review",IF(J79>30,"Reminder Sent","Current")))) -> Escalate | M79: =IF(OR(K79="61-90",K79="90+"),"Yes","No") -> Yes
A80: INV000079 | B80: ORD000084 | C80: DSP0118 | D80: 46078 | E80: 46093 | F80: 58.98 | G80: 46092 | H80: 58.98 | I80: =F80-H80 -> 0 | J80: =MAX(0,TODAY()-E80) -> 65 | K80: =IF(I80=0,"Paid",IF(J80<=30,"0-30",IF(J80<=60,"31-60",IF(J80<=90,"61-90","90+")))) -> Paid | L80: =IF(I80=0,"Closed",IF(J80>90,"Escalate",IF(J80>60,"Collections Review",IF(J80>30,"Reminder Sent","Current")))) -> Closed | M80: =IF(OR(K80="61-90",K80="90+"),"Yes","No") -> No
A81: INV000080 | B81: ORD000085 | C81: DSP0004 | D81: 46121 | E81: 46151 | F81: 746.64 | H81: 0 | I81: =F81-H81 -> 746.64 | J81: =MAX(0,TODAY()-E81) -> 7 | K81: =IF(I81=0,"Paid",IF(J81<=30,"0-30",IF(J81<=60,"31-60",IF(J81<=90,"61-90","90+")))) -> 0-30 | L81: =IF(I81=0,"Closed",IF(J81>90,"Escalate",IF(J81>60,"Collections Review",IF(J81>30,"Reminder Sent","Current")))) -> Current | M81: =IF(OR(K81="61-90",K81="90+"),"Yes","No") -> No
A82: INV000081 | B82: ORD000086 | C82: DSP0073 | D82: 46044 | E82: 46059 | F82: 43.32 | G82: 46060 | H82: 43.32 | I82: =F82-H82 -> 0 | J82: =MAX(0,TODAY()-E82) -> 99 | K82: =IF(I82=0,"Paid",IF(J82<=30,"0-30",IF(J82<=60,"31-60",IF(J82<=90,"61-90","90+")))) -> Paid | L82: =IF(I82=0,"Closed",IF(J82>90,"Escalate",IF(J82>60,"Collections Review",IF(J82>30,"Reminder Sent","Current")))) -> Closed | M82: =IF(OR(K82="61-90",K82="90+"),"Yes","No") -> No
A83: INV000082 | B83: ORD000087 | C83: DSP0063 | D83: 46093 | E83: 46123 | F83: 355.2 | G83: 46160 | H83: 355.2 | I83: =F83-H83 -> 0 | J83: =MAX(0,TODAY()-E83) -> 35 | K83: =IF(I83=0,"Paid",IF(J83<=30,"0-30",IF(J83<=60,"31-60",IF(J83<=90,"61-90","90+")))) -> Paid | L83: =IF(I83=0,"Closed",IF(J83>90,"Escalate",IF(J83>60,"Collections Review",IF(J83>30,"Reminder Sent","Current")))) -> Closed | M83: =IF(OR(K83="61-90",K83="90+"),"Yes","No") -> No
A84: INV000083 | B84: ORD000088 | C84: DSP0076 | D84: 46097 | E84: 46127 | F84: 908.46 | G84: 46150 | H84: 908.46 | I84: =F84-H84 -> 0 | J84: =MAX(0,TODAY()-E84) -> 31 | K84: =IF(I84=0,"Paid",IF(J84<=30,"0-30",IF(J84<=60,"31-60",IF(J84<=90,"61-90","90+")))) -> Paid | L84: =IF(I84=0,"Closed",IF(J84>90,"Escalate",IF(J84>60,"Collections Review",IF(J84>30,"Reminder Sent","Current")))) -> Closed | M84: =IF(OR(K84="61-90",K84="90+"),"Yes","No") -> No
A85: INV000084 | B85: ORD000090 | C85: DSP0091 | D85: 46095 | E85: 46110 | F85: 825.84 | G85: 46112 | H85: 825.84 | I85: =F85-H85 -> 0 | J85: =MAX(0,TODAY()-E85) -> 48 | K85: =IF(I85=0,"Paid",IF(J85<=30,"0-30",IF(J85<=60,"31-60",IF(J85<=90,"61-90","90+")))) -> Paid | L85: =IF(I85=0,"Closed",IF(J85>90,"Escalate",IF(J85>60,"Collections Review",IF(J85>30,"Reminder Sent","Current")))) -> Closed | M85: =IF(OR(K85="61-90",K85="90+"),"Yes","No") -> No
A86: INV000085 | B86: ORD000091 | C86: DSP0010 | D86: 46100 | E86: 46130 | F86: 511.2 | G86: 46155 | H86: 511.2 | I86: =F86-H86 -> 0 | J86: =MAX(0,TODAY()-E86) -> 28 | K86: =IF(I86=0,"Paid",IF(J86<=30,"0-30",IF(J86<=60,"31-60",IF(J86<=90,"61-90","90+")))) -> Paid | L86: =IF(I86=0,"Closed",IF(J86>90,"Escalate",IF(J86>60,"Collections Review",IF(J86>30,"Reminder Sent","Current")))) -> Closed | M86: =IF(OR(K86="61-90",K86="90+"),"Yes","No") -> No
A87: INV000086 | B87: ORD000092 | C87: DSP0022 | D87: 46094 | E87: 46109 | F87: 255.96 | H87: 0 | I87: =F87-H87 -> 255.96 | J87: =MAX(0,TODAY()-E87) -> 49 | K87: =IF(I87=0,"Paid",IF(J87<=30,"0-30",IF(J87<=60,"31-60",IF(J87<=90,"61-90","90+")))) -> 31-60 | L87: =IF(I87=0,"Closed",IF(J87>90,"Escalate",IF(J87>60,"Collections Review",IF(J87>30,"Reminder Sent","Current")))) -> Reminder Sent | M87: =IF(OR(K87="61-90",K87="90+"),"Yes","No") -> No
A88: INV000087 | B88: ORD000094 | C88: DSP0100 | D88: 46068 | E88: 46098 | F88: 1339.2 | G88: 46116 | H88: 1339.2 | I88: =F88-H88 -> 0 | J88: =MAX(0,TODAY()-E88) -> 60 | K88: =IF(I88=0,"Paid",IF(J88<=30,"0-30",IF(J88<=60,"31-60",IF(J88<=90,"61-90","90+")))) -> Paid | L88: =IF(I88=0,"Closed",IF(J88>90,"Escalate",IF(J88>60,"Collections Review",IF(J88>30,"Reminder Sent","Current")))) -> Closed | M88: =IF(OR(K88="61-90",K88="90+"),"Yes","No") -> No
A89: INV000088 | B89: ORD000095 | C89: DSP0098 | D89: 46055 | E89: 46085 | F89: 1318.8 | G89: 46121 | H89: 1318.8 | I89: =F89-H89 -> 0 | J89: =MAX(0,TODAY()-E89) -> 73 | K89: =IF(I89=0,"Paid",IF(J89<=30,"0-30",IF(J89<=60,"31-60",IF(J89<=90,"61-90","90+")))) -> Paid | L89: =IF(I89=0,"Closed",IF(J89>90,"Escalate",IF(J89>60,"Collections Review",IF(J89>30,"Reminder Sent","Current")))) -> Closed | M89: =IF(OR(K89="61-90",K89="90+"),"Yes","No") -> No
A90: INV000089 | B90: ORD000096 | C90: DSP0083 | D90: 46066 | E90: 46081 | F90: 896.4 | G90: 46111 | H90: 896.4 | I90: =F90-H90 -> 0 | J90: =MAX(0,TODAY()-E90) -> 77 | K90: =IF(I90=0,"Paid",IF(J90<=30,"0-30",IF(J90<=60,"31-60",IF(J90<=90,"61-90","90+")))) -> Paid | L90: =IF(I90=0,"Closed",IF(J90>90,"Escalate",IF(J90>60,"Collections Review",IF(J90>30,"Reminder Sent","Current")))) -> Closed | M90: =IF(OR(K90="61-90",K90="90+"),"Yes","No") -> No
A91: INV000090 | B91: ORD000097 | C91: DSP0046 | D91: 46040 | E91: 46070 | F91: 223.2 | G91: 46071 | H91: 223.2 | I91: =F91-H91 -> 0 | J91: =MAX(0,TODAY()-E91) -> 88 | K91: =IF(I91=0,"Paid",IF(J91<=30,"0-30",IF(J91<=60,"31-60",IF(J91<=90,"61-90","90+")))) -> Paid | L91: =IF(I91=0,"Closed",IF(J91>90,"Escalate",IF(J91>60,"Collections Review",IF(J91>30,"Reminder Sent","Current")))) -> Closed | M91: =IF(OR(K91="61-90",K91="90+"),"Yes","No") -> No
A92: INV000091 | B92: ORD000098 | C92: DSP0110 | D92: 46105 | E92: 46135 | F92: 1057.92 | H92: 0 | I92: =F92-H92 -> 1057.92 | J92: =MAX(0,TODAY()-E92) -> 23 | K92: =IF(I92=0,"Paid",IF(J92<=30,"0-30",IF(J92<=60,"31-60",IF(J92<=90,"61-90","90+")))) -> 0-30 | L92: =IF(I92=0,"Closed",IF(J92>90,"Escalate",IF(J92>60,"Collections Review",IF(J92>30,"Reminder Sent","Current")))) -> Current | M92: =IF(OR(K92="61-90",K92="90+"),"Yes","No") -> No
A93: INV000092 | B93: ORD000099 | C93: DSP0084 | D93: 46077 | E93: 46107 | F93: 979.2 | G93: 46124 | H93: 979.2 | I93: =F93-H93 -> 0 | J93: =MAX(0,TODAY()-E93) -> 51 | K93: =IF(I93=0,"Paid",IF(J93<=30,"0-30",IF(J93<=60,"31-60",IF(J93<=90,"61-90","90+")))) -> Paid | L93: =IF(I93=0,"Closed",IF(J93>90,"Escalate",IF(J93>60,"Collections Review",IF(J93>30,"Reminder Sent","Current")))) -> Closed | M93: =IF(OR(K93="61-90",K93="90+"),"Yes","No") -> No
A94: INV000093 | B94: ORD000100 | C94: DSP0092 | D94: 46098 | E94: 46113 | F94: 1356.96 | H94: 0 | I94: =F94-H94 -> 1356.96 | J94: =MAX(0,TODAY()-E94) -> 45 | K94: =IF(I94=0,"Paid",IF(J94<=30,"0-30",IF(J94<=60,"31-60",IF(J94<=90,"61-90","90+")))) -> 31-60 | L94: =IF(I94=0,"Closed",IF(J94>90,"Escalate",IF(J94>60,"Collections Review",IF(J94>30,"Reminder Sent","Current")))) -> Reminder Sent | M94: =IF(OR(K94="61-90",K94="90+"),"Yes","No") -> No
A95: INV000094 | B95: ORD000101 | C95: DSP0047 | D95: 46150 | E95: 46180 | F95: 430.92 | H95: 0 | I95: =F95-H95 -> 430.92 | J95: =MAX(0,TODAY()-E95) -> 0 | K95: =IF(I95=0,"Paid",IF(J95<=30,"0-30",IF(J95<=60,"31-60",IF(J95<=90,"61-90","90+")))) -> 0-30 | L95: =IF(I95=0,"Closed",IF(J95>90,"Escalate",IF(J95>60,"Collections Review",IF(J95>30,"Reminder Sent","Current")))) -> Current | M95: =IF(OR(K95="61-90",K95="90+"),"Yes","No") -> No
A96: INV000095 | B96: ORD000102 | C96: DSP0009 | D96: 46036 | E96: 46081 | F96: 782.64 | G96: 46105 | H96: 782.64 | I96: =F96-H96 -> 0 | J96: =MAX(0,TODAY()-E96) -> 77 | K96: =IF(I96=0,"Paid",IF(J96<=30,"0-30",IF(J96<=60,"31-60",IF(J96<=90,"61-90","90+")))) -> Paid | L96: =IF(I96=0,"Closed",IF(J96>90,"Escalate",IF(J96>60,"Collections Review",IF(J96>30,"Reminder Sent","Current")))) -> Closed | M96: =IF(OR(K96="61-90",K96="90+"),"Yes","No") -> No
A97: INV000096 | B97: ORD000103 | C97: DSP0075 | D97: 46146 | E97: 46176 | F97: 414.12 | G97: 46171 | H97: 414.12 | I97: =F97-H97 -> 0 | J97: =MAX(0,TODAY()-E97) -> 0 | K97: =IF(I97=0,"Paid",IF(J97<=30,"0-30",IF(J97<=60,"31-60",IF(J97<=90,"61-90","90+")))) -> Paid | L97: =IF(I97=0,"Closed",IF(J97>90,"Escalate",IF(J97>60,"Collections Review",IF(J97>30,"Reminder Sent","Current")))) -> Closed | M97: =IF(OR(K97="61-90",K97="90+"),"Yes","No") -> No
A98: INV000097 | B98: ORD000104 | C98: DSP0040 | D98: 46074 | E98: 46104 | F98: 920.4 | G98: 46138 | H98: 920.4 | I98: =F98-H98 -> 0 | J98: =MAX(0,TODAY()-E98) -> 54 | K98: =IF(I98=0,"Paid",IF(J98<=30,"0-30",IF(J98<=60,"31-60",IF(J98<=90,"61-90","90+")))) -> Paid | L98: =IF(I98=0,"Closed",IF(J98>90,"Escalate",IF(J98>60,"Collections Review",IF(J98>30,"Reminder Sent","Current")))) -> Closed | M98: =IF(OR(K98="61-90",K98="90+"),"Yes","No") -> No
A99: INV000098 | B99: ORD000105 | C99: DSP0066 | D99: 46034 | E99: 46064 | F99: 363.6 | G99: 46072 | H99: 363.6 | I99: =F99-H99 -> 0 | J99: =MAX(0,TODAY()-E99) -> 94 | K99: =IF(I99=0,"Paid",IF(J99<=30,"0-30",IF(J99<=60,"31-60",IF(J99<=90,"61-90","90+")))) -> Paid | L99: =IF(I99=0,"Closed",IF(J99>90,"Escalate",IF(J99>60,"Collections Review",IF(J99>30,"Reminder Sent","Current")))) -> Closed | M99: =IF(OR(K99="61-90",K99="90+"),"Yes","No") -> No
A100: INV000099 | B100: ORD000106 | C100: DSP0020 | D100: 46067 | E100: 46097 | F100: 132.24 | H100: 0 | I100: =F100-H100 -> 132.24 | J100: =MAX(0,TODAY()-E100) -> 61 | K100: =IF(I100=0,"Paid",IF(J100<=30,"0-30",IF(J100<=60,"31-60",IF(J100<=90,"61-90","90+")))) -> 61-90 | L100: =IF(I100=0,"Closed",IF(J100>90,"Escalate",IF(J100>60,"Collections Review",IF(J100>30,"Reminder Sent","Current")))) -> Collections Review | M100: =IF(OR(K100="61-90",K100="90+"),"Yes","No") -> Yes
...

Sheet order_compliance_review
A1: order_id | B1: order_date | C1: customer_id | D1: state | E1: sku | F1: customer_license_status | G1: license_expiration_date | H1: metrc_manifest_id | I1: sku_approval_status | J1: compliance_hold_flag | K1: hold_reason | L1: release_owner
A2: ORD000372 | B2: 46038 | D2: =IFERROR(VLOOKUP(C2,customer_lookup!$A:$E,3,FALSE),"") | E2: SKU0019 | F2: Valid | G2: 46134 | H2: METRC-5829108 | I2: Approved | J2: No | K2: Clear | L2: Compliance
A3: ORD000730 | B3: 46100 | D3: =IFERROR(VLOOKUP(C3,customer_lookup!$A:$E,3,FALSE),"") | E3: SKU0012 | F3: Valid | G3: 46223 | I3: Approved | J3: Yes | K3: missing manifest | L3: Compliance
A4: ORD000004 | B4: 46113 | C4: DSP0089 | D4: AZ | E4: SKU0005 | F4: Valid | G4: 46194 | H4: METRC-5309257 | I4: Approved | J4: No | K4: Clear | L4: Distribution
A5: ORD000018 | B5: 46054 | C5: DSP0113 | D5: AZ | E5: SKU0015 | F5: Valid | G5: 46107 | H5: METRC-1233839 | I5: Restricted | J5: Yes | K5: sku approval | L5: Sales Ops
A6: ORD000033 | B6: 46140 | C6: DSP0077 | D6: AZ | E6: SKU0019 | F6: Valid | G6: 46147 | H6: METRC-8719270 | I6: Approved | J6: No | K6: Clear | L6: Sales Ops
A7: ORD000037 | B7: 46064 | C7: DSP0053 | D7: AZ | E7: SKU0011 | F7: Expiring Soon | G7: 46079 | H7: METRC-1089175 | I7: Approved | J7: No | K7: Clear | L7: Compliance
A8: ORD000060 | B8: 46139 | C8: DSP0017 | D8: AZ | E8: SKU0003 | F8: Expiring Soon | G8: 46150 | H8: METRC-7604999 | I8: Approved | J8: No | K8: Clear | L8: Compliance
A9: ORD000061 | B9: 46129 | C9: DSP0065 | D9: AZ | E9: SKU0009 | F9: Valid | G9: 46248 | H9: METRC-6206514 | I9: Approved | J9: No | K9: Clear | L9: Distribution
A10: ORD000070 | B10: 46049 | C10: DSP0017 | D10: AZ | E10: SKU0019 | F10: Valid | G10: 46084 | H10: METRC-3280671 | I10: Approved | J10: No | K10: Clear | L10: Distribution
A11: ORD000074 | B11: 46028 | C11: DSP0029 | D11: AZ | E11: SKU0020 | F11: Valid | G11: 46124 | H11: METRC-5132079 | I11: Approved | J11: No | K11: Clear | L11: Distribution
A12: ORD000078 | B12: 46128 | C12: DSP0053 | D12: AZ | E12: SKU0011 | F12: Valid | G12: 46134 | H12: METRC-2222008 | I12: Approved | J12: No | K12: Clear | L12: Sales Ops
A13: ORD000119 | B13: 46093 | C13: DSP0065 | D13: AZ | E13: SKU0017 | F13: Valid | G13: 46215 | H13: METRC-4976984 | I13: Approved | J13: No | K13: Clear | L13: Sales Ops
A14: ORD000120 | B14: 46067 | C14: DSP0101 | D14: AZ | E14: SKU0003 | F14: Expiring Soon | G14: 46107 | H14: METRC-3865996 | I14: Approved | J14: No | K14: Clear | L14: Compliance
A15: ORD000138 | B15: 46129 | C15: DSP0065 | D15: AZ | E15: SKU0002 | F15: Valid | G15: 46289 | H15: METRC-8965446 | I15: Approved | J15: No | K15: Clear | L15: Distribution
... A22: ORD000236 | B22: 46088 | C22: DSP0089 | D22: AZ | E22: SKU0005 | F22: Valid | G22: 46076 | H22: METRC-3255241 | I22: Approved | J22: No | K22: Clear | L22: Sales Ops
A23: ORD000252 | B23: 46043 | C23: DSP0017 | D23: AZ | E23: SKU0010 | F23: Valid | G23: 46160 | I23: Restricted | J23: Yes | K23: missing manifest, sku approval | L23: Distribution
A24: ORD000261 | B24: 46090 | C24: DSP0077 | D24: AZ | E24: SKU0003 | F24: Valid | G24: 46174 | H24: METRC-7303916 | I24: Approved | J24: No | K24: Clear | L24: Distribution
A25: ORD000276 | B25: 46065 | C25: DSP0113 | D25: AZ | E25: SKU0001 | F25: Valid | G25: 46152 | H25: METRC-5487558 | I25: Approved | J25: No | K25: Clear | L25: Compliance
A26: ORD000296 | B26: 46030 | C26: DSP0005 | D26: AZ | E26: SKU0003 | F26: Valid | G26: 46143 | H26: METRC-7396879 | I26: Approved | J26: No | K26: Clear | L26: Distribution
A27: ORD000297 | B27: 46114 | C27: DSP0017 | D27: AZ | E27: SKU0011 | F27: Valid | G27: 46253 | I27: Approved | J27: Yes | K27: missing manifest | L27: Distribution
A28: ORD000327 | B28: 46104 | C28: DSP0065 | D28: AZ | E28: SKU0013 | F28: Valid | G28: 46170 | H28: METRC-9274446 | I28: Approved | J28: No | K28: Clear | L28: Sales Ops
A29: ORD000343 | B29: 46039 | C29: DSP0101 | D29: AZ | E29: SKU0003 | F29: Expired | G29: 46193 | H29: METRC-8146807 | I29: Approved | J29: Yes | K29: license issue | L29: Compliance
A30: ORD000345 | B30: 46062 | C30: DSP0089 | D30: AZ | E30: SKU0012 | F30: Expired | G30: 46182 | H30: METRC-7898660 | I30: Approved | J30: Yes | K30: license issue | L30: Compliance
A31: ORD000369 | B31: 46066 | C31: DSP0029 | D31: AZ | E31: SKU0001 | F31: Valid | G31: 46177 | H31: METRC-1125708 | I31: Approved | J31: No | K31: Clear | L31: Sales Ops
A32: ORD000375 | B32: 46058 | C32: DSP0089 | D32: AZ | E32: SKU0008 | F32: Valid | G32: 46074 | H32: METRC-9067295 | I32: Approved | J32: No | K32: Clear | L32: Compliance
A33: ORD000388 | B33: 46089 | C33: DSP0029 | D33: AZ | E33: SKU0006 | F33: Valid | G33: 46156 | H33: METRC-1975520 | I33: Approved | J33: No | K33: Clear | L33: Compliance
A34: ORD000395 | B34: 46032 | C34: DSP0005 | D34: AZ | E34: SKU0003 | F34: Valid | G34: 46028 | H34: METRC-7733607 | I34: Approved | J34: No | K34: Clear | L34: Distribution
A35: ORD000423 | B35: 46025 | C35: DSP0017 | D35: AZ | E35: SKU0004 | F35: Valid | G35: 46153 | H35: METRC-7497626 | I35: Approved | J35: No | K35: Clear | L35: Compliance
A36: ORD000428 | B36: 46047 | C36: DSP0053 | D36: AZ | E36: SKU0009 | F36: Expiring Soon | G36: 46050 | H36: METRC-5738586 | I36: Approved | J36: No | K36: Clear | L36: Distribution
A37: ORD000434 | B37: 46033 | C37: DSP0029 | D37: AZ | E37: SKU0012 | F37: Valid | G37: 46178 | H37: METRC-8814822 | I37: Approved | J37: No | K37: Clear | L37: Distribution
A38: ORD000435 | B38: 46122 | C38: DSP0077 | D38: AZ | E38: SKU0002 | F38: Valid | G38: 46159 | H38: METRC-8067258 | I38: Approved | J38: No | K38: Clear | L38: Sales Ops
A39: ORD000436 | B39: 46089 | C39: DSP0077 | D39: AZ | E39: SKU0017 | F39: Valid | G39: 46228 | H39: METRC-1129567 | I39: Approved | J39: No | K39: Clear | L39: Compliance
... A79: ORD000966 | B79: 46087 | C79: DSP0113 | D79: AZ | E79: SKU0013 | F79: Valid | G79: 46185 | H79: METRC-2878425 | I79: Approved | J79: No | K79: Clear | L79: Sales Ops
A80: ORD000986 | B80: 46057 | C80: DSP0029 | D80: AZ | E80: SKU0011 | F80: Valid | G80: 46197 | I80: Approved | J80: Yes | K80: missing manifest | L80: Compliance
A81: ORD000002 | B81: 46080 | C81: DSP0111 | D81: CA | E81: SKU0016 | F81: Valid | G81: 46064 | H81: METRC-4874329 | I81: Approved | J81: No | K81: Clear | L81: Sales Ops
A82: ORD000011 | B82: 46042 | C82: DSP0003 | D82: CA | E82: SKU0020 | F82: Valid | G82: 46089 | H82: METRC-6406189 | I82: Approved | J82: No | K82: Clear | L82: Sales Ops
A83: ORD000035 | B83: 46098 | C83: DSP0087 | D83: CA | E83: SKU0019 | F83: Valid | G83: 46090 | H83: METRC-2591432 | I83: Approved | J83: No | K83: Clear | L83: Sales Ops
A84: ORD000040 | B84: 46093 | C84: DSP0027 | D84: CA | E84: SKU0009 | F84: Valid | G84: 46244 | I84: Approved | J84: Yes | K84: missing manifest | L84: Compliance
A85: ORD000045 | B85: 46080 | C85: DSP0111 | D85: CA | E85: SKU0005 | F85: Valid | G85: 46220 | H85: METRC-7993854 | I85: Approved | J85: No | K85: Clear | L85: Distribution
A86: ORD000057 | B86: 46024 | C86: DSP0051 | D86: CA | E86: SKU0009 | F86: Expired | G86: 46050 | H86: METRC-3219696 | I86: Approved | J86: Yes | K86: license issue | L86: Sales Ops
A87: ORD000059 | B87: 46103 | C87: DSP0099 | D87: CA | E87: SKU0005 | F87: Valid | G87: 46151 | H87: METRC-7545337 | I87: Approved | J87: No | K87: Clear | L87: Compliance
A88: ORD000062 | B88: 46032 | C88: DSP0015 | D88: CA | E88: SKU0015 | F88: Valid | G88: 46098 | H88: METRC-3437167 | I88: Approved | J88: No | K88: Clear | L88: Compliance
A89: ORD000072 | B89: 46039 | C89: DSP0111 | D89: CA | E89: SKU0001 | F89: Valid | G89: 46188 | H89: METRC-2537198 | I89: Restricted | J89: Yes | K89: sku approval | L89: Compliance
A90: ORD000076 | B90: 46114 | C90: DSP0075 | D90: CA | E90: SKU0018 | F90: Valid | G90: 46231 | H90: METRC-6681178 | I90: Approved | J90: No | K90: Clear | L90: Compliance
A91: ORD000087 | B91: 46079 | C91: DSP0063 | D91: CA | E91: SKU0020 | F91: Valid | G91: 46179 | H91: METRC-1793240 | I91: Approved | J91: No | K91: Clear | L91: Sales Ops
A92: ORD000103 | B92: 46140 | C92: DSP0075 | D92: CA | E92: SKU0005 | F92: Valid | G92: 46193 | H92: METRC-5816096 | I92: Approved | J92: No | K92: Clear | L92: Distribution
A93: ORD000107 | B93: 46039 | C93: DSP0099 | D93: CA | E93: SKU0020 | F93: Valid | G93: 46137 | H93: METRC-5524377 | I93: Approved | J93: No | K93: Clear | L93: Sales Ops
A94: ORD000154 | B94: 46127 | C94: DSP0039 | D94: CA | E94: SKU0016 | F94: Valid | G94: 46244 | H94: METRC-6381255 | I94: Approved | J94: No | K94: Clear | L94: Compliance
A95: ORD000156 | B95: 46044 | C95: DSP0075 | D95: CA | E95: SKU0016 | F95: Expiring Soon | G95: 46029 | H95: METRC-1703209 | I95: Approved | J95: No | K95: Clear | L95: Sales Ops
A96: ORD000161 | B96: 46084 | C96: DSP0063 | D96: CA | E96: SKU0011 | F96: Valid | G96: 46100 | H96: METRC-1830167 | I96: Approved | J96: No | K96: Clear | L96: Sales Ops
... A99: ORD000223 | B99: 46055 | C99: DSP0039 | D99: CA | E99: SKU0008 | F99: Valid | G99: 46101 | H99: METRC-2373574 | I99: Pending Review | J99: Yes | K99: sku approval | L99: Distribution
A100: ORD000230 | B100: 46131 | C100: DSP0015 | D100: CA | E100: SKU0001 | F100: Valid | G100: 46278 | I100: Restricted | J100: Yes | K100: missing manifest, sku approval | L100: Compliance
A101: ORD000244 | B101: 46126 | C101: DSP0027 | D101: CA | E101: SKU0007 | F101: Valid | G101: 46151 | H101: METRC-6994376 | I101: Approved | J101: No | K101: Clear | L101: Distribution
A102: ORD000246 | B102: 46112 | C102: DSP0111 | D102: CA | E102: SKU0005 | F102: Valid | G102: 46203 | H102: METRC-8241732 | I102: Approved | J102: No | K102: Clear | L102: Sales Ops
A103: ORD000260 | B103: 46105 | C103: DSP0051 | D103: CA | E103: SKU0010 | F103: Valid | G103: 46210 | H103: METRC-2277593 | I103: Approved | J103: No | K103: Clear | L103: Compliance
A104: ORD000263 | B104: 46059 | C104: DSP0051 | D104: CA | E104: SKU0017 | F104: Valid | G104: 46125 | H104: METRC-2353133 | I104: Approved | J104: No | K104: Clear | L104: Compliance
A105: ORD000280 | B105: 46063 | C105: DSP0051 | D105: CA | E105: SKU0011 | F105: Valid | G105: 46185 | H105: METRC-9659281 | I105: Approved | J105: No | K105: Clear | L105: Sales Ops
A106: ORD000315 | B106: 46073 | C106: DSP0039 | D106: CA | E106: SKU0003 | F106: Valid | G106: 46054 | H106: METRC-9622906 | I106: Approved | J106: No | K106: Clear | L106: Distribution
A107: ORD000330 | B107: 46083 | C107: DSP0111 | D107: CA | E107: SKU0001 | F107: Expiring Soon | G107: 46125 | H107: METRC-7505305 | I107: Restricted | J107: Yes | K107: sku approval | L107: Compliance
A108: ORD000332 | B108: 46036 | C108: DSP0051 | D108: CA | E108: SKU0019 | F108: Valid | G108: 46143 | H108: METRC-8528059 | I108: Approved | J108: No | K108: Clear | L108: Sales Ops
A109: ORD000353 | B109: 46065 | C109: DSP0027 | D109: CA | E109: SKU0016 | F109: Valid | G109: 46196 | H109: METRC-4470099 | I109: Approved | J109: No | K109: Clear | L109: Distribution
A110: ORD000364 | B110: 46053 | C110: DSP0063 | D110: CA | E110: SKU0011 | F110: Expiring Soon | G110: 46052 | H110: METRC-9577903 | I110: Approved | J110: No | K110: Clear | L110: Compliance
A111: ORD000366 | B111: 46074 | C111: DSP0003 | D111: CA | E111: SKU0004 | F111: Valid | G111: 46121 | H111: METRC-4772134 | I111: Approved | J111: No | K111: Clear | L111: Sales Ops
A112: ORD000386 | B112: 46023 | C112: DSP0075 | D112: CA | E112: SKU0009 | F112: Valid | G112: 46098 | H112: METRC-1198504 | I112: Approved | J112: No | K112: Clear | L112: Distribution
... A115: ORD000410 | B115: 46116 | C115: DSP0099 | D115: CA | E115: SKU0019 | F115: Valid | G115: 46204 | H115: METRC-3100895 | I115: Approved | J115: No | K115: Clear | L115: Sales Ops
A116: ORD000413 | B116: 46139 | C116: DSP0027 | D116: CA | E116: SKU0017 | F116: Valid | G116: 46146 | I116: Approved | J116: Yes | K116: missing manifest | L116: Sales Ops
A117: ORD000418 | B117: 46109 | C117: DSP0015 | D117: CA | E117: SKU0016 | F117: Valid | G117: 46155 | H117: METRC-1623482 | I117: Approved | J117: No | K117: Clear | L117: Distribution
A118: ORD000429 | B118: 46075 | C118: DSP0027 | D118: CA | E118: SKU0011 | F118: Valid | G118: 46115 | H118: METRC-6045988 | I118: Approved | J118: No | K118: Clear | L118: Sales Ops
A119: ORD000454 | B119: 46055 | C119: DSP0063 | D119: CA | E119: SKU0010 | F119: Valid | G119: 46115 | H119: METRC-4385728 | I119: Approved | J119: No | K119: Clear | L119: Sales Ops
A120: ORD000457 | B120: 46136 | C120: DSP0063 | D120: CA | E120: SKU0015 | F120: Valid | G120: 46138 | H120: METRC-8117427 | I120: Approved | J120: No | K120: Clear | L120: Compliance
A121: ORD000518 | B121: 46134 | C121: DSP0087 | D121: CA | E121: SKU0020 | F121: Valid | G121: 46239 | H121: METRC-9892103 | I121: Approved | J121: No | K121: Clear | L121: Distribution
A122: ORD000534 | B122: 46104 | C122: DSP0015 | D122: CA | E122: SKU0015 | F122: Valid | G122: 46229 | H122: METRC-7981781 | I122: Approved | J122: No | K122: Clear | L122: Sales Ops
A123: ORD000536 | B123: 46076 | C123: DSP0099 | D123: CA | E123: SKU0002 | F123: Valid | G123: 46133 | I123: Approved | J123: Yes | K123: missing manifest | L123: Compliance
A124: ORD000557 | B124: 46049 | C124: DSP0087 | D124: CA | E124: SKU0005 | F124: Valid | G124: 46033 | H124: METRC-6168882 | I124: Approved | J124: No | K124: Clear | L124: Distribution
A125: ORD000574 | B125: 46140 | C125: DSP0087 | D125: CA | E125: SKU0010 | F125: Expiring Soon | G125: 46300 | H125: METRC-4195132 | I125: Approved | J125: No | K125: Clear | L125: Compliance
A126: ORD000599 | B126: 46055 | C126: DSP0015 | D126: CA | E126: SKU0006 | F126: Valid | G126: 46081 | H126: METRC-4495653 | I126: Approved | J126: No | K126: Clear | L126: Compliance
A127: ORD000617 | B127: 46040 | C127: DSP0075 | D127: CA | E127: SKU0002 | F127: Valid | G127: 46123 | I127: Approved | J127: Yes | K127: missing manifest | L127: Sales Ops
A128: ORD000670 | B128: 46141 | C128: DSP0015 | D128: CA | E128: SKU0005 | F128: Valid | G128: 46205 | H128: METRC-3777030 | I128: Approved | J128: No | K128: Clear | L128: Compliance
A129: ORD000672 | B129: 46033 | C129: DSP0027 | D129: CA | E129: SKU0005 | F129: Valid | G129: 46114 | H129: METRC-1557636 | I129: Approved | J129: No | K129: Clear | L129: Distribution
A130: ORD000682 | B130: 46073 | C130: DSP0063 | D130: CA | E130: SKU0004 | F130: Valid | G130: 46229 | H130: METRC-1478171 | I130: Approved | J130: No | K130: Clear | L130: Sales Ops
A131: ORD000691 | B131: 46110 | C131: DSP0063 | D131: CA | E131: SKU0018 | F131: Valid | G131: 46185 | H131: METRC-5945954 | I131: Approved | J131: No | K131: Clear | L131: Distribution
A132: ORD000697 | B132: 46111 | C132: DSP0063 | D132: CA | E132: SKU0004 | F132: Valid | G132: 46178 | H132: METRC-8210083 | I132: Approved | J132: No | K132: Clear | L132: Sales Ops
A133: ORD000699 | B133: 46074 | C133: DSP0039 | D133: CA | E133: SKU0019 | F133: Valid | G133: 46126 | H133: METRC-9004799 | I133: Approved | J133: No | K133: Clear | L133: Compliance
A134: ORD000709 | B134: 46053 | C134: DSP0051 | D134: CA | E134: SKU0005 | F134: Valid | G134: 46089 | H134: METRC-1302651 | I134: Approved | J134: No | K134: Clear | L134: Distribution
A135: ORD000727 | B135: 46076 | C135: DSP0087 | D135: CA | E135: SKU0007 | F135: Valid | G135: 46106 | H135: METRC-6976919 | I135: Approved | J135: No | K135: Clear | L135: Compliance
A136: ORD000736 | B136: 46028 | C136: DSP0015 | D136: CA | E136: SKU0016 | F136: Valid | G136: 46101 | H136: METRC-3183153 | I136: Approved | J136: No | K136: Clear | L136: Compliance
A137: ORD000739 | B137: 46109 | C137: DSP0099 | D137: CA | E137: SKU0016 | F137: Valid | G137: 46136 | I137: Approved | J137: Yes | K137: missing manifest | L137: Compliance
A138: ORD000743 | B138: 46034 | C138: DSP0099 | D138: CA | E138: SKU0013 | F138: Valid | G138: 46155 | H138: METRC-6813328 | I138: Approved | J138: No | K138: Clear | L138: Distribution
A139: ORD000750 | B139: 46121 | C139: DSP0075 | D139: CA | E139: SKU0003 | F139: Valid | G139: 46178 | H139: METRC-7038575 | I139: Approved | J139: No | K139: Clear | L139: Distribution
A140: ORD000753 | B140: 46024 | C140: DSP0051 | D140: CA | E140: SKU0004 | F140: Valid | G140: 46159 | H140: METRC-4424802 | I140: Approved | J140: No | K140: Clear | L140: Compliance
A141: ORD000755 | B141: 46112 | C141: DSP0015 | D141: CA | E141: SKU0001 | F141: Expiring Soon | G141: 46199 | H141: METRC-5710481 | I141: Restricted | J141: Yes | K141: sku approval | L141: Distribution
A142: ORD000760 | B142: 46096 | C142: DSP0003 | D142: CA | E142: SKU0014 | F142: Valid | G142: 46247 | H142: METRC-4360522 | I142: Restricted | J142: Yes | K142: sku approval | L142: Compliance
A143: ORD000767 | B143: 46057 | C143: DSP0099 | D143: CA | E143: SKU0018 | F143: Valid | G143: 46212 | H143: METRC-4287651 | I143: Approved | J143: No | K143: Clear | L143: Sales Ops
A144: ORD000771 | B144: 46054 | C144: DSP0099 | D144: CA | E144: SKU0001 | F144: Valid | G144: 46177 | H144: METRC-2348130 | I144: Restricted | J144: Yes | K144: sku approval | L144: Distribution
A145: ORD000783 | B145: 46108 | C145: DSP0039 | D145: CA | E145: SKU0010 | F145: Expired | G145: 46260 | H145: METRC-8794881 | I145: Approved | J145: Yes | K145: license issue | L145: Sales Ops
A146: ORD000786 | B146: 46104 | C146: DSP0075 | D146: CA | E146: SKU0016 | F146: Expired | G146: 46090 | H146: METRC-7270382 | I146: Approved | J146: Yes | K146: license issue | L146: Distribution
A147: ORD000816 | B147: 46095 | C147: DSP0015 | D147: CA | E147: SKU0009 | F147: Valid | G147: 46103 | I147: Approved | J147: Yes | K147: missing manifest | L147: Distribution
A148: ORD000834 | B148: 46065 | C148: DSP0075 | D148: CA | E148: SKU0019 | F148: Missing | G148: 46131 | H148: METRC-9117617 | I148: Approved | J148: Yes | K148: license issue | L148: Sales Ops
A149: ORD000839 | B149: 46071 | C149: DSP0087 | D149: CA | E149: SKU0005 | F149: Valid | G149: 46211 | H149: METRC-7650446 | I149: Approved | J149: No | K149: Clear | L149: Distribution
...

Sheet customer_support_cases
A1: case_id | B1: order_id | C1: customer_id | D1: issue_type | E1: opened_date | F1: resolved_date | G1: owner_team | H1: escalation_flag | I1: resolution_status | J1: sla_hours | K1: hours_to_resolve | L1: sla_status | M1: case_notes
A2: CASE000001 | B2: ORD000181 | C2: DSP0008 | D2: Missing Product | E2: 46152 | F2: 46157.583 | G2: Distribution | H2: No | I2: Resolved | J2: 24 | K2: =IF(F2="",(TODAY()-E2)*24,(F2-E2)*24) -> 134 | L2: =IF(K2>J2,"Breach","OK") -> Breach | M2: Missing Product routed for owner follow-up
A3: CASE000002 | B3: ORD000185 | C3: DSP0079 | D3: Credit Memo Request | E3: 46071 | F3: 46074.458 | G3: Distribution | H3: No | I3: Resolved | J3: 24 | K3: =IF(F3="",(TODAY()-E3)*24,(F3-E3)*24) -> 83 | L3: =IF(K3>J3,"Breach","OK") -> Breach | M3: Credit Memo Request routed for owner follow-up
A4: CASE000003 | B4: ORD000881 | C4: DSP0077 | D4: Refused Delivery | E4: 46113 | F4: 46115.125 | G4: Customer Success | H4: No | I4: Closed | J4: 96 | K4: =IF(F4="",(TODAY()-E4)*24,(F4-E4)*24) -> 51 | L4: =IF(K4>J4,"Breach","OK") -> OK | M4: Refused Delivery routed for owner follow-up
A5: CASE000004 | B5: ORD000323 | C5: DSP0088 | D5: Pricing Discrepancy | E5: 46141 | G5: Compliance | H5: No | I5: In Progress | J5: 96 | K5: =IF(F5="",(TODAY()-E5)*24,(F5-E5)*24) -> 408 | L5: =IF(K5>J5,"Breach","OK") -> Breach | M5: Pricing Discrepancy routed for owner follow-up
A6: CASE000005 | B6: ORD000126 | C6: DSP0011 | D6: Credit Memo Request | E6: 46108 | F6: 46110.25 | G6: Sales Ops | H6: No | I6: Closed | J6: 48 | K6: =IF(F6="",(TODAY()-E6)*24,(F6-E6)*24) -> 54 | L6: =IF(K6>J6,"Breach","OK") -> Breach | M6: Credit Memo Request routed for owner follow-up
A7: CASE000006 | B7: ORD000260 | C7: DSP0051 | D7: Compliance Hold | E7: 46110 | G7: Compliance | H7: No | I7: Open | J7: 48 | K7: =IF(F7="",(TODAY()-E7)*24,(F7-E7)*24) -> 1152 | L7: =IF(K7>J7,"Breach","OK") -> Breach | M7: Compliance Hold routed for owner follow-up
A8: CASE000007 | B8: ORD000598 | C8: DSP0091 | D8: Pricing Discrepancy | E8: 46041 | F8: 46044.292 | G8: Customer Success | H8: No | I8: Closed | J8: 24 | K8: =IF(F8="",(TODAY()-E8)*24,(F8-E8)*24) -> 79 | L8: =IF(K8>J8,"Breach","OK") -> Breach | M8: Pricing Discrepancy routed for owner follow-up
A9: CASE000008 | B9: ORD000837 | C9: DSP0081 | D9: Damaged Shipment | E9: 46149 | F9: 46149.667 | G9: Finance | H9: No | I9: Resolved | J9: 24 | K9: =IF(F9="",(TODAY()-E9)*24,(F9-E9)*24) -> 16 | L9: =IF(K9>J9,"Breach","OK") -> OK | M9: Damaged Shipment routed for owner follow-up
A10: CASE000009 | B10: ORD000880 | C10: DSP0028 | D10: Pricing Discrepancy | E10: 46064 | F10: 46065.625 | G10: Finance | H10: No | I10: Closed | J10: 48 | K10: =IF(F10="",(TODAY()-E10)*24,(F10-E10)*24) -> 39 | L10: =IF(K10>J10,"Breach","OK") -> OK | M10: Pricing Discrepancy routed for owner follow-up
A11: CASE000010 | B11: ORD000760 | C11: DSP0003 | D11: Compliance Hold | E11: 46113 | F11: 46115.792 | G11: Compliance | H11: No | I11: Closed | J11: 96 | K11: =IF(F11="",(TODAY()-E11)*24,(F11-E11)*24) -> 67 | L11: =IF(K11>J11,"Breach","OK") -> OK | M11: Compliance Hold routed for owner follow-up
A12: CASE000011 | B12: ORD000380 | C12: DSP0035 | D12: Invoice Mismatch | E12: 46074 | G12: Finance | H12: No | I12: Open | J12: 96 | K12: =IF(F12="",(TODAY()-E12)*24,(F12-E12)*24) -> 2016 | L12: =IF(K12>J12,"Breach","OK") -> Breach | M12: Invoice Mismatch routed for owner follow-up
A13: CASE000012 | B13: ORD000137 | C13: DSP0088 | D13: Missing Product | E13: 46079 | F13: 46083.792 | G13: Sales Ops | H13: Yes | I13: Resolved | J13: 72 | K13: =IF(F13="",(TODAY()-E13)*24,(F13-E13)*24) -> 115 | L13: =IF(K13>J13,"Breach","OK") -> Breach | M13: Missing Product routed for owner follow-up
A14: CASE000013 | B14: ORD000716 | C14: DSP0097 | D14: Invoice Mismatch | E14: 46066 | G14: Customer Success | H14: Yes | I14: In Progress | J14: 72 | K14: =IF(F14="",(TODAY()-E14)*24,(F14-E14)*24) -> 2208 | L14: =IF(K14>J14,"Breach","OK") -> Breach | M14: Invoice Mismatch routed for owner follow-up
A15: CASE000014 | B15: ORD000742 | C15: DSP0103 | D15: Pricing Discrepancy | E15: 46076 | F15: 46081.042 | G15: Compliance | H15: No | I15: Closed | J15: 96 | K15: =IF(F15="",(TODAY()-E15)*24,(F15-E15)*24) -> 121 | L15: =IF(K15>J15,"Breach","OK") -> Breach | M15: Pricing Discrepancy routed for owner follow-up
A16: CASE000015 | B16: ORD000287 | C16: DSP0043 | D16: Invoice Mismatch | E16: 46042 | G16: Distribution | H16: No | I16: In Progress | J16: 72 | K16: =IF(F16="",(TODAY()-E16)*24,(F16-E16)*24) -> 2784 | L16: =IF(K16>J16,"Breach","OK") -> Breach | M16: Invoice Mismatch routed for owner follow-up
A17: CASE000016 | B17: ORD000291 | C17: DSP0070 | D17: Pricing Discrepancy | E17: 46083 | F17: 46083.333 | G17: Finance | H17: No | I17: Resolved | J17: 96 | K17: =IF(F17="",(TODAY()-E17)*24,(F17-E17)*24) -> 8 | L17: =IF(K17>J17,"Breach","OK") -> OK | M17: Pricing Discrepancy routed for owner follow-up
A18: CASE000017 | B18: ORD000219 | C18: DSP0043 | D18: Credit Memo Request | E18: 46079 | F18: 46080 | G18: Distribution | H18: No | I18: Resolved | J18: 72 | K18: =IF(F18="",(TODAY()-E18)*24,(F18-E18)*24) -> 24 | L18: =IF(K18>J18,"Breach","OK") -> OK | M18: Credit Memo Request routed for owner follow-up
A19: CASE000018 | B19: ORD000143 | C19: DSP0088 | D19: Pricing Discrepancy | E19: 46071 | F19: 46076.75 | G19: Finance | H19: No | I19: Closed | J19: 96 | K19: =IF(F19="",(TODAY()-E19)*24,(F19-E19)*24) -> 138 | L19: =IF(K19>J19,"Breach","OK") -> Breach | M19: Pricing Discrepancy routed for owner follow-up
A20: CASE000019 | B20: ORD000833 | C20: DSP0026 | D20: Credit Memo Request | E20: 46113 | F20: 46114.625 | G20: Sales Ops | H20: No | I20: Resolved | J20: 24 | K20: =IF(F20="",(TODAY()-E20)*24,(F20-E20)*24) -> 39 | L20: =IF(K20>J20,"Breach","OK") -> Breach | M20: Credit Memo Request routed for owner follow-up
A21: CASE000020 | B21: ORD000538 | C21: DSP0028 | D21: Pricing Discrepancy | E21: 46119 | F21: 46122.583 | G21: Sales Ops | H21: No | I21: Resolved | J21: 72 | K21: =IF(F21="",(TODAY()-E21)*24,(F21-E21)*24) -> 86 | L21: =IF(K21>J21,"Breach","OK") -> Breach | M21: Pricing Discrepancy routed for owner follow-up
A22: CASE000021 | B22: ORD000749 | C22: DSP0010 | D22: Pricing Discrepancy | E22: 46098 | G22: Customer Success | H22: Yes | I22: Open | J22: 72 | K22: =IF(F22="",(TODAY()-E22)*24,(F22-E22)*24) -> 1440 | L22: =IF(K22>J22,"Breach","OK") -> Breach | M22: Pricing Discrepancy routed for owner follow-up
A23: CASE000022 | B23: ORD000684 | C23: DSP0093 | D23: Credit Memo Request | E23: 46059 | G23: Compliance | H23: No | I23: Open | J23: 24 | K23: =IF(F23="",(TODAY()-E23)*24,(F23-E23)*24) -> 2376 | L23: =IF(K23>J23,"Breach","OK") -> Breach | M23: Credit Memo Request routed for owner follow-up
A24: CASE000023 | B24: ORD000544 | C24: DSP0068 | D24: Invoice Mismatch | E24: 46090 | F24: 46092 | G24: Customer Success | H24: No | I24: Resolved | J24: 24 | K24: =IF(F24="",(TODAY()-E24)*24,(F24-E24)*24) -> 48 | L24: =IF(K24>J24,"Breach","OK") -> Breach | M24: Invoice Mismatch routed for owner follow-up
A25: CASE000024 | B25: ORD000505 | C25: DSP0026 | D25: Pricing Discrepancy | E25: 46077 | G25: Distribution | H25: No | I25: Open | J25: 72 | K25: =IF(F25="",(TODAY()-E25)*24,(F25-E25)*24) -> 1944 | L25: =IF(K25>J25,"Breach","OK") -> Breach | M25: Pricing Discrepancy routed for owner follow-up
A26: CASE000025 | B26: ORD000430 | C26: DSP0047 | D26: Missing Product | E26: 46072 | F26: 46074.833 | G26: Finance | H26: No | I26: Resolved | J26: 48 | K26: =IF(F26="",(TODAY()-E26)*24,(F26-E26)*24) -> 68 | L26: =IF(K26>J26,"Breach","OK") -> Breach | M26: Missing Product routed for owner follow-up
A27: CASE000026 | B27: ORD000907 | C27: DSP0087 | D27: Missing Product | E27: 46029 | G27: Compliance | H27: Yes | I27: In Progress | J27: 24 | K27: =IF(F27="",(TODAY()-E27)*24,(F27-E27)*24) -> 3096 | L27: =IF(K27>J27,"Breach","OK") -> Breach | M27: Missing Product routed for owner follow-up
A28: CASE000027 | B28: ORD000139 | C28: DSP0115 | D28: Credit Memo Request | E28: 46145 | F28: 46148.917 | G28: Sales Ops | H28: Yes | I28: Closed | J28: 48 | K28: =IF(F28="",(TODAY()-E28)*24,(F28-E28)*24) -> 94 | L28: =IF(K28>J28,"Breach","OK") -> Breach | M28: Credit Memo Request routed for owner follow-up
A29: CASE000028 | B29: ORD000374 | C29: DSP0105 | D29: Missing Product | E29: 46051 | F29: 46052.125 | G29: Sales Ops | H29: No | I29: Closed | J29: 48 | K29: =IF(F29="",(TODAY()-E29)*24,(F29-E29)*24) -> 27 | L29: =IF(K29>J29,"Breach","OK") -> OK | M29: Missing Product routed for owner follow-up
A30: CASE000029 | B30: ORD000392 | C30: DSP0103 | D30: Refused Delivery | E30: 46093 | F30: 46095.458 | G30: Distribution | H30: No | I30: Resolved | J30: 72 | K30: =IF(F30="",(TODAY()-E30)*24,(F30-E30)*24) -> 59 | L30: =IF(K30>J30,"Breach","OK") -> OK | M30: Refused Delivery routed for owner follow-up
A31: CASE000030 | B31: ORD000333 | C31: DSP0037 | D31: Damaged Shipment | E31: 46121 | F31: 46125.833 | G31: Sales Ops | H31: Yes | I31: Resolved | J31: 48 | K31: =IF(F31="",(TODAY()-E31)*24,(F31-E31)*24) -> 116 | L31: =IF(K31>J31,"Breach","OK") -> Breach | M31: Damaged Shipment routed for owner follow-up
A32: CASE000031 | B32: ORD000502 | C32: DSP0041 | D32: Invoice Mismatch | E32: 46111 | G32: Customer Success | H32: No | I32: Open | J32: 72 | K32: =IF(F32="",(TODAY()-E32)*24,(F32-E32)*24) -> 1128 | L32: =IF(K32>J32,"Breach","OK") -> Breach | M32: Invoice Mismatch routed for owner follow-up
A33: CASE000032 | B33: ORD000283 | C33: DSP0012 | D33: Missing Product | E33: 46081 | F33: 46084.042 | G33: Customer Success | H33: No | I33: Resolved | J33: 48 | K33: =IF(F33="",(TODAY()-E33)*24,(F33-E33)*24) -> 73 | L33: =IF(K33>J33,"Breach","OK") -> Breach | M33: Missing Product routed for owner follow-up
A34: CASE000033 | B34: ORD000683 | C34: DSP0014 | D34: Compliance Hold | E34: 46038 | G34: Distribution | H34: No | I34: Open | J34: 24 | K34: =IF(F34="",(TODAY()-E34)*24,(F34-E34)*24) -> 2880 | L34: =IF(K34>J34,"Breach","OK") -> Breach | M34: Compliance Hold routed for owner follow-up
A35: CASE000034 | B35: ORD000467 | C35: DSP0002 | D35: Compliance Hold | E35: 46130 | F35: 46135.375 | G35: Customer Success | H35: Yes | I35: Resolved | J35: 24 | K35: =IF(F35="",(TODAY()-E35)*24,(F35-E35)*24) -> 129 | L35: =IF(K35>J35,"Breach","OK") -> Breach | M35: Compliance Hold routed for owner follow-up
A36: CASE000035 | B36: ORD000112 | C36: DSP0098 | D36: Missing Product | E36: 46062 | F36: 46065.667 | G36: Distribution | H36: No | I36: Resolved | J36: 24 | K36: =IF(F36="",(TODAY()-E36)*24,(F36-E36)*24) -> 88 | L36: =IF(K36>J36,"Breach","OK") -> Breach | M36: Missing Product routed for owner follow-up
A37: CASE000036 | B37: ORD000515 | C37: DSP0006 | D37: Invoice Mismatch | E37: 46145 | F37: 46147.167 | G37: Finance | H37: No | I37: Closed | J37: 72 | K37: =IF(F37="",(TODAY()-E37)*24,(F37-E37)*24) -> 52 | L37: =IF(K37>J37,"Breach","OK") -> OK | M37: Invoice Mismatch routed for owner follow-up
A38: CASE000037 | B38: ORD000644 | C38: DSP0120 | D38: Compliance Hold | E38: 46099 | G38: Distribution | H38: No | I38: In Progress | J38: 96 | K38: =IF(F38="",(TODAY()-E38)*24,(F38-E38)*24) -> 1416 | L38: =IF(K38>J38,"Breach","OK") -> Breach | M38: Compliance Hold routed for owner follow-up
A39: CASE000038 | B39: ORD000449 | C39: DSP0059 | D39: Damaged Shipment | E39: 46127 | F39: 46131.167 | G39: Distribution | H39: No | I39: Resolved | J39: 72 | K39: =IF(F39="",(TODAY()-E39)*24,(F39-E39)*24) -> 100 | L39: =IF(K39>J39,"Breach","OK") -> Breach | M39: Damaged Shipment routed for owner follow-up
A40: CASE000039 | B40: ORD000394 | C40: DSP0014 | D40: Missing Product | E40: 46105 | G40: Sales Ops | H40: No | I40: Open | J40: 48 | K40: =IF(F40="",(TODAY()-E40)*24,(F40-E40)*24) -> 1272 | L40: =IF(K40>J40,"Breach","OK") -> Breach | M40: Missing Product routed for owner follow-up
A41: CASE000040 | B41: ORD000711 | C41: DSP0104 | D41: Credit Memo Request | E41: 46156 | G41: Distribution | H41: Yes | I41: In Progress | J41: 24 | K41: =IF(F41="",(TODAY()-E41)*24,(F41-E41)*24) -> 48 | L41: =IF(K41>J41,"Breach","OK") -> Breach | M41: Credit Memo Request routed for owner follow-up
A42: CASE000041 | B42: ORD000766 | C42: DSP0056 | D42: Pricing Discrepancy | E42: 46105 | F42: 46106.583 | G42: Sales Ops | H42: No | I42: Resolved | J42: 48 | K42: =IF(F42="",(TODAY()-E42)*24,(F42-E42)*24) -> 38 | L42: =IF(K42>J42,"Breach","OK") -> OK | M42: Pricing Discrepancy routed for owner follow-up
A43: CASE000042 | B43: ORD000903 | C43: DSP0063 | D43: Compliance Hold | E43: 46040 | F43: 46041.167 | G43: Distribution | H43: No | I43: Resolved | J43: 24 | K43: =IF(F43="",(TODAY()-E43)*24,(F43-E43)*24) -> 28 | L43: =IF(K43>J43,"Breach","OK") -> Breach | M43: Compliance Hold routed for owner follow-up
A44: CASE000043 | B44: ORD000477 | C44: DSP0082 | D44: Damaged Shipment | E44: 46049 | G44: Customer Success | H44: No | I44: In Progress | J44: 72 | K44: =IF(F44="",(TODAY()-E44)*24,(F44-E44)*24) -> 2616 | L44: =IF(K44>J44,"Breach","OK") -> Breach | M44: Damaged Shipment routed for owner follow-up
A45: CASE000044 | B45: ORD000741 | C45: DSP0085 | D45: Pricing Discrepancy | E45: 46082 | G45: Customer Success | H45: No | I45: Open | J45: 72 | K45: =IF(F45="",(TODAY()-E45)*24,(F45-E45)*24) -> 1824 | L45: =IF(K45>J45,"Breach","OK") -> Breach | M45: Pricing Discrepancy routed for owner follow-up
A46: CASE000045 | B46: ORD000204 | C46: DSP0080 | D46: Damaged Shipment | E46: 46065 | F46: 46068.333 | G46: Sales Ops | H46: No | I46: Resolved | J46: 48 | K46: =IF(F46="",(TODAY()-E46)*24,(F46-E46)*24) -> 80 | L46: =IF(K46>J46,"Breach","OK") -> Breach | M46: Damaged Shipment routed for owner follow-up
A47: CASE000046 | B47: ORD000658 | C47: DSP0115 | D47: Damaged Shipment | E47: 46131 | G47: Sales Ops | H47: No | I47: In Progress | J47: 24 | K47: =IF(F47="",(TODAY()-E47)*24,(F47-E47)*24) -> 648 | L47: =IF(K47>J47,"Breach","OK") -> Breach | M47: Damaged Shipment routed for owner follow-up
A48: CASE000047 | B48: ORD000090 | C48: DSP0091 | D48: Missing Product | E48: 46098 | F48: 46103.792 | G48: Compliance | H48: No | I48: Closed | J48: 48 | K48: =IF(F48="",(TODAY()-E48)*24,(F48-E48)*24) -> 139 | L48: =IF(K48>J48,"Breach","OK") -> Breach | M48: Missing Product routed for owner follow-up
A49: CASE000048 | B49: ORD000202 | C49: DSP0117 | D49: Refused Delivery | E49: 46122 | F49: 46125.208 | G49: Distribution | H49: Yes | I49: Resolved | J49: 24 | K49: =IF(F49="",(TODAY()-E49)*24,(F49-E49)*24) -> 77 | L49: =IF(K49>J49,"Breach","OK") -> Breach | M49: Refused Delivery routed for owner follow-up
A50: CASE000049 | B50: ORD000797 | C50: DSP0101 | D50: Credit Memo Request | E50: 46055 | F50: 46059.792 | G50: Distribution | H50: No | I50: Resolved | J50: 48 | K50: =IF(F50="",(TODAY()-E50)*24,(F50-E50)*24) -> 115 | L50: =IF(K50>J50,"Breach","OK") -> Breach | M50: Credit Memo Request routed for owner follow-up
A51: CASE000050 | B51: ORD000064 | C51: DSP0048 | D51: Credit Memo Request | E51: 46121 | F51: 46123.208 | G51: Customer Success | H51: Yes | I51: Resolved | J51: 72 | K51: =IF(F51="",(TODAY()-E51)*24,(F51-E51)*24) -> 53 | L51: =IF(K51>J51,"Breach","OK") -> OK | M51: Credit Memo Request routed for owner follow-up
A52: CASE000051 | B52: ORD000481 | C52: DSP0072 | D52: Pricing Discrepancy | E52: 46129 | F52: 46129.375 | G52: Distribution | H52: No | I52: Closed | J52: 24 | K52: =IF(F52="",(TODAY()-E52)*24,(F52-E52)*24) -> 9 | L52: =IF(K52>J52,"Breach","OK") -> OK | M52: Pricing Discrepancy routed for owner follow-up
A53: CASE000052 | B53: ORD000814 | C53: DSP0091 | D53: Invoice Mismatch | E53: 46050 | G53: Distribution | H53: No | I53: In Progress | J53: 96 | K53: =IF(F53="",(TODAY()-E53)*24,(F53-E53)*24) -> 2592 | L53: =IF(K53>J53,"Breach","OK") -> Breach | M53: Invoice Mismatch routed for owner follow-up
A54: CASE000053 | B54: ORD000919 | C54: DSP0099 | D54: Damaged Shipment | E54: 46040 | F54: 46041.083 | G54: Finance | H54: No | I54: Closed | J54: 96 | K54: =IF(F54="",(TODAY()-E54)*24,(F54-E54)*24) -> 26 | L54: =IF(K54>J54,"Breach","OK") -> OK | M54: Damaged Shipment routed for owner follow-up
A55: CASE000054 | B55: ORD000524 | C55: DSP0046 | D55: Pricing Discrepancy | E55: 46115 | G55: Sales Ops | H55: No | I55: In Progress | J55: 24 | K55: =IF(F55="",(TODAY()-E55)*24,(F55-E55)*24) -> 1032 | L55: =IF(K55>J55,"Breach","OK") -> Breach | M55: Pricing Discrepancy routed for owner follow-up
A56: CASE000055 | B56: ORD000762 | C56: DSP0076 | D56: Damaged Shipment | E56: 46146 | G56: Finance | H56: No | I56: Open | J56: 24 | K56: =IF(F56="",(TODAY()-E56)*24,(F56-E56)*24) -> 288 | L56: =IF(K56>J56,"Breach","OK") -> Breach | M56: Damaged Shipment routed for owner follow-up
A57: CASE000056 | B57: ORD000577 | C57: DSP0052 | D57: Refused Delivery | E57: 46088 | F57: 46092.375 | G57: Customer Success | H57: No | I57: Resolved | J57: 72 | K57: =IF(F57="",(TODAY()-E57)*24,(F57-E57)*24) -> 105 | L57: =IF(K57>J57,"Breach","OK") -> Breach | M57: Refused Delivery routed for owner follow-up
A58: CASE000057 | B58: ORD000739 | C58: DSP0099 | D58: Pricing Discrepancy | E58: 46110 | F58: 46111.708 | G58: Compliance | H58: No | I58: Resolved | J58: 24 | K58: =IF(F58="",(TODAY()-E58)*24,(F58-E58)*24) -> 41 | L58: =IF(K58>J58,"Breach","OK") -> Breach | M58: Pricing Discrepancy routed for owner follow-up
A59: CASE000058 | B59: ORD000836 | C59: DSP0052 | D59: Compliance Hold | E59: 46132 | G59: Distribution | H59: No | I59: In Progress | J59: 96 | K59: =IF(F59="",(TODAY()-E59)*24,(F59-E59)*24) -> 624 | L59: =IF(K59>J59,"Breach","OK") -> Breach | M59: Compliance Hold routed for owner follow-up
A60: CASE000059 | B60: ORD000025 | C60: DSP0071 | D60: Late Shipment | E60: 46128 | G60: Customer Success | H60: No | I60: In Progress | J60: 96 | K60: =IF(F60="",(TODAY()-E60)*24,(F60-E60)*24) -> 720 | L60: =IF(K60>J60,"Breach","OK") -> Breach | M60: Late Shipment routed for owner follow-up
A61: CASE000060 | B61: ORD000130 | C61: DSP0074 | D61: Damaged Shipment | E61: 46095 | F61: 46096.708 | G61: Distribution | H61: No | I61: Resolved | J61: 72 | K61: =IF(F61="",(TODAY()-E61)*24,(F61-E61)*24) -> 41 | L61: =IF(K61>J61,"Breach","OK") -> OK | M61: Damaged Shipment routed for owner follow-up
A62: CASE000061 | B62: ORD000409 | C62: DSP0028 | D62: Invoice Mismatch | E62: 46096 | G62: Sales Ops | H62: No | I62: Open | J62: 96 | K62: =IF(F62="",(TODAY()-E62)*24,(F62-E62)*24) -> 1488 | L62: =IF(K62>J62,"Breach","OK") -> Breach | M62: Invoice Mismatch routed for owner follow-up
A63: CASE000062 | B63: ORD000292 | C63: DSP0104 | D63: Refused Delivery | E63: 46037 | F63: 46042.667 | G63: Finance | H63: No | I63: Resolved | J63: 96 | K63: =IF(F63="",(TODAY()-E63)*24,(F63-E63)*24) -> 136 | L63: =IF(K63>J63,"Breach","OK") -> Breach | M63: Refused Delivery routed for owner follow-up
A64: CASE000063 | B64: ORD000877 | C64: DSP0107 | D64: Refused Delivery | E64: 46122 | G64: Finance | H64: Yes | I64: In Progress | J64: 96 | K64: =IF(F64="",(TODAY()-E64)*24,(F64-E64)*24) -> 864 | L64: =IF(K64>J64,"Breach","OK") -> Breach | M64: Refused Delivery routed for owner follow-up
A65: CASE000064 | B65: ORD000828 | C65: DSP0055 | D65: Pricing Discrepancy | E65: 46111 | F65: 46111.667 | G65: Customer Success | H65: No | I65: Closed | J65: 24 | K65: =IF(F65="",(TODAY()-E65)*24,(F65-E65)*24) -> 16 | L65: =IF(K65>J65,"Breach","OK") -> OK | M65: Pricing Discrepancy routed for owner follow-up
A66: CASE000065 | B66: ORD000206 | C66: DSP0071 | D66: Pricing Discrepancy | E66: 46038 | F66: 46041 | G66: Distribution | H66: No | I66: Closed | J66: 24 | K66: =IF(F66="",(TODAY()-E66)*24,(F66-E66)*24) -> 72 | L66: =IF(K66>J66,"Breach","OK") -> Breach | M66: Pricing Discrepancy routed for owner follow-up
A67: CASE000066 | B67: ORD000860 | C67: DSP0078 | D67: Missing Product | E67: 46039 | G67: Sales Ops | H67: No | I67: Open | J67: 72 | K67: =IF(F67="",(TODAY()-E67)*24,(F67-E67)*24) -> 2856 | L67: =IF(K67>J67,"Breach","OK") -> Breach | M67: Missing Product routed for owner follow-up
A68: CASE000067 | B68: ORD000007 | C68: DSP0044 | D68: Late Shipment | E68: 46125 | G68: Compliance | H68: No | I68: Open | J68: 72 | K68: =IF(F68="",(TODAY()-E68)*24,(F68-E68)*24) -> 792 | L68: =IF(K68>J68,"Breach","OK") -> Breach | M68: Late Shipment routed for owner follow-up
A69: CASE000068 | B69: ORD000270 | C69: DSP0115 | D69: Damaged Shipment | E69: 46122 | F69: 46122.375 | G69: Finance | H69: No | I69: Resolved | J69: 72 | K69: =IF(F69="",(TODAY()-E69)*24,(F69-E69)*24) -> 9 | L69: =IF(K69>J69,"Breach","OK") -> OK | M69: Damaged Shipment routed for owner follow-up
A70: CASE000069 | B70: ORD000104 | C70: DSP0040 | D70: Invoice Mismatch | E70: 46075 | G70: Distribution | H70: No | I70: Open | J70: 96 | K70: =IF(F70="",(TODAY()-E70)*24,(F70-E70)*24) -> 1992 | L70: =IF(K70>J70,"Breach","OK") -> Breach | M70: Invoice Mismatch routed for owner follow-up
A71: CASE000070 | B71: ORD000410 | C71: DSP0099 | D71: Credit Memo Request | E71: 46128 | G71: Customer Success | H71: No | I71: In Progress | J71: 48 | K71: =IF(F71="",(TODAY()-E71)*24,(F71-E71)*24) -> 720 | L71: =IF(K71>J71,"Breach","OK") -> Breach | M71: Credit Memo Request routed for owner follow-up
A72: CASE000071 | B72: ORD000856 | C72: DSP0095 | D72: Pricing Discrepancy | E72: 46091 | G72: Sales Ops | H72: No | I72: Open | J72: 48 | K72: =IF(F72="",(TODAY()-E72)*24,(F72-E72)*24) -> 1608 | L72: =IF(K72>J72,"Breach","OK") -> Breach | M72: Pricing Discrepancy routed for owner follow-up
A73: CASE000072 | B73: ORD000146 | C73: DSP0079 | D73: Refused Delivery | E73: 46066 | G73: Customer Success | H73: No | I73: Open | J73: 72 | K73: =IF(F73="",(TODAY()-E73)*24,(F73-E73)*24) -> 2208 | L73: =IF(K73>J73,"Breach","OK") -> Breach | M73: Refused Delivery routed for owner follow-up
A74: CASE000073 | B74: ORD000318 | C74: DSP0110 | D74: Late Shipment | E74: 46091 | G74: Finance | H74: No | I74: In Progress | J74: 48 | K74: =IF(F74="",(TODAY()-E74)*24,(F74-E74)*24) -> 1608 | L74: =IF(K74>J74,"Breach","OK") -> Breach | M74: Late Shipment routed for owner follow-up
A75: CASE000074 | B75: ORD000036 | C75: DSP0067 | D75: Damaged Shipment | E75: 46156 | G75: Distribution | H75: No | I75: Open | J75: 24 | K75: =IF(F75="",(TODAY()-E75)*24,(F75-E75)*24) -> 48 | L75: =IF(K75>J75,"Breach","OK") -> Breach | M75: Damaged Shipment routed for owner follow-up
A76: CASE000075 | B76: ORD000520 | C76: DSP0091 | D76: Pricing Discrepancy | E76: 46152 | F76: 46155.292 | G76: Compliance | H76: Yes | I76: Resolved | J76: 48 | K76: =IF(F76="",(TODAY()-E76)*24,(F76-E76)*24) -> 79 | L76: =IF(K76>J76,"Breach","OK") -> Breach | M76: Pricing Discrepancy routed for owner follow-up
A77: CASE000076 | B77: ORD000570 | C77: DSP0085 | D77: Credit Memo Request | E77: 46128 | F77: 46130.125 | G77: Sales Ops | H77: No | I77: Closed | J77: 96 | K77: =IF(F77="",(TODAY()-E77)*24,(F77-E77)*24) -> 51 | L77: =IF(K77>J77,"Breach","OK") -> OK | M77: Credit Memo Request routed for owner follow-up
A78: CASE000077 | B78: ORD000606 | C78: DSP0046 | D78: Damaged Shipment | E78: 46120 | G78: Customer Success | H78: No | I78: In Progress | J78: 96 | K78: =IF(F78="",(TODAY()-E78)*24,(F78-E78)*24) -> 912 | L78: =IF(K78>J78,"Breach","OK") -> Breach | M78: Damaged Shipment routed for owner follow-up
A79: CASE000078 | B79: ORD000511 | C79: DSP0090 | D79: Credit Memo Request | E79: 46089 | F79: 46089.333 | G79: Finance | H79: Yes | I79: Resolved | J79: 48 | K79: =IF(F79="",(TODAY()-E79)*24,(F79-E79)*24) -> 8 | L79: =IF(K79>J79,"Breach","OK") -> OK | M79: Credit Memo Request routed for owner follow-up
A80: CASE000079 | B80: ORD000858 | C80: DSP0117 | D80: Credit Memo Request | E80: 46106 | F80: 46106.542 | G80: Customer Success | H80: No | I80: Closed | J80: 24 | K80: =IF(F80="",(TODAY()-E80)*24,(F80-E80)*24) -> 13 | L80: =IF(K80>J80,"Breach","OK") -> OK | M80: Credit Memo Request routed for owner follow-up
A81: CASE000080 | B81: ORD000433 | C81: DSP0007 | D81: Damaged Shipment | E81: 46081 | F81: 46085.5 | G81: Customer Success | H81: No | I81: Closed | J81: 48 | K81: =IF(F81="",(TODAY()-E81)*24,(F81-E81)*24) -> 108 | L81: =IF(K81>J81,"Breach","OK") -> Breach | M81: Damaged Shipment routed for owner follow-up
A82: CASE000081 | B82: ORD000352 | C82: DSP0100 | D82: Refused Delivery | E82: 46132 | F82: 46136.042 | G82: Distribution | H82: Yes | I82: Resolved | J82: 72 | K82: =IF(F82="",(TODAY()-E82)*24,(F82-E82)*24) -> 97 | L82: =IF(K82>J82,"Breach","OK") -> Breach | M82: Refused Delivery routed for owner follow-up
A83: CASE000082 | B83: ORD000780 | C83: DSP0004 | D83: Credit Memo Request | E83: 46104 | F83: 46108.667 | G83: Customer Success | H83: No | I83: Resolved | J83: 72 | K83: =IF(F83="",(TODAY()-E83)*24,(F83-E83)*24) -> 112 | L83: =IF(K83>J83,"Breach","OK") -> Breach | M83: Credit Memo Request routed for owner follow-up
A84: CASE000083 | B84: ORD000397 | C84: DSP0006 | D84: Compliance Hold | E84: 46086 | F84: 46091.583 | G84: Compliance | H84: No | I84: Resolved | J84: 96 | K84: =IF(F84="",(TODAY()-E84)*24,(F84-E84)*24) -> 134 | L84: =IF(K84>J84,"Breach","OK") -> Breach | M84: Compliance Hold routed for owner follow-up
A85: CASE000084 | B85: ORD000332 | C85: DSP0051 | D85: Credit Memo Request | E85: 46052 | F85: 46057.583 | G85: Customer Success | H85: No | I85: Closed | J85: 24 | K85: =IF(F85="",(TODAY()-E85)*24,(F85-E85)*24) -> 134 | L85: =IF(K85>J85,"Breach","OK") -> Breach | M85: Credit Memo Request routed for owner follow-up
A86: CASE000085 | B86: ORD000461 | C86: DSP0011 | D86: Late Shipment | E86: 46062 | G86: Customer Success | H86: No | I86: In Progress | J86: 48 | K86: =IF(F86="",(TODAY()-E86)*24,(F86-E86)*24) -> 2304 | L86: =IF(K86>J86,"Breach","OK") -> Breach | M86: Late Shipment routed for owner follow-up
A87: CASE000086 | B87: ORD000288 | C87: DSP0055 | D87: Refused Delivery | E87: 46075 | F87: 46075.833 | G87: Sales Ops | H87: No | I87: Resolved | J87: 72 | K87: =IF(F87="",(TODAY()-E87)*24,(F87-E87)*24) -> 20 | L87: =IF(K87>J87,"Breach","OK") -> OK | M87: Refused Delivery routed for owner follow-up
A88: CASE000087 | B88: ORD000701 | C88: DSP0085 | D88: Invoice Mismatch | E88: 46080 | F88: 46081.25 | G88: Distribution | H88: Yes | I88: Closed | J88: 48 | K88: =IF(F88="",(TODAY()-E88)*24,(F88-E88)*24) -> 30 | L88: =IF(K88>J88,"Breach","OK") -> OK | M88: Invoice Mismatch routed for owner follow-up
A89: CASE000088 | B89: ORD000966 | C89: DSP0113 | D89: Damaged Shipment | E89: 46105 | G89: Finance | H89: Yes | I89: Open | J89: 96 | K89: =IF(F89="",(TODAY()-E89)*24,(F89-E89)*24) -> 1272 | L89: =IF(K89>J89,"Breach","OK") -> Breach | M89: Damaged Shipment routed for owner follow-up
A90: CASE000089 | B90: ORD000699 | C90: DSP0039 | D90: Credit Memo Request | E90: 46090 | G90: Distribution | H90: Yes | I90: In Progress | J90: 72 | K90: =IF(F90="",(TODAY()-E90)*24,(F90-E90)*24) -> 1632 | L90: =IF(K90>J90,"Breach","OK") -> Breach | M90: Credit Memo Request routed for owner follow-up
A91: CASE000090 | B91: ORD000565 | C91: DSP0091 | D91: Invoice Mismatch | E91: 46093 | G91: Distribution | H91: No | I91: In Progress | J91: 96 | K91: =IF(F91="",(TODAY()-E91)*24,(F91-E91)*24) -> 1560 | L91: =IF(K91>J91,"Breach","OK") -> Breach | M91: Invoice Mismatch routed for owner follow-up
A92: CASE000091 | B92: ORD000708 | C92: DSP0115 | D92: Damaged Shipment | E92: 46066 | F92: 46069.208 | G92: Sales Ops | H92: No | I92: Resolved | J92: 72 | K92: =IF(F92="",(TODAY()-E92)*24,(F92-E92)*24) -> 77 | L92: =IF(K92>J92,"Breach","OK") -> Breach | M92: Damaged Shipment routed for owner follow-up
A93: CASE000092 | B93: ORD000581 | C93: DSP0055 | D93: Credit Memo Request | E93: 46037 | G93: Sales Ops | H93: No | I93: In Progress | J93: 96 | K93: =IF(F93="",(TODAY()-E93)*24,(F93-E93)*24) -> 2904 | L93: =IF(K93>J93,"Breach","OK") -> Breach | M93: Credit Memo Request routed for owner follow-up
A94: CASE000093 | B94: ORD000096 | C94: DSP0083 | D94: Credit Memo Request | E94: 46079 | G94: Finance | H94: No | I94: In Progress | J94: 24 | K94: =IF(F94="",(TODAY()-E94)*24,(F94-E94)*24) -> 1896 | L94: =IF(K94>J94,"Breach","OK") -> Breach | M94: Credit Memo Request routed for owner follow-up
A95: CASE000094 | B95: ORD000065 | C95: DSP0009 | D95: Invoice Mismatch | E95: 46146 | G95: Finance | H95: No | I95: In Progress | J95: 72 | K95: =IF(F95="",(TODAY()-E95)*24,(F95-E95)*24) -> 288 | L95: =IF(K95>J95,"Breach","OK") -> Breach | M95: Invoice Mismatch routed for owner follow-up
A96: CASE000095 | B96: ORD000887 | C96: DSP0086 | D96: Damaged Shipment | E96: 46137 | G96: Finance | H96: No | I96: In Progress | J96: 48 | K96: =IF(F96="",(TODAY()-E96)*24,(F96-E96)*24) -> 504 | L96: =IF(K96>J96,"Breach","OK") -> Breach | M96: Damaged Shipment routed for owner follow-up
A97: CASE000096 | B97: ORD000586 | C97: DSP0119 | D97: Refused Delivery | E97: 46128 | G97: Compliance | H97: No | I97: In Progress | J97: 48 | K97: =IF(F97="",(TODAY()-E97)*24,(F97-E97)*24) -> 720 | L97: =IF(K97>J97,"Breach","OK") -> Breach | M97: Refused Delivery routed for owner follow-up
A98: CASE000097 | B98: ORD000091 | C98: DSP0010 | D98: Credit Memo Request | E98: 46111 | G98: Customer Success | H98: No | I98: In Progress | J98: 72 | K98: =IF(F98="",(TODAY()-E98)*24,(F98-E98)*24) -> 1128 | L98: =IF(K98>J98,"Breach","OK") -> Breach | M98: Credit Memo Request routed for owner follow-up
A99: CASE000098 | B99: ORD000194 | C99: DSP0028 | D99: Invoice Mismatch | E99: 46129 | F99: 46130.083 | G99: Finance | H99: Yes | I99: Resolved | J99: 96 | K99: =IF(F99="",(TODAY()-E99)*24,(F99-E99)*24) -> 26 | L99: =IF(K99>J99,"Breach","OK") -> OK | M99: Invoice Mismatch routed for owner follow-up
A100: CASE000099 | B100: ORD000282 | C100: DSP0016 | D100: Credit Memo Request | E100: 46044 | F100: 46045.458 | G100: Customer Success | H100: No | I100: Resolved | J100: 48 | K100: =IF(F100="",(TODAY()-E100)*24,(F100-E100)*24) -> 35 | L100: =IF(K100>J100,"Breach","OK") -> OK | M100: Credit Memo Request routed for owner follow-up
...

Sheet returns_credit_memos
A1: credit_memo_id | B1: original_order_id | C1: credit_date | D1: reason_code | E1: credit_amount | F1: status | G1: linked_invoice_exists
A2: CM000001 | B2: ORD000011 | C2: 46132 | D2: Return | E2: -107.72 | F2: Approved | G2: =IF(COUNTIF(erp_invoices!$B:$B,B2)>0,"Yes","No") -> Yes
A3: CM000002 | B3: ORD000018 | C3: 46128 | D3: Compliance Rejection | E3: -154.63 | F3: Posted | G3: =IF(COUNTIF(erp_invoices!$B:$B,B3)>0,"Yes","No") -> Yes
A4: CM000003 | B4: ORD000043 | C4: 46103 | D4: Compliance Rejection | E4: -32.1 | F4: Approved | G4: =IF(COUNTIF(erp_invoices!$B:$B,B4)>0,"Yes","No") -> Yes
A5: CM000004 | B5: ORD000072 | C5: 46084 | D5: Damaged Shipment | E5: -214.76 | F5: Posted | G5: =IF(COUNTIF(erp_invoices!$B:$B,B5)>0,"Yes","No") -> Yes
A6: CM000005 | B6: ORD000088 | C6: 46140 | D6: Pricing Adjustment | E6: -92.08 | F6: Posted | G6: =IF(COUNTIF(erp_invoices!$B:$B,B6)>0,"Yes","No") -> Yes
A7: CM000006 | B7: ORD000093 | C7: 46098 | D7: Compliance Rejection | E7: -123.42 | F7: Pending | G7: =IF(COUNTIF(erp_invoices!$B:$B,B7)>0,"Yes","No") -> No
A8: CM000007 | B8: ORD000106 | C8: 46056 | D8: Compliance Rejection | E8: -168.64 | F8: Approved | G8: =IF(COUNTIF(erp_invoices!$B:$B,B8)>0,"Yes","No") -> Yes
A9: CM000008 | B9: ORD000113 | C9: 46153 | D9: Damaged Shipment | E9: -63.2 | F9: Approved | G9: =IF(COUNTIF(erp_invoices!$B:$B,B9)>0,"Yes","No") -> Yes
A10: CM000009 | B10: ORD000114 | C10: 46111 | D10: Short Ship | E10: -117.43 | F10: Pending | G10: =IF(COUNTIF(erp_invoices!$B:$B,B10)>0,"Yes","No") -> Yes
A11: CM000010 | B11: ORD000115 | C11: 46113 | D11: Refusal | E11: -33.6 | F11: Approved | G11: =IF(COUNTIF(erp_invoices!$B:$B,B11)>0,"Yes","No") -> Yes
A12: CM000011 | B12: ORD000118 | C12: 46070 | D12: Pricing Adjustment | E12: -60.77 | F12: Posted | G12: =IF(COUNTIF(erp_invoices!$B:$B,B12)>0,"Yes","No") -> Yes
A13: CM000012 | B13: ORD000121 | C13: 46075 | D13: Damaged Shipment | E13: -32.28 | F13: Rejected | G13: =IF(COUNTIF(erp_invoices!$B:$B,B13)>0,"Yes","No") -> Yes
... A120: CM000119 | B120: ORD000992 | C120: 46095 | D120: Damaged Shipment | E120: -19.02 | F120: Pending | G120: =IF(COUNTIF(erp_invoices!$B:$B,B120)>0,"Yes","No") -> Yes

Sheet inventory_snapshot
A1: snapshot_date | B1: sku | C1: warehouse | D1: on_hand_qty | E1: available_qty | F1: allocated_qty
A2: 46143 | B2: SKU0001 | C2: WHSE_OR | D2: 456 | E2: 408 | F2: 48
A3: 46143 | B3: SKU0001 | C3: WHSE_WA | D3: 481 | E3: 391 | F3: 90
A4: 46143 | B4: SKU0001 | C4: WHSE_CA | D4: 518 | E4: 297 | F4: 221
A5: 46143 | B5: SKU0001 | C5: WHSE_CO | D5: 140 | E5: 133 | F5: 7
A6: 46143 | B6: SKU0001 | C6: WHSE_MW | D6: 387 | E6: 360 | F6: 27
A7: 46143 | B7: SKU0002 | C7: WHSE_OR | D7: 234 | E7: 166 | F7: 68
A8: 46143 | B8: SKU0002 | C8: WHSE_WA | D8: 472 | E8: 426 | F8: 46
A9: 46143 | B9: SKU0002 | C9: WHSE_CA | D9: 295 | E9: 276 | F9: 19
A10: 46143 | B10: SKU0002 | C10: WHSE_CO | D10: 603 | E10: 553 | F10: 50
A11: 46143 | B11: SKU0002 | C11: WHSE_MW | D11: 593 | E11: 586 | F11: 7
A12: 46143 | B12: SKU0003 | C12: WHSE_OR | D12: 282 | E12: 261 | F12: 21
A13: 46143 | B13: SKU0003 | C13: WHSE_WA | D13: 532 | E13: 478 | F13: 54
... A101: 46143 | B101: SKU0020 | C101: WHSE_MW | D101: 515 | E101: 345 | F101: 170

Sheet sales_forecast
A1: month_start | B1: state | C1: channel | D1: sku | E1: forecast_units | F1: actual_ordered_units | G1: actual_shipped_units | H1: forecast_variance_units | I1: forecast_accuracy_pct | J1: variance_reason
A2: 46023 | B2: AZ | C2: Wholesale | D2: SKU0018 | E2: 359 | F2: =SUMIFS(crm_orders!$J:$J,crm_orders!$B:$B,">="&A2,crm_orders!$B:$B,"<"&DATE(YEAR(A2),MONTH(A2)+1,1),crm_orders!$E:$E,B2,crm_orders!$G:$G,C2,crm_orders!$H:$H,D2) -> 0 | G2: =SUMIFS(warehouse_shipments!$H:$H,warehouse_shipments!$C:$C,">="&A2,warehouse_shipments!$C:$C,"<"&DATE(YEAR(A2),MONTH(A2)+1,1),warehouse_shipments!$P:$P,B2,warehouse_shipments!$Q:$Q,C2,warehouse_shipments!$R:$R,D2) -> 0 | H2: =F2-E2 -> -359 | I2: =IFERROR(1-ABS(H2)/E2,0) -> 0 | J2: Inventory constraint
A3: 46023 | B3: AZ | C3: Wholesale | D3: SKU0011 | E3: 438 | F3: =SUMIFS(crm_orders!$J:$J,crm_orders!$B:$B,">="&A3,crm_orders!$B:$B,"<"&DATE(YEAR(A3),MONTH(A3)+1,1),crm_orders!$E:$E,B3,crm_orders!$G:$G,C3,crm_orders!$H:$H,D3) -> 18 | G3: =SUMIFS(warehouse_shipments!$H:$H,warehouse_shipments!$C:$C,">="&A3,warehouse_shipments!$C:$C,"<"&DATE(YEAR(A3),MONTH(A3)+1,1),warehouse_shipments!$P:$P,B3,warehouse_shipments!$Q:$Q,C3,warehouse_shipments!$R:$R,D3) -> 0 | H3: =F3-E3 -> -420 | I3: =IFERROR(1-ABS(H3)/E3,0) -> 0.04109589 | J3: Promotion lift
A4: 46023 | B4: AZ | C4: Wholesale | D4: SKU0003 | E4: 89 | F4: =SUMIFS(crm_orders!$J:$J,crm_orders!$B:$B,">="&A4,crm_orders!$B:$B,"<"&DATE(YEAR(A4),MONTH(A4)+1,1),crm_orders!$E:$E,B4,crm_orders!$G:$G,C4,crm_orders!$H:$H,D4) -> 186 | G4: =SUMIFS(warehouse_shipments!$H:$H,warehouse_shipments!$C:$C,">="&A4,warehouse_shipments!$C:$C,"<"&DATE(YEAR(A4),MONTH(A4)+1,1),warehouse_shipments!$P:$P,B4,warehouse_shipments!$Q:$Q,C4,warehouse_shipments!$R:$R,D4) -> 24 | H4: =F4-E4 -> 97 | I4: =IFERROR(1-ABS(H4)/E4,0) -> -0.08988764 | J4: Promotion lift
A5: 46023 | B5: AZ | C5: Wholesale | D5: SKU0006 | E5: 319 | F5: =SUMIFS(crm_orders!$J:$J,crm_orders!$B:$B,">="&A5,crm_orders!$B:$B,"<"&DATE(YEAR(A5),MONTH(A5)+1,1),crm_orders!$E:$E,B5,crm_orders!$G:$G,C5,crm_orders!$H:$H,D5) -> 96 | G5: =SUMIFS(warehouse_shipments!$H:$H,warehouse_shipments!$C:$C,">="&A5,warehouse_shipments!$C:$C,"<"&DATE(YEAR(A5),MONTH(A5)+1,1),warehouse_shipments!$P:$P,B5,warehouse_shipments!$Q:$Q,C5,warehouse_shipments!$R:$R,D5) -> 96 | H5: =F5-E5 -> -223 | I5: =IFERROR(1-ABS(H5)/E5,0) -> 0.30094044 | J5: Promotion lift
A6: 46023 | B6: AZ | C6: Wholesale | D6: SKU0012 | E6: 318 | F6: =SUMIFS(crm_orders!$J:$J,crm_orders!$B:$B,">="&A6,crm_orders!$B:$B,"<"&DATE(YEAR(A6),MONTH(A6)+1,1),crm_orders!$E:$E,B6,crm_orders!$G:$G,C6,crm_orders!$H:$H,D6) -> 120 | G6: =SUMIFS(warehouse_shipments!$H:$H,warehouse_shipments!$C:$C,">="&A6,warehouse_shipments!$C:$C,"<"&DATE(YEAR(A6),MONTH(A6)+1,1),warehouse_shipments!$P:$P,B6,warehouse_shipments!$Q:$Q,C6,warehouse_shipments!$R:$R,D6) -> 0 | H6: =F6-E6 -> -198 | I6: =IFERROR(1-ABS(H6)/E6,0) -> 0.37735849 | J6: Distributor bulk order
A7: 46023 | B7: AZ | C7: Wholesale | D7: SKU0010 | E7: 346 | F7: =SUMIFS(crm_orders!$J:$J,crm_orders!$B:$B,">="&A7,crm_orders!$B:$B,"<"&DATE(YEAR(A7),MONTH(A7)+1,1),crm_orders!$E:$E,B7,crm_orders!$G:$G,C7,crm_orders!$H:$H,D7) -> 30 | G7: =SUMIFS(warehouse_shipments!$H:$H,warehouse_shipments!$C:$C,">="&A7,warehouse_shipments!$C:$C,"<"&DATE(YEAR(A7),MONTH(A7)+1,1),warehouse_shipments!$P:$P,B7,warehouse_shipments!$Q:$Q,C7,warehouse_shipments!$R:$R,D7) -> 30 | H7: =F7-E7 -> -316 | I7: =IFERROR(1-ABS(H7)/E7,0) -> 0.086705202 | J7: Distributor bulk order
A8: 46023 | B8: AZ | C8: Wholesale | D8: SKU0001 | E8: 329 | F8: =SUMIFS(crm_orders!$J:$J,crm_orders!$B:$B,">="&A8,crm_orders!$B:$B,"<"&DATE(YEAR(A8),MONTH(A8)+1,1),crm_orders!$E:$E,B8,crm_orders!$G:$G,C8,crm_orders!$H:$H,D8) -> 0 | G8: =SUMIFS(warehouse_shipments!$H:$H,warehouse_shipments!$C:$C,">="&A8,warehouse_shipments!$C:$C,"<"&DATE(YEAR(A8),MONTH(A8)+1,1),warehouse_shipments!$P:$P,B8,warehouse_shipments!$Q:$Q,C8,warehouse_shipments!$R:$R,D8) -> 0 | H8: =F8-E8 -> -329 | I8: =IFERROR(1-ABS(H8)/E8,0) -> 0 | J8: Demand timing
A9: 46023 | B9: AZ | C9: Wholesale | D9: SKU0009 | E9: 354 | F9: =SUMIFS(crm_orders!$J:$J,crm_orders!$B:$B,">="&A9,crm_orders!$B:$B,"<"&DATE(YEAR(A9),MONTH(A9)+1,1),crm_orders!$E:$E,B9,crm_orders!$G:$G,C9,crm_orders!$H:$H,D9) -> 6 | G9: =SUMIFS(warehouse_shipments!$H:$H,warehouse_shipments!$C:$C,">="&A9,warehouse_shipments!$C:$C,"<"&DATE(YEAR(A9),MONTH(A9)+1,1),warehouse_shipments!$P:$P,B9,warehouse_shipments!$Q:$Q,C9,warehouse_shipments!$R:$R,D9) -> 6 | H9: =F9-E9 -> -348 | I9: =IFERROR(1-ABS(H9)/E9,0) -> 0.016949153 | J9: Demand timing
A10: 46023 | B10: AZ | C10: Retail | D10: SKU0009 | E10: 105 | F10: =SUMIFS(crm_orders!$J:$J,crm_orders!$B:$B,">="&A10,crm_orders!$B:$B,"<"&DATE(YEAR(A10),MONTH(A10)+1,1),crm_orders!$E:$E,B10,crm_orders!$G:$G,C10,crm_orders!$H:$H,D10) -> 0 | G10: =SUMIFS(warehouse_shipments!$H:$H,warehouse_shipments!$C:$C,">="&A10,warehouse_shipments!$C:$C,"<"&DATE(YEAR(A10),MONTH(A10)+1,1),warehouse_shipments!$P:$P,B10,warehouse_shipments!$Q:$Q,C10,warehouse_shipments!$R:$R,D10) -> 0 | H10: =F10-E10 -> -105 | I10: =IFERROR(1-ABS(H10)/E10,0) -> 0 | J10: Inventory constraint
A11: 46023 | B11: AZ | C11: Retail | D11: SKU0010 | E11: 299 | F11: =SUMIFS(crm_orders!$J:$J,crm_orders!$B:$B,">="&A11,crm_orders!$B:$B,"<"&DATE(YEAR(A11),MONTH(A11)+1,1),crm_orders!$E:$E,B11,crm_orders!$G:$G,C11,crm_orders!$H:$H,D11) -> 0 | G11: =SUMIFS(warehouse_shipments!$H:$H,warehouse_shipments!$C:$C,">="&A11,warehouse_shipments!$C:$C,"<"&DATE(YEAR(A11),MONTH(A11)+1,1),warehouse_shipments!$P:$P,B11,warehouse_shipments!$Q:$Q,C11,warehouse_shipments!$R:$R,D11) -> 0 | H11: =F11-E11 -> -299 | I11: =IFERROR(1-ABS(H11)/E11,0) -> 0 | J11: Inventory constraint
A12: 46023 | B12: AZ | C12: Retail | D12: SKU0014 | E12: 103 | F12: =SUMIFS(crm_orders!$J:$J,crm_orders!$B:$B,">="&A12,crm_orders!$B:$B,"<"&DATE(YEAR(A12),MONTH(A12)+1,1),crm_orders!$E:$E,B12,crm_orders!$G:$G,C12,crm_orders!$H:$H,D12) -> 0 | G12: =SUMIFS(warehouse_shipments!$H:$H,warehouse_shipments!$C:$C,">="&A12,warehouse_shipments!$C:$C,"<"&DATE(YEAR(A12),MONTH(A12)+1,1),warehouse_shipments!$P:$P,B12,warehouse_shipments!$Q:$Q,C12,warehouse_shipments!$R:$R,D12) -> 0 | H12: =F12-E12 -> -103 | I12: =IFERROR(1-ABS(H12)/E12,0) -> 0 | J12: Promotion lift
A13: 46023 | B13: AZ | C13: Retail | D13: SKU0017 | E13: 393 | F13: =SUMIFS(crm_orders!$J:$J,crm_orders!$B:$B,">="&A13,crm_orders!$B:$B,"<"&DATE(YEAR(A13),MONTH(A13)+1,1),crm_orders!$E:$E,B13,crm_orders!$G:$G,C13,crm_orders!$H:$H,D13) -> 0 | G13: =SUMIFS(warehouse_shipments!$H:$H,warehouse_shipments!$C:$C,">="&A13,warehouse_shipments!$C:$C,"<"&DATE(YEAR(A13),MONTH(A13)+1,1),warehouse_shipments!$P:$P,B13,warehouse_shipments!$Q:$Q,C13,warehouse_shipments!$R:$R,D13) -> 0 | H13: =F13-E13 -> -393 | I13: =IFERROR(1-ABS(H13)/E13,0) -> 0 | J13: Promotion lift
... A1441: 46143 | B1441: WA | C1441: Distributor | D1441: SKU0018 | E1441: 329 | F1441: =SUMIFS(crm_orders!$J:$J,crm_orders!$B:$B,">="&A1441,crm_orders!$B:$B,"<"&DATE(YEAR(A1441),MONTH(A1441)+1,1),crm_orders!$E:$E,B1441,crm_orders!$G:$G,C1441,crm_orders!$H:$H,D1441) -> 0 | G1441: =SUMIFS(warehouse_shipments!$H:$H,warehouse_shipments!$C:$C,">="&A1441,warehouse_shipments!$C:$C,"<"&DATE(YEAR(A1441),MONTH(A1441)+1,1),warehouse_shipments!$P:$P,B1441,warehouse_shipments!$Q:$Q,C1441,warehouse_shipments!$R:$R,D1441) -> 0 | H1441: =F1441-E1441 -> -329 | I1441: =IFERROR(1-ABS(H1441)/E1441,0) -> 0 | J1441: Normal variance

Sheet source_file_manifest
A1: source_system | B1: file_name | C1: received_timestamp | D1: expected_row_count | E1: actual_row_count | F1: load_status | G1: refresh_owner | H1: control_notes
A2: Salesforce CRM | B2: crm_orders_2026_05.csv | C2: 46143.3 | D2: 1000 | E2: 1000 | F2: Loaded | G2: Sales Ops | H2: Primary CRM order extract
A3: Business Central ERP | B3: erp_invoices_2026_05.csv | C3: 46143.309 | D3: 934 | E3: 934 | F3: Loaded | G3: Finance | H3: Invoice extract from ERP
A4: WMS | B4: warehouse_shipments_2026_05.csv | C4: 46143.319 | D4: 786 | E4: 786 | F4: Loaded | G4: Distribution | H4: Shipment confirm extract
A5: Inventory ERP | B5: inventory_snapshot_2026_05.csv | C5: 46143.281 | D5: 100 | E5: 100 | F5: Loaded | G5: Supply Chain | H5: Inventory position snapshot
A6: Compliance | B6: compliance_rules_2026_05.csv | C6: 46143.335 | D6: 60 | E6: 60 | F6: Loaded | G6: Compliance | H6: State-specific rule file
A7: AR Subledger | B7: ar_aging_2026_05.csv | C7: 46143.344 | D7: 934 | E7: 934 | F7: Loaded | G7: Finance | H7: AR aging extract
A8: Customer Support | B8: support_cases_2026_05.csv | C8: 46143.354 | D8: 340 | E8: 340 | F8: Loaded | G8: Customer Success | H8: Ticket export
A9: Forecasting | B9: sales_forecast_2026_05.csv | C9: 46143.365 | D9: 1440 | E9: 1440 | F9: Loaded | G9: FP&A | H9: Forecast baseline file

Sheet customer_crosswalk
A1: crm_customer_id | B1: erp_customer_no | C1: wms_customer_id | D1: customer_name | E1: state | F1: account_status | G1: match_status | H1: notes
A2: DSP0001 | B2: CUST-0001 | C2: WMS100001 | D2: OR Account 0001 | E2: OR | F2: Inactive | G2: Review | H2: Name punctuation differs
A3: DSP0002 | B3: CUST-0002 | C3: WMS100002 | D3: WA Account 0002 | E3: WA | F3: Active | G3: Matched | H3: Standard cross-system mapping
A4: DSP0003 | B4: CUST-0003 | C4: WMS100003 | D4: CA Account 0003 | E4: CA | F4: Active | G4: Matched | H4: Standard cross-system mapping
A5: DSP0004 | B5: CUST-0004 | C5: WMS100004 | D5: CO Account 0004 | E5: CO | F5: Active | G5: Matched | H5: Standard cross-system mapping
A6: DSP0005 | B6: CUST-0005 | C6: WMS100005 | D6: AZ Account 0005 | E6: AZ | F6: Inactive | G6: Matched | H6: Standard cross-system mapping
A7: DSP0006 | B7: CUST-0006 | C7: WMS100006 | D7: NV Account 0006 | E7: NV | F7: Active | G7: Matched | H7: Standard cross-system mapping
A8: DSP0007 | B8: CUST-0007 | C8: WMS100007 | D8: IL Account 0007 | E8: IL | F8: Credit Hold | G8: Matched | H8: Standard cross-system mapping
A9: DSP0008 | B9: CUST-0008 | C9: WMS100008 | D9: MI Account 0008 | E9: MI | F9: Active | G9: Matched | H9: Standard cross-system mapping
A10: DSP0009 | B10: CUST-0009 | C10: WMS100009 | D10: MO Account 0009 | E10: MO | F10: Active | G10: Review | H10: ERP record inactive
A11: DSP0010 | B11: CUST-0010 | C11: WMS100010 | D11: NM Account 0010 | E11: NM | F11: Compliance Hold | G11: Matched | H11: Standard cross-system mapping
A12: DSP0011 | B12: CUST-0011 | C12: WMS100011 | D12: NY Account 0011 | E12: NY | F12: Active | G12: Matched | H12: Standard cross-system mapping
... A121: DSP0120 | B121: CUST-0120 | C121: WMS100120 | D121: OK Account 0120 | E121: OK | F121: Active | G121: Matched | H121: Standard cross-system mapping

Sheet field_mapping_crm_to_erp
A1: source_system | B1: source_field | C1: target_system | D1: target_field | E1: required | F1: transformation_rule | G1: qa_check
A2: Salesforce CRM | B2: order_id | C2: Business Central ERP | D2: sales_order_no | E2: Yes | F2: Trim, uppercase, preserve original ID | G2: No blank values; no duplicate active order IDs
A3: Salesforce CRM | B3: order_date | C3: Business Central ERP | D3: document_date | E3: Yes | F3: Parse to yyyy-mm-dd | G3: Must be valid date
A4: Salesforce CRM | B4: customer_id | C4: Business Central ERP | D4: customer_no | E4: Yes | F4: Trim, uppercase, match customer master | G4: Must exist in customer_lookup
A5: Salesforce CRM | B5: sku | C5: Business Central ERP | D5: item_no | E5: Yes | F5: Trim, uppercase, match item master | G5: Must exist in product_lookup
A6: Salesforce CRM | B6: qty_ordered | C6: Business Central ERP | D6: quantity | E6: Yes | F6: Cast to whole number | G6: Must be > 0
A7: Salesforce CRM | B7: unit_price | C7: Business Central ERP | D7: unit_price | E7: Yes | F7: Currency, 2 decimals | G7: Must be >= 0
A8: Salesforce CRM | B8: gross_sales | C8: Business Central ERP | D8: line_amount | E8: Yes | F8: qty_ordered * unit_price | G8: Recompute and compare
A9: Business Central ERP | B9: invoice_id | C9: Reporting | D9: invoice_key | E9: Yes | F9: Direct map | G9: No duplicate invoice_id
A10: Business Central ERP | B10: invoice_amount | C10: Reporting | D10: invoice_revenue | E10: Yes | F10: Currency, 2 decimals | G10: Compare to CRM gross_sales
A11: WMS / Inventory | B11: available_qty | C11: Reporting | D11: available_inventory | E11: Yes | F11: SUM available by sku | G11: Flag orders where inventory < order qty
A12: Returns/Credit Memo | B12: credit_amount | C12: Finance Reporting | D12: credit_amount | E12: No | F12: Negative amount for approved credits | G12: Amount should be <= 0

Sheet compliance_rules
A1: state | B1: rule_type | C1: rule_value | D1: severity | E1: owner_team | F1: business_meaning
A2: AZ | B2: customer_license_required | C2: Yes | D2: Critical | E2: Compliance | F2: Customer must have a valid state license before order ships
A3: AZ | B3: manifest_required | C3: Yes | D3: Critical | E3: Compliance | F3: Manifest ID required before shipment leaves warehouse
A4: CA | B4: customer_license_required | C4: Yes | D4: Critical | E4: Compliance | F4: Customer must have a valid state license before order ships
A5: CA | B5: manifest_required | C5: Yes | D5: Critical | E5: Compliance | F5: Manifest ID required before shipment leaves warehouse
A6: CO | B6: customer_license_required | C6: Yes | D6: Critical | E6: Compliance | F6: Customer must have a valid state license before order ships
A7: CO | B7: manifest_required | C7: Yes | D7: Critical | E7: Compliance | F7: Manifest ID required before shipment leaves warehouse
A8: IL | B8: customer_license_required | C8: Yes | D8: Critical | E8: Compliance | F8: Customer must have a valid state license before order ships
A9: IL | B9: manifest_required | C9: Yes | D9: Critical | E9: Compliance | F9: Manifest ID required before shipment leaves warehouse
A10: MI | B10: customer_license_required | C10: Yes | D10: Critical | E10: Compliance | F10: Customer must have a valid state license before order ships
A11: MI | B11: manifest_required | C11: Yes | D11: Critical | E11: Compliance | F11: Manifest ID required before shipment leaves warehouse
A12: MO | B12: customer_license_required | C12: Yes | D12: Critical | E12: Compliance | F12: Customer must have a valid state license before order ships
... A61: WA | B61: restricted_sku | C61: SKU0007 | D61: High | E61: Compliance | F61: SKU0007 requires review or is not approved in WA
A64: Rule ID | B64: Rule Category | C64: Rule Description | D64: Pass/Fail Conditions
A65: R01 | B65: License | C65: Customer must have a valid state-issued cannabis license | D65: License number format must be 10-15 characters, alphanumeric
A66: R02 | B66: Age Restriction | C66: Customer must be 21+ for adult-use products | D66: Birth year ≤ 2005 (for current year)
A67: R03 | B67: Product Category | C67: Medical-only products cannot go to adult-use customers | D67: If Product Type = "Medical Only" AND Channel = "Adult-Use" → FAIL
A68: R04 | B68: COA | C68: Certificate of Analysis must be attached and valid | D68: COA number must be present AND not expired (>30 days old)
A69: R05 | B69: Quantity Limit | C69: Adult-use purchase cannot exceed state daily limit | D69: Quantity > 28g (1oz) → FAIL for adult-use
A70: R06 | B70: METRC Tag | C70: Each product must have a valid METRC tag ID | D70: Tag ID format: 1-4 letters + 6-8 digits (e.g., ABCD123456)
A71: R07 | B71: Return Window | C71: Returns must be within state allowed days | D71: If Return = Yes AND Days Since Original Order > 14 → FAIL
A72: R08 | B72: License Status | C72: Customer license must be active, not suspended | D72: License Status must = "Active"

Sheet SOP

Sheet exception_log
A1: exception_id | B1: exception_type | C1: reference_id | D1: severity | E1: owner | F1: status | G1: created_date | H1: age_days | I1: notes
A2: EX000012 | B2: Missing Key | C2: ORD000117 | D2: Critical | E2: Sales Ops | F2: Open | G2: 46099 | H2: =TODAY()-G2 -> 59 | I2: Missing customer_id or sku
A3: EX000041 | B3: Missing Key | C3: ORD000372 | D3: Critical | E3: Sales Ops | F3: Open | G3: 46038 | H3: =TODAY()-G3 -> 120 | I3: Missing customer_id or sku
A4: EX000049 | B4: Missing Key | C4: ORD000495 | D4: Critical | E4: Sales Ops | F4: Open | G4: 46121 | H4: =TODAY()-G4 -> 37 | I4: Missing customer_id or sku
A5: EX000066 | B5: Missing Key | C5: ORD000730 | D5: Critical | E5: Sales Ops | F5: Open | G5: 46100 | H5: =TODAY()-G5 -> 58 | I5: Missing customer_id or sku
A6: EX000077 | B6: Missing Key | C6: ORD000938 | D6: Critical | E6: Sales Ops | F6: Open | G6: 46119 | H6: =TODAY()-G6 -> 39 | I6: Missing customer_id or sku
A7: EX000231 | B7: Orphan Invoice | C7: INV000920 | D7: Critical | E7: Finance | F7: Open | G7: 46107 | H7: =TODAY()-G7 -> 51 | I7: Invoice exists without matching CRM order
A8: EX000232 | B8: Orphan Invoice | C8: INV000921 | D8: Critical | E8: Finance | F8: Open | G8: 46136 | H8: =TODAY()-G8 -> 22 | I8: Invoice exists without matching CRM order
A9: EX000233 | B9: Orphan Invoice | C9: INV000922 | D9: Critical | E9: Finance | F9: Open | G9: 46143 | H9: =TODAY()-G9 -> 15 | I9: Invoice exists without matching CRM order
A10: EX000234 | B10: Orphan Invoice | C10: INV000923 | D10: Critical | E10: Finance | F10: Open | G10: 46057 | H10: =TODAY()-G10 -> 101 | I10: Invoice exists without matching CRM order
A11: EX000235 | B11: Orphan Invoice | C11: INV000924 | D11: Critical | E11: Finance | F11: Open | G11: 46060 | H11: =TODAY()-G11 -> 98 | I11: Invoice exists without matching CRM order
A12: EX000236 | B12: Orphan Invoice | C12: INV000925 | D12: Critical | E12: Finance | F12: Open | G12: 46103 | H12: =TODAY()-G12 -> 55 | I12: Invoice exists without matching CRM order
A13: EX000237 | B13: Orphan Invoice | C13: INV000926 | D13: Critical | E13: Finance | F13: Open | G13: 46051 | H13: =TODAY()-G13 -> 107 | I13: Invoice exists without matching CRM order
... A250: EX000230 | B250: Invoice Mismatch | C250: ORD001000 | D250: High | E250: Finance | F250: Closed | G250: 46096 | H250: =TODAY()-G250 -> 62 | I250: Qty or amount does not match CRM order

Sheet product_lookup
A1: sku | B1: product_name | C1: category | D1: standard_unit_price
A2: SKU0001 | B2: Blood Orange 1:1 Gummies | C2: Gummies | D2: 10
A3: SKU0002 | B3: Boysenberry 1:1:1 Gummies | C3: Gummies | D3: 10.5
A4: SKU0003 | B4: Elderberry 2:1 Gummies | C4: Gummies | D4: 11
A5: SKU0004 | B5: Grapefruit 1:1:1 Gummies | C5: Gummies | D5: 10.75
A6: SKU0005 | B6: Huckleberry THC Gummies | C6: Gummies | D6: 10.25
A7: SKU0006 | B7: Kiwi 1:1 Gummies | C7: Gummies | D7: 10.75
A8: SKU0007 | B8: Marionberry THC Gummies | C8: Gummies | D8: 10.25
A9: SKU0008 | B9: Peach 2:1 Gummies | C9: Gummies | D9: 10.75
A10: SKU0009 | B10: Pear 1:1 Gummies | C10: Gummies | D10: 11.25
A11: SKU0010 | B11: Pomegranate 1:1 Gummies | C11: Gummies | D11: 11
A12: SKU0011 | B12: Raspberry THC Gummies | C12: Gummies | D12: 10.5
A13: SKU0012 | B13: Sour Apple THC Gummies | C13: Gummies | D13: 10.5
... A21: SKU0020 | B21: Pineapple Sparkling Beverage | C21: Beverage | D21: 7.75

Sheet customer_lookup
A1: customer_id | B1: customer_name | C1: state | D1: account_status | E1: default_sales_rep
A2: DSP0040 | B2: CO Account 0040 | C2: CO | D2: Compliance Hold | E2: Alex
A3: DSP0060 | B3: OK Account 0060 | C3: OK | D3: Active | E3: Alex
A4: DSP0063 | B4: CA Account 0063 | C4: CA | D4: Active | E4: Alex
A5: DSP0064 | B5: CO Account 0064 | C5: CO | D5: Inactive | E5: Alex
A6: DSP0075 | B6: CA Account 0075 | C6: CA | D6: Credit Hold | E6: Alex
A7: DSP0078 | B7: NV Account 0078 | C7: NV | D7: Compliance Hold | E7: Alex
A8: DSP0094 | B8: NM Account 0094 | C8: NM | D8: Active | E8: Alex
A9: DSP0096 | B9: OK Account 0096 | C9: OK | D9: Compliance Hold | E9: Alex
A10: DSP0005 | B10: AZ Account 0005 | C10: AZ | D10: Inactive | E10: Avery
A11: DSP0011 | B11: NY Account 0011 | C11: NY | D11: Active | E11: Avery
A12: DSP0012 | B12: OK Account 0012 | C12: OK | D12: Active | E12: Avery
... A121: DSP0111 | B121: CA Account 0111 | C121: CA | D121: Inactive | E121: Taylor

Sheet pivot_practice
A1: Pivot Practice / Interview Drills
A2: Practice recreating summaries with PivotTables, VLOOKUP/INDEX-MATCH, conditional formatting, reconciliation checks, SUMIFS, COUNTIFS, and filters.
A4: Sales by State
A5: State | B5: CRM Gross Sales | C5: Order Count
A6: OR | B6: =SUMIF(crm_orders!$E:$E,A6,crm_orders!$L:$L) -> 45535.74 | C6: =COUNTIF(crm_orders!$E:$E,A6) -> 91
A7: WA | B7: =SUMIF(crm_orders!$E:$E,A7,crm_orders!$L:$L) -> 43595.82 | C7: =COUNTIF(crm_orders!$E:$E,A7) -> 95
A8: CA | B8: =SUMIF(crm_orders!$E:$E,A8,crm_orders!$L:$L) -> 38299.38 | C8: =COUNTIF(crm_orders!$E:$E,A8) -> 93
A9: CO | B9: =SUMIF(crm_orders!$E:$E,A9,crm_orders!$L:$L) -> 45658.44 | C9: =COUNTIF(crm_orders!$E:$E,A9) -> 83
A10: AZ | B10: =SUMIF(crm_orders!$E:$E,A10,crm_orders!$L:$L) -> 32817 | C10: =COUNTIF(crm_orders!$E:$E,A10) -> 77
A11: NV | B11: =SUMIF(crm_orders!$E:$E,A11,crm_orders!$L:$L) -> 37552.56 | C11: =COUNTIF(crm_orders!$E:$E,A11) -> 77
A12: IL | B12: =SUMIF(crm_orders!$E:$E,A12,crm_orders!$L:$L) -> 40055.82 | C12: =COUNTIF(crm_orders!$E:$E,A12) -> 96
A13: MI | B13: =SUMIF(crm_orders!$E:$E,A13,crm_orders!$L:$L) -> 45680.88 | C13: =COUNTIF(crm_orders!$E:$E,A13) -> 80
A14: MO | B14: =SUMIF(crm_orders!$E:$E,A14,crm_orders!$L:$L) -> 28381.14 | C14: =COUNTIF(crm_orders!$E:$E,A14) -> 67
A15: NM | B15: =SUMIF(crm_orders!$E:$E,A15,crm_orders!$L:$L) -> 31870.02 | C15: =COUNTIF(crm_orders!$E:$E,A15) -> 76
A16: NY | B16: =SUMIF(crm_orders!$E:$E,A16,crm_orders!$L:$L) -> 48070.62 | C16: =COUNTIF(crm_orders!$E:$E,A16) -> 99
A17: OK | B17: =SUMIF(crm_orders!$E:$E,A17,crm_orders!$L:$L) -> 32972.7 | C17: =COUNTIF(crm_orders!$E:$E,A17) -> 64
A20: Sales by Channel
A21: Channel | B21: CRM Gross Sales | C21: Order Count
A22: Wholesale | B22: =SUMIF(crm_orders!$G:$G,A22,crm_orders!$L:$L) -> 305021.1 | C22: =COUNTIF(crm_orders!$G:$G,A22) -> 663
A23: Retail | B23: =SUMIF(crm_orders!$G:$G,A23,crm_orders!$L:$L) -> 73396.8 | C23: =COUNTIF(crm_orders!$G:$G,A23) -> 151
A24: Distributor | B24: =SUMIF(crm_orders!$G:$G,A24,crm_orders!$L:$L) -> 93910.62 | C24: =COUNTIF(crm_orders!$G:$G,A24) -> 186
A27: Exceptions by Severity
A28: Severity | B28: Count
A29: Critical | B29: =COUNTIF(exception_log!$D:$D,A29) -> 24
A30: High | B30: =COUNTIF(exception_log!$D:$D,A30) -> 225
A31: Medium | B31: =COUNTIF(exception_log!$D:$D,A31) -> 0
A32: Low | B32: =COUNTIF(exception_log!$D:$D,A32) -> 0

Sheet interview_tasks
A1: Task # | B1: Skill | C1: Instruction | D1: Expected Output
A2: 1 | B2: Pivot Table | C2: Create a pivot showing CRM Gross Sales by state and channel. | D2: State/channel revenue summary
A3: 2 | B3: Reconciliation | C3: Filter erp_invoices for non-zero qty or amount variance. | D3: List of mismatched orders
A4: 3 | B4: Data Quality | C4: Find duplicate CRM order IDs. | D4: Duplicate order exception list
A5: 4 | B5: Data Quality | C5: Find orders missing customer_id or sku. | D5: Missing-key exception list
A6: 5 | B6: Inventory | C6: Filter crm_orders where inventory_flag = Short. | D6: Fulfillment risk list
A7: 6 | B7: Returns | C7: Summarize credit memo amount by reason_code and status. | D7: Credit memo impact table
A8: 7 | B8: SLA | C8: Use exception age_days to prioritize open issues. | D8: Aging backlog report
A9: 8 | B9: Lookup | C9: Use VLOOKUP or INDEX/MATCH to map customer state and sales rep. | D9: Customer attributes joined to CRM orders
A10: 9 | B10: Power Query | C10: Describe how you would clean CRM and ERP exports before reporting. | D10: Plain-English data prep workflow
A11: 10 | B11: Business Story | C11: Explain whether revenue is ready to publish or needs review. | D11: Recommendation based on controls

Sheet formulas

